Workbook

Sheet README
A1: Financial model - B1 circular ready-mix plant, Zuid-Holland (Rotterdam-Drechtsteden)
A2: Built by model/build_model.py from model/inputs.csv. Same model as model/model_core.py (checked: model/check_report.md).
A4: COLOUR CODE
A5: Blue font (yellow fill) = input you may change. Black font = live formula. Grey italic = value computed by model_core.py (not live). Green fill = check (must be 0).
A7: HOW IT WORKS
A8: 1. Inputs: every parameter has low/base/high. Cell Inputs!C3 picks the scenario (1 pessimistic, 2 base, 3 optimistic).
A9: Column H picks the column per parameter; column I is an OVERRIDE; column J is the ACTIVE value. Each active cell has a defined name = parameter name.
A10: Pessimistic = high column for cost-type inputs, low column for revenue-type inputs (column N 'direction'). 'fixed' inputs stay at base in all scenarios.
A11: 2. Capex -> Revenue -> Opex -> PnL -> CashFlow -> Valuation. Yearly sheets: column C = 2026 (t=0), D..M = 2027..2036 (t=1..10).
A12: 3. UnitEconomics: EUR/m3 stack for circular vs standard mix and plant average, for the year in UnitEconomics!C3.
A13: 4. Scenarios, Sensitivity, Viability criterion 4: computed with model_core.py (one model run per case) and pasted as values.
A15: KEY CONVENTIONS
... A36: model/inputs.csv, model/model_core.py, model/build_model.py, model/check_model.py, model/charts.py, model/charts/*.png, model/model_summary.md, model/check_report.md

Sheet Inputs
A1: Inputs - all model parameters (from model/inputs.csv) + option hooks
A3: ACTIVE SCENARIO (1 = pessimistic, 2 = base, 3 = optimistic) | C3: 2 | D3: =CHOOSE(scenario,"Pessimistic","Base","Optimistic") -> Base | F3: ACTIVE OPTION (0 = none; see Opt_Overview) | I3: 0
A4: Column H picks low/base/high per row: pessimistic uses column F, optimistic column G (1=low, 2=base, 3=high). Column I = OVERRIDE (leave empty = use H). Column O = value of the ACTIVE OPTION (cell I3, matrix on sheet Opt_Overview). Column J = ACTIVE value used by every formula (priority: Override > option > scenario; defined name = parameter name).
A5: parameter (= defined name) | B5: unit | C5: low | D5: base | E5: high | F5: pess. col | G5: opt. col | H5: scenario value | I5: OVERRIDE | J5: ACTIVE | K5: label | L5: source_ids | M5: notes | N5: direction | O5: option value
A6: price_basis | B6: - | C6: real 2026 EUR excl. VAT | D6: real 2026 EUR excl. VAT | E6: real 2026 EUR excl. VAT | F6: 2 | G6: 2 | H6: =INDEX(C6:E6,1,CHOOSE(scenario,F6,2,G6)) -> real 2026 EUR excl. VAT | J6: =IF(I6<>"",I6,IF(O6<>"",O6,H6)) -> real 2026 EUR excl. VAT | K6: ASSUMPTION | L6: plan.md | M6: All money in real 2026 EUR; general inflation = 0 in the model; only explicit real escalations below | N6: fixed | O6: =IFERROR(IF(option_sel=0,"",IF(LEN(INDEX(Opt_Overview!$C$7:$M$38,MATCH($A6,Opt_Overview!$A$7:$A$38,0),option_sel))=0,"",INDEX(Opt_Overview!$C$7:$M$38,MATCH($A6,Opt_Overview!$A$7:$A$38,0),option_sel))),"")
A7: general_inflation_real_model | B7: %/yr | C7: 0 | D7: 0 | E7: 0 | F7: 2 | G7: 2 | H7: =INDEX(C7:E7,1,CHOOSE(scenario,F7,2,G7)) -> 0 | J7: =IF(I7<>"",I7,IF(O7<>"",O7,H7)) -> 0 | K7: ASSUMPTION | L7: plan.md | M7: Real model. CBS CPI 2026 ~3.4% only used to convert older prices (TEC-44) | N7: fixed | O7: =IFERROR(IF(option_sel=0,"",IF(LEN(INDEX(Opt_Overview!$C$7:$M$38,MATCH($A7,Opt_Overview!$A$7:$A$38,0),option_sel))=0,"",INDEX(Opt_Overview!$C$7:$M$38,MATCH($A7,Opt_Overview!$A$7:$A$38,0),option_sel))),"")
A8: cpi_factor_2025_to_2026 | B8: x | C8: 1.02 | D8: 1.022 | E8: 1.03 | F8: 2 | G8: 2 | H8: =INDEX(C8:E8,1,CHOOSE(scenario,F8,2,G8)) -> 1.022 | J8: =IF(I8<>"",I8,IF(O8<>"",O8,H8)) -> 1.022 | K8: ESTIMATE | L8: MKT-54 | M8: CBS CPI Jan-2026 99.21 / Jan-2025 97.09 = 1.022; replaces placeholder A-CMP-15 | N8: fixed | O8: =IFERROR(IF(option_sel=0,"",IF(LEN(INDEX(Opt_Overview!$C$7:$M$38,MATCH($A8,Opt_Overview!$A$7:$A$38,0),option_sel))=0,"",INDEX(Opt_Overview!$C$7:$M$38,MATCH($A8,Opt_Overview!$A$7:$A$38,0),option_sel))),"")
A9: discount_rate_real | B9: % | C9: 6 | D9: 8 | E9: 10 | F9: 2 | G9: 2 | H9: =INDEX(C9:E9,1,CHOOSE(scenario,F9,2,G9)) -> 8 | J9: =IF(I9<>"",I9,IF(O9<>"",O9,H9)) -> 8 | K9: ASSUMPTION | L9: plan.md | M9: Client choice | N9: fixed | O9: =IFERROR(IF(option_sel=0,"",IF(LEN(INDEX(Opt_Overview!$C$7:$M$38,MATCH($A9,Opt_Overview!$A$7:$A$38,0),option_sel))=0,"",INDEX(Opt_Overview!$C$7:$M$38,MATCH($A9,Opt_Overview!$A$7:$A$38,0),option_sel))),"")
A10: tax_rate_vpb_low_bracket | B10: % | C10: 19 | D10: 19 | E10: 19 | F10: 2 | G10: 2 | H10: =INDEX(C10:E10,1,CHOOSE(scenario,F10,2,G10)) -> 19 | J10: =IF(I10<>"",I10,IF(O10<>"",O10,H10)) -> 19 | K10: ASSUMPTION | L10: A-CST-30 | M10: Dutch Vpb on first EUR 200k taxable profit (rate in force 2023-2026; not re-checked this session) | N10: fixed | O10: =IFERROR(IF(option_sel=0,"",IF(LEN(INDEX(Opt_Overview!$C$7:$M$38,MATCH($A10,Opt_Overview!$A$7:$A$38,0),option_sel))=0,"",INDEX(Opt_Overview!$C$7:$M$38,MATCH($A10,Opt_Overview!$A$7:$A$38,0),option_sel))),"")
A11: tax_vpb_low_bracket_limit | B11: EUR | C11: 200000 | D11: 200000 | E11: 200000 | F11: 2 | G11: 2 | H11: =INDEX(C11:E11,1,CHOOSE(scenario,F11,2,G11)) -> 200000 | J11: =IF(I11<>"",I11,IF(O11<>"",O11,H11)) -> 200000 | K11: ASSUMPTION | L11: A-CST-30 | N11: fixed | O11: =IFERROR(IF(option_sel=0,"",IF(LEN(INDEX(Opt_Overview!$C$7:$M$38,MATCH($A11,Opt_Overview!$A$7:$A$38,0),option_sel))=0,"",INDEX(Opt_Overview!$C$7:$M$38,MATCH($A11,Opt_Overview!$A$7:$A$38,0),option_sel))),"")
A12: tax_rate_vpb_high_bracket | B12: % | C12: 25.8 | D12: 25.8 | E12: 25.8 | F12: 2 | G12: 2 | H12: =INDEX(C12:E12,1,CHOOSE(scenario,F12,2,G12)) -> 25.8 | J12: =IF(I12<>"",I12,IF(O12<>"",O12,H12)) -> 25.8 | K12: ASSUMPTION | L12: A-CST-30 | M12: Above EUR 200k | N12: fixed | O12: =IFERROR(IF(option_sel=0,"",IF(LEN(INDEX(Opt_Overview!$C$7:$M$38,MATCH($A12,Opt_Overview!$A$7:$A$38,0),option_sel))=0,"",INDEX(Opt_Overview!$C$7:$M$38,MATCH($A12,Opt_Overview!$A$7:$A$38,0),option_sel))),"")
A13: mia_net_value_pct_eligible_capex | B13: % | C13: 7 | D13: 9.3 | E13: 11.6 | F13: 1 | G13: 3 | H13: =INDEX(C13:E13,1,CHOOSE(scenario,F13,2,G13)) -> 9.3 | J13: =IF(I13<>"",I13,IF(O13<>"",O13,H13)) -> 9.3 | K13: ESTIMATE | L13: A-POL-21 | M13: Only if taxable profit | N13: rev | O13: =IFERROR(IF(option_sel=0,"",IF(LEN(INDEX(Opt_Overview!$C$7:$M$38,MATCH($A13,Opt_Overview!$A$7:$A$38,0),option_sel))=0,"",INDEX(Opt_Overview!$C$7:$M$38,MATCH($A13,Opt_Overview!$A$7:$A$38,0),option_sel))),"")
A14: mia_eligible_share_of_capex | B14: % | C14: 0 | D14: 20 | E14: 50 | F14: 1 | G14: 3 | H14: =INDEX(C14:E14,1,CHOOSE(scenario,F14,2,G14)) -> 20 | J14: =IF(I14<>"",I14,IF(O14<>"",O14,H14)) -> 20 | K14: ASSUMPTION | L14: A-POL-22 | N14: rev | O14: =IFERROR(IF(option_sel=0,"",IF(LEN(INDEX(Opt_Overview!$C$7:$M$38,MATCH($A14,Opt_Overview!$A$7:$A$38,0),option_sel))=0,"",INDEX(Opt_Overview!$C$7:$M$38,MATCH($A14,Opt_Overview!$A$7:$A$38,0),option_sel))),"")
A15: grant_dei_veki_first_plant | B15: MEUR | C15: 0 | D15: 0.4 | E15: 1.5 | F15: 1 | G15: 3 | H15: =INDEX(C15:E15,1,CHOOSE(scenario,F15,2,G15)) -> 0.4 | J15: =IF(I15<>"",I15,IF(O15<>"",O15,H15)) -> 0.4 | K15: ASSUMPTION | L15: A-POL-24 | M15: Upside; competitive | N15: rev | O15: =IFERROR(IF(option_sel=0,"",IF(LEN(INDEX(Opt_Overview!$C$7:$M$38,MATCH($A15,Opt_Overview!$A$7:$A$38,0),option_sel))=0,"",INDEX(Opt_Overview!$C$7:$M$38,MATCH($A15,Opt_Overview!$A$7:$A$38,0),option_sel))),"")
A16: plant_capacity_hourly | B16: m3/h | C16: 100 | D16: 120 | E16: 150 | F16: 2 | G16: 2 | H16: =INDEX(C16:E16,1,CHOOSE(scenario,F16,2,G16)) -> 120 | J16: =IF(I16<>"",I16,IF(O16<>"",O16,H16)) -> 120 | K16: ESTIMATE | L16: A-TEC-23 | M16: Twin-shaft 3 m3 mixer | N16: fixed | O16: =IFERROR(IF(option_sel=0,"",IF(LEN(INDEX(Opt_Overview!$C$7:$M$38,MATCH($A16,Opt_Overview!$A$7:$A$38,0),option_sel))=0,"",INDEX(Opt_Overview!$C$7:$M$38,MATCH($A16,Opt_Overview!$A$7:$A$38,0),option_sel))),"")
A17: plant_capacity_theoretical | B17: m3/yr | C17: 200000 | D17: 240000 | E17: 280000 | F17: 2 | G17: 2 | H17: =INDEX(C17:E17,1,CHOOSE(scenario,F17,2,G17)) -> 240000 | J17: =IF(I17<>"",I17,IF(O17<>"",O17,H17)) -> 240000 | K17: ESTIMATE | L17: A-TEC-23 | M17: One shift ~2,000 h/yr | N17: fixed | O17: =IFERROR(IF(option_sel=0,"",IF(LEN(INDEX(Opt_Overview!$C$7:$M$38,MATCH($A17,Opt_Overview!$A$7:$A$38,0),option_sel))=0,"",INDEX(Opt_Overview!$C$7:$M$38,MATCH($A17,Opt_Overview!$A$7:$A$38,0),option_sel))),"")
A18: output_steady_state | B18: m3/yr | C18: 50000 | D18: 70000 | E18: 90000 | F18: 1 | G18: 3 | H18: =INDEX(C18:E18,1,CHOOSE(scenario,F18,2,G18)) -> 70000 | J18: =IF(I18<>"",I18,IF(O18<>"",O18,H18)) -> 70000 | K18: ESTIMATE | L18: A-TEC-24;A-MKT-32 | M18: Brief base 70k. MKT SOM base is 60k: test 60k. NL avg plant 33.7k m3 (CMP-43) | N18: rev | O18: =IFERROR(IF(option_sel=0,"",IF(LEN(INDEX(Opt_Overview!$C$7:$M$38,MATCH($A18,Opt_Overview!$A$7:$A$38,0),option_sel))=0,"",INDEX(Opt_Overview!$C$7:$M$38,MATCH($A18,Opt_Overview!$A$7:$A$38,0),option_sel))),"")
A19: ramp_year1_pct_of_steady | B19: % | C19: 35 | D19: 50 | E19: 65 | F19: 1 | G19: 3 | H19: =INDEX(C19:E19,1,CHOOSE(scenario,F19,2,G19)) -> 50 | J19: =IF(I19<>"",I19,IF(O19<>"",O19,H19)) -> 50 | K19: ASSUMPTION | L19: A-CST-01 | M19: First full operating year; base 35k m3 (TEC section 8) | N19: rev | O19: =IFERROR(IF(option_sel=0,"",IF(LEN(INDEX(Opt_Overview!$C$7:$M$38,MATCH($A19,Opt_Overview!$A$7:$A$38,0),option_sel))=0,"",INDEX(Opt_Overview!$C$7:$M$38,MATCH($A19,Opt_Overview!$A$7:$A$38,0),option_sel))),"")
A20: ramp_year2_pct_of_steady | B20: % | C20: 60 | D20: 79 | E20: 90 | F20: 1 | G20: 3 | H20: =INDEX(C20:E20,1,CHOOSE(scenario,F20,2,G20)) -> 79 | J20: =IF(I20<>"",I20,IF(O20<>"",O20,H20)) -> 79 | K20: ASSUMPTION | L20: A-CST-01 | M20: base 55k m3 | N20: rev | O20: =IFERROR(IF(option_sel=0,"",IF(LEN(INDEX(Opt_Overview!$C$7:$M$38,MATCH($A20,Opt_Overview!$A$7:$A$38,0),option_sel))=0,"",INDEX(Opt_Overview!$C$7:$M$38,MATCH($A20,Opt_Overview!$A$7:$A$38,0),option_sel))),"")
A21: ramp_year3plus_pct_of_steady | B21: % | C21: 85 | D21: 100 | E21: 100 | F21: 1 | G21: 3 | H21: =INDEX(C21:E21,1,CHOOSE(scenario,F21,2,G21)) -> 100 | J21: =IF(I21<>"",I21,IF(O21<>"",O21,H21)) -> 100 | K21: ASSUMPTION | L21: A-CST-01 | M21: base 70k m3 from year 3 | N21: rev | O21: =IFERROR(IF(option_sel=0,"",IF(LEN(INDEX(Opt_Overview!$C$7:$M$38,MATCH($A21,Opt_Overview!$A$7:$A$38,0),option_sel))=0,"",INDEX(Opt_Overview!$C$7:$M$38,MATCH($A21,Opt_Overview!$A$7:$A$38,0),option_sel))),"")
A22: circular_share_of_volume | B22: % | C22: 40 | D22: 60 | E22: 80 | F22: 1 | G22: 3 | H22: =INDEX(C22:E22,1,CHOOSE(scenario,F22,2,G22)) -> 60 | J22: =IF(I22<>"",I22,IF(O22<>"",O22,H22)) -> 60 | K22: ASSUMPTION | L22: A-TEC-44 | M22: Rest = standard CEM III/B mixes | N22: rev | O22: =IFERROR(IF(option_sel=0,"",IF(LEN(INDEX(Opt_Overview!$C$7:$M$38,MATCH($A22,Opt_Overview!$A$7:$A$38,0),option_sel))=0,"",INDEX(Opt_Overview!$C$7:$M$38,MATCH($A22,Opt_Overview!$A$7:$A$38,0),option_sel))),"")
A23: public_share_of_sales | B23: % | C23: 30 | D23: 40 | E23: 50 | F23: 1 | G23: 3 | H23: =INDEX(C23:E23,1,CHOOSE(scenario,F23,2,G23)) -> 40 | J23: =IF(I23<>"",I23,IF(O23<>"",O23,H23)) -> 40 | K23: ESTIMATE | L23: A-MKT-24 | M23: Public + housing corporations | N23: rev | O23: =IFERROR(IF(option_sel=0,"",IF(LEN(INDEX(Opt_Overview!$C$7:$M$38,MATCH($A23,Opt_Overview!$A$7:$A$38,0),option_sel))=0,"",INDEX(Opt_Overview!$C$7:$M$38,MATCH($A23,Opt_Overview!$A$7:$A$38,0),option_sel))),"")
A24: operating_days | B24: d/yr | C24: 220 | D24: 235 | E24: 250 | F24: 2 | G24: 2 | H24: =INDEX(C24:E24,1,CHOOSE(scenario,F24,2,G24)) -> 235 | J24: =IF(I24<>"",I24,IF(O24<>"",O24,H24)) -> 235 | K24: ASSUMPTION | L24: A-TEC-30 | N24: fixed | O24: =IFERROR(IF(option_sel=0,"",IF(LEN(INDEX(Opt_Overview!$C$7:$M$38,MATCH($A24,Opt_Overview!$A$7:$A$38,0),option_sel))=0,"",INDEX(Opt_Overview!$C$7:$M$38,MATCH($A24,Opt_Overview!$A$7:$A$38,0),option_sel))),"")
A25: capex_plant_equipment | B25: MEUR | C25: 3 | D25: 4 | E25: 5.5 | F25: 3 | G25: 1 | H25: =INDEX(C25:E25,1,CHOOSE(scenario,F25,2,G25)) -> 4 | J25: =IF(I25<>"",I25,IF(O25<>"",O25,H25)) -> 4 | K25: ASSUMPTION | L25: A-TEC-21;A-CST-02 | M25: Batching plant, mixer, 6-8 bins (3 RCA), 4-5 silos, covered RCA store, sprinklers, moisture probes, lab, wash-water recycling | N25: cost | O25: =IFERROR(IF(option_sel=0,"",IF(LEN(INDEX(Opt_Overview!$C$7:$M$38,MATCH($A25,Opt_Overview!$A$7:$A$38,0),option_sel))=0,"",INDEX(Opt_Overview!$C$7:$M$38,MATCH($A25,Opt_Overview!$A$7:$A$38,0),option_sel))),"")
A26: capex_site_prep_civil | B26: MEUR | C26: 0.6 | D26: 1 | E26: 1.8 | F26: 3 | G26: 1 | H26: =INDEX(C26:E26,1,CHOOSE(scenario,F26,2,G26)) -> 1 | J26: =IF(I26<>"",I26,IF(O26<>"",O26,H26)) -> 1 | K26: ASSUMPTION | L26: A-TEC-21;A-CST-02 | M26: Paving, foundations, drainage, grid connection, quay works. Sum with equipment+permits = 4.0/5.5/8.0 (brief) | N26: cost | O26: =IFERROR(IF(option_sel=0,"",IF(LEN(INDEX(Opt_Overview!$C$7:$M$38,MATCH($A26,Opt_Overview!$A$7:$A$38,0),option_sel))=0,"",INDEX(Opt_Overview!$C$7:$M$38,MATCH($A26,Opt_Overview!$A$7:$A$38,0),option_sel))),"")
A27: capex_permits_engineering | B27: MEUR | C27: 0.4 | D27: 0.5 | E27: 0.7 | F27: 3 | G27: 1 | H27: =INDEX(C27:E27,1,CHOOSE(scenario,F27,2,G27)) -> 0.5 | J27: =IF(I27<>"",I27,IF(O27<>"",O27,H27)) -> 0.5 | K27: ASSUMPTION | L27: A-CST-02 | M27: Permits, AERIUS/noise studies, engineering, start-up. Amortise 10 yr | N27: cost | O27: =IFERROR(IF(option_sel=0,"",IF(LEN(INDEX(Opt_Overview!$C$7:$M$38,MATCH($A27,Opt_Overview!$A$7:$A$38,0),option_sel))=0,"",INDEX(Opt_Overview!$C$7:$M$38,MATCH($A27,Opt_Overview!$A$7:$A$38,0),option_sel))),"")
A28: capex_lca_epd_one_off | B28: EUR | C28: 40000 | D28: 80000 | E28: 160000 | F28: 3 | G28: 1 | H28: =INDEX(C28:E28,1,CHOOSE(scenario,F28,2,G28)) -> 80000 | J28: =IF(I28<>"",I28,IF(O28<>"",O28,H28)) -> 80000 | K28: ASSUMPTION | L28: A-TEC-47;A-CST-03 | M28: 4 product families x EUR 20k (10-40k) | N28: cost | O28: =IFERROR(IF(option_sel=0,"",IF(LEN(INDEX(Opt_Overview!$C$7:$M$38,MATCH($A28,Opt_Overview!$A$7:$A$38,0),option_sel))=0,"",INDEX(Opt_Overview!$C$7:$M$38,MATCH($A28,Opt_Overview!$A$7:$A$38,0),option_sel))),"")
A29: capex_preopening_costs | B29: EUR | C29: 200000 | D29: 300000 | E29: 500000 | F29: 3 | G29: 1 | H29: =INDEX(C29:E29,1,CHOOSE(scenario,F29,2,G29)) -> 300000 | J29: =IF(I29<>"",I29,IF(O29<>"",O29,H29)) -> 300000 | K29: ASSUMPTION | L29: A-CST-04 | M29: Hiring before opening, trial mixes, initial type testing for KOMO | N29: cost | O29: =IFERROR(IF(option_sel=0,"",IF(LEN(INDEX(Opt_Overview!$C$7:$M$38,MATCH($A29,Opt_Overview!$A$7:$A$38,0),option_sel))=0,"",INDEX(Opt_Overview!$C$7:$M$38,MATCH($A29,Opt_Overview!$A$7:$A$38,0),option_sel))),"")
A30: capex_truck_mixers_option | B30: MEUR | C30: 1 | D30: 1.08 | E30: 1.2 | F30: 2 | G30: 2 | H30: =INDEX(C30:E30,1,CHOOSE(scenario,F30,2,G30)) -> 1.08 | J30: =IF(I30<>"",I30,IF(O30<>"",O30,H30)) -> 1.08 | K30: ESTIMATE | L30: A-TEC-31 | M30: Only if trucks bought (8 x EUR 135k); base = subcontracted | N30: fixed | O30: =IFERROR(IF(option_sel=0,"",IF(LEN(INDEX(Opt_Overview!$C$7:$M$38,MATCH($A30,Opt_Overview!$A$7:$A$38,0),option_sel))=0,"",INDEX(Opt_Overview!$C$7:$M$38,MATCH($A30,Opt_Overview!$A$7:$A$38,0),option_sel))),"")
A31: land_purchase | B31: MEUR | C31: 0 | D31: 0 | E31: 0 | F31: 2 | G31: 2 | H31: =INDEX(C31:E31,1,CHOOSE(scenario,F31,2,G31)) -> 0 | J31: =IF(I31<>"",I31,IF(O31<>"",O31,H31)) -> 0 | K31: ASSUMPTION | L31: A-CST-05 | M31: Land leased in base case | N31: fixed | O31: =IFERROR(IF(option_sel=0,"",IF(LEN(INDEX(Opt_Overview!$C$7:$M$38,MATCH($A31,Opt_Overview!$A$7:$A$38,0),option_sel))=0,"",INDEX(Opt_Overview!$C$7:$M$38,MATCH($A31,Opt_Overview!$A$7:$A$38,0),option_sel))),"")
A32: lifetime_plant_equipment | B32: yr | C32: 20 | D32: 25 | E32: 30 | F32: 2 | G32: 2 | H32: =INDEX(C32:E32,1,CHOOSE(scenario,F32,2,G32)) -> 25 | J32: =IF(I32<>"",I32,IF(O32<>"",O32,H32)) -> 25 | K32: ASSUMPTION | L32: A-TEC-39 | N32: fixed | O32: =IFERROR(IF(option_sel=0,"",IF(LEN(INDEX(Opt_Overview!$C$7:$M$38,MATCH($A32,Opt_Overview!$A$7:$A$38,0),option_sel))=0,"",INDEX(Opt_Overview!$C$7:$M$38,MATCH($A32,Opt_Overview!$A$7:$A$38,0),option_sel))),"")
A33: lifetime_civil_works | B33: yr | C33: 20 | D33: 25 | E33: 30 | F33: 2 | G33: 2 | H33: =INDEX(C33:E33,1,CHOOSE(scenario,F33,2,G33)) -> 25 | J33: =IF(I33<>"",I33,IF(O33<>"",O33,H33)) -> 25 | K33: ASSUMPTION | L33: A-TEC-39 | N33: fixed | O33: =IFERROR(IF(option_sel=0,"",IF(LEN(INDEX(Opt_Overview!$C$7:$M$38,MATCH($A33,Opt_Overview!$A$7:$A$38,0),option_sel))=0,"",INDEX(Opt_Overview!$C$7:$M$38,MATCH($A33,Opt_Overview!$A$7:$A$38,0),option_sel))),"")
A34: lifetime_permits_engineering | B34: yr | C34: 10 | D34: 10 | E34: 10 | F34: 2 | G34: 2 | H34: =INDEX(C34:E34,1,CHOOSE(scenario,F34,2,G34)) -> 10 | J34: =IF(I34<>"",I34,IF(O34<>"",O34,H34)) -> 10 | K34: ASSUMPTION | L34: A-CST-02 | N34: fixed | O34: =IFERROR(IF(option_sel=0,"",IF(LEN(INDEX(Opt_Overview!$C$7:$M$38,MATCH($A34,Opt_Overview!$A$7:$A$38,0),option_sel))=0,"",INDEX(Opt_Overview!$C$7:$M$38,MATCH($A34,Opt_Overview!$A$7:$A$38,0),option_sel))),"")
A35: salvage_value_yr10_pct_of_plant_civil_capex | B35: % | C35: 10 | D35: 25 | E35: 40 | F35: 1 | G35: 3 | H35: =INDEX(C35:E35,1,CHOOSE(scenario,F35,2,G35)) -> 25 | J35: =IF(I35<>"",I35,IF(O35<>"",O35,H35)) -> 25 | K35: ASSUMPTION | L35: A-CST-06 | M35: Terminal value = salvage only (plan 2.1). Used batching plants sell well below book value | N35: rev | O35: =IFERROR(IF(option_sel=0,"",IF(LEN(INDEX(Opt_Overview!$C$7:$M$38,MATCH($A35,Opt_Overview!$A$7:$A$38,0),option_sel))=0,"",INDEX(Opt_Overview!$C$7:$M$38,MATCH($A35,Opt_Overview!$A$7:$A$38,0),option_sel))),"")
A36: working_capital_receivable_days | B36: d | C36: 45 | D36: 60 | E36: 75 | F36: 3 | G36: 1 | H36: =INDEX(C36:E36,1,CHOOSE(scenario,F36,2,G36)) -> 60 | J36: =IF(I36<>"",I36,IF(O36<>"",O36,H36)) -> 60 | K36: ASSUMPTION | L36: A-CST-07 | M36: Dutch construction payment practice; contractors pay slowly | N36: cost | O36: =IFERROR(IF(option_sel=0,"",IF(LEN(INDEX(Opt_Overview!$C$7:$M$38,MATCH($A36,Opt_Overview!$A$7:$A$38,0),option_sel))=0,"",INDEX(Opt_Overview!$C$7:$M$38,MATCH($A36,Opt_Overview!$A$7:$A$38,0),option_sel))),"")
A37: working_capital_payable_days | B37: d | C37: 21 | D37: 30 | E37: 45 | F37: 1 | G37: 3 | H37: =INDEX(C37:E37,1,CHOOSE(scenario,F37,2,G37)) -> 30 | J37: =IF(I37<>"",I37,IF(O37<>"",O37,H37)) -> 30 | K37: ASSUMPTION | L37: A-CST-07 | M37: Cement and aggregate suppliers | N37: rev | O37: =IFERROR(IF(option_sel=0,"",IF(LEN(INDEX(Opt_Overview!$C$7:$M$38,MATCH($A37,Opt_Overview!$A$7:$A$38,0),option_sel))=0,"",INDEX(Opt_Overview!$C$7:$M$38,MATCH($A37,Opt_Overview!$A$7:$A$38,0),option_sel))),"")
A38: working_capital_inventory_days | B38: d | C38: 7 | D38: 10 | E38: 15 | F38: 3 | G38: 1 | H38: =INDEX(C38:E38,1,CHOOSE(scenario,F38,2,G38)) -> 10 | J38: =IF(I38<>"",I38,IF(O38<>"",O38,H38)) -> 10 | K38: ASSUMPTION | L38: A-CST-07 | M38: Of raw material cost | N38: cost | O38: =IFERROR(IF(option_sel=0,"",IF(LEN(INDEX(Opt_Overview!$C$7:$M$38,MATCH($A38,Opt_Overview!$A$7:$A$38,0),option_sel))=0,"",INDEX(Opt_Overview!$C$7:$M$38,MATCH($A38,Opt_Overview!$A$7:$A$38,0),option_sel))),"")
A39: sustaining_capex_pct_of_capex | B39: %/yr | C39: 0.5 | D39: 1 | E39: 2 | F39: 3 | G39: 1 | H39: =INDEX(C39:E39,1,CHOOSE(scenario,F39,2,G39)) -> 1 | J39: =IF(I39<>"",I39,IF(O39<>"",O39,H39)) -> 1 | K39: ASSUMPTION | L39: A-CST-08 | M39: On top of maintenance opex; mixer liners and wear parts are in maintenance | N39: cost | O39: =IFERROR(IF(option_sel=0,"",IF(LEN(INDEX(Opt_Overview!$C$7:$M$38,MATCH($A39,Opt_Overview!$A$7:$A$38,0),option_sel))=0,"",INDEX(Opt_Overview!$C$7:$M$38,MATCH($A39,Opt_Overview!$A$7:$A$38,0),option_sel))),"")
A40: mix_circ_binder | B40: kg/m3 | C40: 330 | D40: 345 | E40: 360 | F40: 2 | G40: 2 | H40: =INDEX(C40:E40,1,CHOOSE(scenario,F40,2,G40)) -> 345 | J40: =IF(I40<>"",I40,IF(O40<>"",O40,H40)) -> 345 | K40: ESTIMATE | L40: TEC-04;A-TEC-11;A-TEC-12;A-CST-09 | M40: CEM III/B | N40: fixed | O40: =IFERROR(IF(option_sel=0,"",IF(LEN(INDEX(Opt_Overview!$C$7:$M$38,MATCH($A40,Opt_Overview!$A$7:$A$38,0),option_sel))=0,"",INDEX(Opt_Overview!$C$7:$M$38,MATCH($A40,Opt_Overview!$A$7:$A$38,0),option_sel))),"")
A41: mix_circ_gravel | B41: kg/m3 | C41: 870 | D41: 620 | E41: 620 | F41: 2 | G41: 2 | H41: =INDEX(C41:E41,1,CHOOSE(scenario,F41,2,G41)) -> 620 | J41: =IF(I41<>"",I41,IF(O41<>"",O41,H41)) -> 620 | K41: ESTIMATE | L41: TEC-04;A-TEC-11;A-TEC-12;A-CST-09 | M41: Circular low = 30% RCA (V/V); base/high = 50% (CUR 112) | N41: fixed | O41: =IFERROR(IF(option_sel=0,"",IF(LEN(INDEX(Opt_Overview!$C$7:$M$38,MATCH($A41,Opt_Overview!$A$7:$A$38,0),option_sel))=0,"",INDEX(Opt_Overview!$C$7:$M$38,MATCH($A41,Opt_Overview!$A$7:$A$38,0),option_sel))),"")
A42: mix_circ_rca_coarse | B42: kg/m3 | C42: 330 | D42: 560 | E42: 560 | F42: 2 | G42: 2 | H42: =INDEX(C42:E42,1,CHOOSE(scenario,F42,2,G42)) -> 560 | J42: =IF(I42<>"",I42,IF(O42<>"",O42,H42)) -> 560 | K42: ESTIMATE | L42: TEC-04;A-TEC-11;A-TEC-12;A-CST-09 | M42: Type A1 betongranulaat 4/16-4/22, SSD density ~2,450 | N42: fixed | O42: =IFERROR(IF(option_sel=0,"",IF(LEN(INDEX(Opt_Overview!$C$7:$M$38,MATCH($A42,Opt_Overview!$A$7:$A$38,0),option_sel))=0,"",INDEX(Opt_Overview!$C$7:$M$38,MATCH($A42,Opt_Overview!$A$7:$A$38,0),option_sel))),"")
A43: mix_circ_sand | B43: kg/m3 | C43: 630 | D43: 630 | E43: 480 | F43: 2 | G43: 2 | H43: =INDEX(C43:E43,1,CHOOSE(scenario,F43,2,G43)) -> 630 | J43: =IF(I43<>"",I43,IF(O43<>"",O43,H43)) -> 630 | K43: ESTIMATE | L43: TEC-04;A-TEC-11;A-TEC-12;A-CST-09 | M43: High-circular variant: 480 sand + 150 recycled sand | N43: fixed | O43: =IFERROR(IF(option_sel=0,"",IF(LEN(INDEX(Opt_Overview!$C$7:$M$38,MATCH($A43,Opt_Overview!$A$7:$A$38,0),option_sel))=0,"",INDEX(Opt_Overview!$C$7:$M$38,MATCH($A43,Opt_Overview!$A$7:$A$38,0),option_sel))),"")
A44: mix_circ_rca_fine | B44: kg/m3 | C44: 0 | D44: 0 | E44: 150 | F44: 2 | G44: 2 | H44: =INDEX(C44:E44,1,CHOOSE(scenario,F44,2,G44)) -> 0 | J44: =IF(I44<>"",I44,IF(O44<>"",O44,H44)) -> 0 | K44: ESTIMATE | L44: TEC-04;A-TEC-11;A-TEC-12;A-CST-09 | M44: Recycled 0/4 only in high-circular variant (CROW-CUR 127) | N44: fixed | O44: =IFERROR(IF(option_sel=0,"",IF(LEN(INDEX(Opt_Overview!$C$7:$M$38,MATCH($A44,Opt_Overview!$A$7:$A$38,0),option_sel))=0,"",INDEX(Opt_Overview!$C$7:$M$38,MATCH($A44,Opt_Overview!$A$7:$A$38,0),option_sel))),"")
A45: mix_circ_water_effective | B45: l/m3 | C45: 165 | D45: 165 | E45: 165 | F45: 2 | G45: 2 | H45: =INDEX(C45:E45,1,CHOOSE(scenario,F45,2,G45)) -> 165 | J45: =IF(I45<>"",I45,IF(O45<>"",O45,H45)) -> 165 | K45: ESTIMATE | L45: TEC-04;A-TEC-11;A-TEC-12;A-CST-09 | N45: fixed | O45: =IFERROR(IF(option_sel=0,"",IF(LEN(INDEX(Opt_Overview!$C$7:$M$38,MATCH($A45,Opt_Overview!$A$7:$A$38,0),option_sel))=0,"",INDEX(Opt_Overview!$C$7:$M$38,MATCH($A45,Opt_Overview!$A$7:$A$38,0),option_sel))),"")
A46: mix_circ_water_absorption | B46: l/m3 | C46: 15 | D46: 28 | E46: 40 | F46: 3 | G46: 1 | H46: =INDEX(C46:E46,1,CHOOSE(scenario,F46,2,G46)) -> 28 | J46: =IF(I46<>"",I46,IF(O46<>"",O46,H46)) -> 28 | K46: ESTIMATE | L46: A-TEC-12 | M46: Pre-wetting/absorption water for RCA, not in w/c | N46: cost | O46: =IFERROR(IF(option_sel=0,"",IF(LEN(INDEX(Opt_Overview!$C$7:$M$38,MATCH($A46,Opt_Overview!$A$7:$A$38,0),option_sel))=0,"",INDEX(Opt_Overview!$C$7:$M$38,MATCH($A46,Opt_Overview!$A$7:$A$38,0),option_sel))),"")
A47: mix_circ_superplasticiser_pct_binder | B47: % | C47: 0.7 | D47: 0.9 | E47: 1.2 | F47: 3 | G47: 1 | H47: =INDEX(C47:E47,1,CHOOSE(scenario,F47,2,G47)) -> 0.9 | J47: =IF(I47<>"",I47,IF(O47<>"",O47,H47)) -> 0.9 | K47: ASSUMPTION | L47: CST-12;A-TEC-13;A-CST-10 | M47: Liquid PCE; circular = reference +0.2 pt (0-0.5) | N47: cost | O47: =IFERROR(IF(option_sel=0,"",IF(LEN(INDEX(Opt_Overview!$C$7:$M$38,MATCH($A47,Opt_Overview!$A$7:$A$38,0),option_sel))=0,"",INDEX(Opt_Overview!$C$7:$M$38,MATCH($A47,Opt_Overview!$A$7:$A$38,0),option_sel))),"")
A48: mix_conv_cem3b_binder | B48: kg/m3 | C48: 330 | D48: 330 | E48: 330 | F48: 2 | G48: 2 | H48: =INDEX(C48:E48,1,CHOOSE(scenario,F48,2,G48)) -> 330 | J48: =IF(I48<>"",I48,IF(O48<>"",O48,H48)) -> 330 | K48: VERIFIED | L48: TEC-04 | M48: CEM III/B | N48: fixed | O48: =IFERROR(IF(option_sel=0,"",IF(LEN(INDEX(Opt_Overview!$C$7:$M$38,MATCH($A48,Opt_Overview!$A$7:$A$38,0),option_sel))=0,"",INDEX(Opt_Overview!$C$7:$M$38,MATCH($A48,Opt_Overview!$A$7:$A$38,0),option_sel))),"")
A49: mix_conv_cem3b_gravel | B49: kg/m3 | C49: 1241 | D49: 1241 | E49: 1241 | F49: 2 | G49: 2 | H49: =INDEX(C49:E49,1,CHOOSE(scenario,F49,2,G49)) -> 1241 | J49: =IF(I49<>"",I49,IF(O49<>"",O49,H49)) -> 1241 | K49: VERIFIED | L49: TEC-04 | M49: Circular low = 30% RCA (V/V); base/high = 50% (CUR 112) | N49: fixed | O49: =IFERROR(IF(option_sel=0,"",IF(LEN(INDEX(Opt_Overview!$C$7:$M$38,MATCH($A49,Opt_Overview!$A$7:$A$38,0),option_sel))=0,"",INDEX(Opt_Overview!$C$7:$M$38,MATCH($A49,Opt_Overview!$A$7:$A$38,0),option_sel))),"")
A50: mix_conv_cem3b_rca_coarse | B50: kg/m3 | C50: 0 | D50: 0 | E50: 0 | F50: 2 | G50: 2 | H50: =INDEX(C50:E50,1,CHOOSE(scenario,F50,2,G50)) -> 0 | J50: =IF(I50<>"",I50,IF(O50<>"",O50,H50)) -> 0 | K50: VERIFIED | L50: TEC-04 | M50: Type A1 betongranulaat 4/16-4/22, SSD density ~2,450 | N50: fixed | O50: =IFERROR(IF(option_sel=0,"",IF(LEN(INDEX(Opt_Overview!$C$7:$M$38,MATCH($A50,Opt_Overview!$A$7:$A$38,0),option_sel))=0,"",INDEX(Opt_Overview!$C$7:$M$38,MATCH($A50,Opt_Overview!$A$7:$A$38,0),option_sel))),"")
A51: mix_conv_cem3b_sand | B51: kg/m3 | C51: 639 | D51: 639 | E51: 639 | F51: 2 | G51: 2 | H51: =INDEX(C51:E51,1,CHOOSE(scenario,F51,2,G51)) -> 639 | J51: =IF(I51<>"",I51,IF(O51<>"",O51,H51)) -> 639 | K51: VERIFIED | L51: TEC-04 | M51: High-circular variant: 480 sand + 150 recycled sand | N51: fixed | O51: =IFERROR(IF(option_sel=0,"",IF(LEN(INDEX(Opt_Overview!$C$7:$M$38,MATCH($A51,Opt_Overview!$A$7:$A$38,0),option_sel))=0,"",INDEX(Opt_Overview!$C$7:$M$38,MATCH($A51,Opt_Overview!$A$7:$A$38,0),option_sel))),"")
A52: mix_conv_cem3b_rca_fine | B52: kg/m3 | C52: 0 | D52: 0 | E52: 0 | F52: 2 | G52: 2 | H52: =INDEX(C52:E52,1,CHOOSE(scenario,F52,2,G52)) -> 0 | J52: =IF(I52<>"",I52,IF(O52<>"",O52,H52)) -> 0 | K52: VERIFIED | L52: TEC-04 | M52: Recycled 0/4 only in high-circular variant (CROW-CUR 127) | N52: fixed | O52: =IFERROR(IF(option_sel=0,"",IF(LEN(INDEX(Opt_Overview!$C$7:$M$38,MATCH($A52,Opt_Overview!$A$7:$A$38,0),option_sel))=0,"",INDEX(Opt_Overview!$C$7:$M$38,MATCH($A52,Opt_Overview!$A$7:$A$38,0),option_sel))),"")
A53: mix_conv_cem3b_water_effective | B53: l/m3 | C53: 165 | D53: 165 | E53: 165 | F53: 2 | G53: 2 | H53: =INDEX(C53:E53,1,CHOOSE(scenario,F53,2,G53)) -> 165 | J53: =IF(I53<>"",I53,IF(O53<>"",O53,H53)) -> 165 | K53: VERIFIED | L53: TEC-04 | N53: fixed | O53: =IFERROR(IF(option_sel=0,"",IF(LEN(INDEX(Opt_Overview!$C$7:$M$38,MATCH($A53,Opt_Overview!$A$7:$A$38,0),option_sel))=0,"",INDEX(Opt_Overview!$C$7:$M$38,MATCH($A53,Opt_Overview!$A$7:$A$38,0),option_sel))),"")
A54: mix_conv_cem3b_water_absorption | B54: l/m3 | C54: 0 | D54: 0 | E54: 0 | F54: 2 | G54: 2 | H54: =INDEX(C54:E54,1,CHOOSE(scenario,F54,2,G54)) -> 0 | J54: =IF(I54<>"",I54,IF(O54<>"",O54,H54)) -> 0 | K54: VERIFIED | L54: A-TEC-12 | M54: Pre-wetting/absorption water for RCA, not in w/c | N54: fixed | O54: =IFERROR(IF(option_sel=0,"",IF(LEN(INDEX(Opt_Overview!$C$7:$M$38,MATCH($A54,Opt_Overview!$A$7:$A$38,0),option_sel))=0,"",INDEX(Opt_Overview!$C$7:$M$38,MATCH($A54,Opt_Overview!$A$7:$A$38,0),option_sel))),"")
A55: mix_conv_cem3b_superplasticiser_pct_binder | B55: % | C55: 0.5 | D55: 0.7 | E55: 0.9 | F55: 3 | G55: 1 | H55: =INDEX(C55:E55,1,CHOOSE(scenario,F55,2,G55)) -> 0.7 | J55: =IF(I55<>"",I55,IF(O55<>"",O55,H55)) -> 0.7 | K55: ASSUMPTION | L55: CST-12;A-TEC-13;A-CST-10 | M55: Liquid PCE; circular = reference +0.2 pt (0-0.5) | N55: cost | O55: =IFERROR(IF(option_sel=0,"",IF(LEN(INDEX(Opt_Overview!$C$7:$M$38,MATCH($A55,Opt_Overview!$A$7:$A$38,0),option_sel))=0,"",INDEX(Opt_Overview!$C$7:$M$38,MATCH($A55,Opt_Overview!$A$7:$A$38,0),option_sel))),"")
A56: mix_conv_cem1_binder | B56: kg/m3 | C56: 320 | D56: 320 | E56: 320 | F56: 2 | G56: 2 | H56: =INDEX(C56:E56,1,CHOOSE(scenario,F56,2,G56)) -> 320 | J56: =IF(I56<>"",I56,IF(O56<>"",O56,H56)) -> 320 | K56: VERIFIED | L56: TEC-04 | M56: CEM I 52.5R. NMD reference | N56: fixed | O56: =IFERROR(IF(option_sel=0,"",IF(LEN(INDEX(Opt_Overview!$C$7:$M$38,MATCH($A56,Opt_Overview!$A$7:$A$38,0),option_sel))=0,"",INDEX(Opt_Overview!$C$7:$M$38,MATCH($A56,Opt_Overview!$A$7:$A$38,0),option_sel))),"")
A57: mix_conv_cem1_gravel | B57: kg/m3 | C57: 1241 | D57: 1241 | E57: 1241 | F57: 2 | G57: 2 | H57: =INDEX(C57:E57,1,CHOOSE(scenario,F57,2,G57)) -> 1241 | J57: =IF(I57<>"",I57,IF(O57<>"",O57,H57)) -> 1241 | K57: VERIFIED | L57: TEC-04 | M57: Circular low = 30% RCA (V/V); base/high = 50% (CUR 112) | N57: fixed | O57: =IFERROR(IF(option_sel=0,"",IF(LEN(INDEX(Opt_Overview!$C$7:$M$38,MATCH($A57,Opt_Overview!$A$7:$A$38,0),option_sel))=0,"",INDEX(Opt_Overview!$C$7:$M$38,MATCH($A57,Opt_Overview!$A$7:$A$38,0),option_sel))),"")
A58: mix_conv_cem1_rca_coarse | B58: kg/m3 | C58: 0 | D58: 0 | E58: 0 | F58: 2 | G58: 2 | H58: =INDEX(C58:E58,1,CHOOSE(scenario,F58,2,G58)) -> 0 | J58: =IF(I58<>"",I58,IF(O58<>"",O58,H58)) -> 0 | K58: VERIFIED | L58: TEC-04 | M58: Type A1 betongranulaat 4/16-4/22, SSD density ~2,450 | N58: fixed | O58: =IFERROR(IF(option_sel=0,"",IF(LEN(INDEX(Opt_Overview!$C$7:$M$38,MATCH($A58,Opt_Overview!$A$7:$A$38,0),option_sel))=0,"",INDEX(Opt_Overview!$C$7:$M$38,MATCH($A58,Opt_Overview!$A$7:$A$38,0),option_sel))),"")
A59: mix_conv_cem1_sand | B59: kg/m3 | C59: 639 | D59: 639 | E59: 639 | F59: 2 | G59: 2 | H59: =INDEX(C59:E59,1,CHOOSE(scenario,F59,2,G59)) -> 639 | J59: =IF(I59<>"",I59,IF(O59<>"",O59,H59)) -> 639 | K59: VERIFIED | L59: TEC-04 | M59: High-circular variant: 480 sand + 150 recycled sand | N59: fixed | O59: =IFERROR(IF(option_sel=0,"",IF(LEN(INDEX(Opt_Overview!$C$7:$M$38,MATCH($A59,Opt_Overview!$A$7:$A$38,0),option_sel))=0,"",INDEX(Opt_Overview!$C$7:$M$38,MATCH($A59,Opt_Overview!$A$7:$A$38,0),option_sel))),"")
A60: mix_conv_cem1_rca_fine | B60: kg/m3 | C60: 0 | D60: 0 | E60: 0 | F60: 2 | G60: 2 | H60: =INDEX(C60:E60,1,CHOOSE(scenario,F60,2,G60)) -> 0 | J60: =IF(I60<>"",I60,IF(O60<>"",O60,H60)) -> 0 | K60: VERIFIED | L60: TEC-04 | M60: Recycled 0/4 only in high-circular variant (CROW-CUR 127) | N60: fixed | O60: =IFERROR(IF(option_sel=0,"",IF(LEN(INDEX(Opt_Overview!$C$7:$M$38,MATCH($A60,Opt_Overview!$A$7:$A$38,0),option_sel))=0,"",INDEX(Opt_Overview!$C$7:$M$38,MATCH($A60,Opt_Overview!$A$7:$A$38,0),option_sel))),"")
A61: mix_conv_cem1_water_effective | B61: l/m3 | C61: 165 | D61: 165 | E61: 165 | F61: 2 | G61: 2 | H61: =INDEX(C61:E61,1,CHOOSE(scenario,F61,2,G61)) -> 165 | J61: =IF(I61<>"",I61,IF(O61<>"",O61,H61)) -> 165 | K61: VERIFIED | L61: TEC-04 | N61: fixed | O61: =IFERROR(IF(option_sel=0,"",IF(LEN(INDEX(Opt_Overview!$C$7:$M$38,MATCH($A61,Opt_Overview!$A$7:$A$38,0),option_sel))=0,"",INDEX(Opt_Overview!$C$7:$M$38,MATCH($A61,Opt_Overview!$A$7:$A$38,0),option_sel))),"")
A62: mix_conv_cem1_water_absorption | B62: l/m3 | C62: 0 | D62: 0 | E62: 0 | F62: 2 | G62: 2 | H62: =INDEX(C62:E62,1,CHOOSE(scenario,F62,2,G62)) -> 0 | J62: =IF(I62<>"",I62,IF(O62<>"",O62,H62)) -> 0 | K62: VERIFIED | L62: A-TEC-12 | M62: Pre-wetting/absorption water for RCA, not in w/c | N62: fixed | O62: =IFERROR(IF(option_sel=0,"",IF(LEN(INDEX(Opt_Overview!$C$7:$M$38,MATCH($A62,Opt_Overview!$A$7:$A$38,0),option_sel))=0,"",INDEX(Opt_Overview!$C$7:$M$38,MATCH($A62,Opt_Overview!$A$7:$A$38,0),option_sel))),"")
A63: mix_conv_cem1_superplasticiser_pct_binder | B63: % | C63: 0.5 | D63: 0.7 | E63: 0.9 | F63: 2 | G63: 2 | H63: =INDEX(C63:E63,1,CHOOSE(scenario,F63,2,G63)) -> 0.7 | J63: =IF(I63<>"",I63,IF(O63<>"",O63,H63)) -> 0.7 | K63: ASSUMPTION | L63: CST-12;A-TEC-13;A-CST-10 | M63: Liquid PCE; circular = reference +0.2 pt (0-0.5) | N63: fixed | O63: =IFERROR(IF(option_sel=0,"",IF(LEN(INDEX(Opt_Overview!$C$7:$M$38,MATCH($A63,Opt_Overview!$A$7:$A$38,0),option_sel))=0,"",INDEX(Opt_Overview!$C$7:$M$38,MATCH($A63,Opt_Overview!$A$7:$A$38,0),option_sel))),"")
A64: mix_plant_avg_binder_conv | B64: kg/m3 | C64: 290 | D64: 310 | E64: 330 | F64: 3 | G64: 1 | H64: =INDEX(C64:E64,1,CHOOSE(scenario,F64,2,G64)) -> 310 | J64: =IF(I64<>"",I64,IF(O64<>"",O64,H64)) -> 310 | K64: ESTIMATE | L64: CMP-43;A-CST-11 | M64: Plant average over all strength classes (NL avg cement ~310 kg/m3, ERMCO 2023). Use with avg price | N64: cost | O64: =IFERROR(IF(option_sel=0,"",IF(LEN(INDEX(Opt_Overview!$C$7:$M$38,MATCH($A64,Opt_Overview!$A$7:$A$38,0),option_sel))=0,"",INDEX(Opt_Overview!$C$7:$M$38,MATCH($A64,Opt_Overview!$A$7:$A$38,0),option_sel))),"")
A65: mix_plant_avg_binder_circ | B65: kg/m3 | C65: 305 | D65: 325 | E65: 345 | F65: 3 | G65: 1 | H65: =INDEX(C65:E65,1,CHOOSE(scenario,F65,2,G65)) -> 325 | J65: =IF(I65<>"",I65,IF(O65<>"",O65,H65)) -> 325 | K65: ESTIMATE | L65: CMP-43;A-TEC-11 | M65: Avg + 15 kg for RCA | N65: cost | O65: =IFERROR(IF(option_sel=0,"",IF(LEN(INDEX(Opt_Overview!$C$7:$M$38,MATCH($A65,Opt_Overview!$A$7:$A$38,0),option_sel))=0,"",INDEX(Opt_Overview!$C$7:$M$38,MATCH($A65,Opt_Overview!$A$7:$A$38,0),option_sel))),"")
A66: price_cem3b_2026_delivered | B66: EUR/t | C66: 95 | D66: 110 | E66: 130 | F66: 3 | G66: 1 | H66: =INDEX(C66:E66,1,CHOOSE(scenario,F66,2,G66)) -> 110 | J66: =IF(I66<>"",I66,IF(O66<>"",O66,H66)) -> 110 | K66: ESTIMATE | L66: A-MKT-19;CST-14;CST-11;MKT-25;A-CST-12 | M66: Bulk delivered, incl. 2026 carbon cost (~EUR 4/t). Raised from A-MKT-19 (105) after Argus/Sika evidence | N66: cost | O66: =IFERROR(IF(option_sel=0,"",IF(LEN(INDEX(Opt_Overview!$C$7:$M$38,MATCH($A66,Opt_Overview!$A$7:$A$38,0),option_sel))=0,"",INDEX(Opt_Overview!$C$7:$M$38,MATCH($A66,Opt_Overview!$A$7:$A$38,0),option_sel))),"")
A67: price_cem1_2026_delivered | B67: EUR/t | C67: 120 | D67: 140 | E67: 165 | F67: 2 | G67: 2 | H67: =INDEX(C67:E67,1,CHOOSE(scenario,F67,2,G67)) -> 140 | J67: =IF(I67<>"",I67,IF(O67<>"",O67,H67)) -> 140 | K67: ESTIMATE | L67: A-MKT-20;CST-14;CST-11;MKT-25;A-CST-12 | M67: Incl. 2026 carbon cost (~EUR 14/t). Raised from A-MKT-20 (125) | N67: fixed | O67: =IFERROR(IF(option_sel=0,"",IF(LEN(INDEX(Opt_Overview!$C$7:$M$38,MATCH($A67,Opt_Overview!$A$7:$A$38,0),option_sel))=0,"",INDEX(Opt_Overview!$C$7:$M$38,MATCH($A67,Opt_Overview!$A$7:$A$38,0),option_sel))),"")
A68: cement_carbon_passthrough | B68: % | C68: 50 | D68: 85 | E68: 100 | F68: 3 | G68: 1 | H68: =INDEX(C68:E68,1,CHOOSE(scenario,F68,2,G68)) -> 85 | J68: =IF(I68<>"",I68,IF(O68<>"",O68,H68)) -> 85 | K68: ASSUMPTION | L68: A-POL-09 | M68: cement_price(y) = price_2026 + passthrough x (carbon_cost(y) - carbon_cost(2026)), same path | N68: cost | O68: =IFERROR(IF(option_sel=0,"",IF(LEN(INDEX(Opt_Overview!$C$7:$M$38,MATCH($A68,Opt_Overview!$A$7:$A$38,0),option_sel))=0,"",INDEX(Opt_Overview!$C$7:$M$38,MATCH($A68,Opt_Overview!$A$7:$A$38,0),option_sel))),"")
A69: cem3b_slag_scarcity_uplift_2031plus | B69: % | C69: 0 | D69: 10 | E69: 25 | F69: 3 | G69: 1 | H69: =INDEX(C69:E69,1,CHOOSE(scenario,F69,2,G69)) -> 10 | J69: =IF(I69<>"",I69,IF(O69<>"",O69,H69)) -> 10 | K69: ASSUMPTION | L69: A-POL-28;A-TEC-46 | M69: Extra CEM III/B price from 2031 (Tata BF7 -> DRI) | N69: cost | O69: =IFERROR(IF(option_sel=0,"",IF(LEN(INDEX(Opt_Overview!$C$7:$M$38,MATCH($A69,Opt_Overview!$A$7:$A$38,0),option_sel))=0,"",INDEX(Opt_Overview!$C$7:$M$38,MATCH($A69,Opt_Overview!$A$7:$A$38,0),option_sel))),"")
A70: concrete_price_passthrough_of_market_binder_cost | B70: % | C70: 50 | D70: 80 | E70: 100 | F70: 1 | G70: 3 | H70: =INDEX(C70:E70,1,CHOOSE(scenario,F70,2,G70)) -> 80 | J70: =IF(I70<>"",I70,IF(O70<>"",O70,H70)) -> 80 | K70: ASSUMPTION | L70: A-CST-13 | M70: Share of the market-wide CEM III/B cost increase passed into ready-mix prices (all producers face it) | N70: rev | O70: =IFERROR(IF(option_sel=0,"",IF(LEN(INDEX(Opt_Overview!$C$7:$M$38,MATCH($A70,Opt_Overview!$A$7:$A$38,0),option_sel))=0,"",INDEX(Opt_Overview!$C$7:$M$38,MATCH($A70,Opt_Overview!$A$7:$A$38,0),option_sel))),"")
A71: eua_price_2026 | B71: EUR/tCO2 | C71: 85 | D71: 85 | E71: 85 | F71: 2 | G71: 2 | H71: =INDEX(C71:E71,1,CHOOSE(scenario,F71,2,G71)) -> 85 | J71: =IF(I71<>"",I71,IF(O71<>"",O71,H71)) -> 85 | K71: VERIFIED | L71: A-POL-01;A-POL-02;A-POL-03;POL-44 | M71: Interpolated between policy anchor years 2027/2030/2034 | N71: fixed | O71: =IFERROR(IF(option_sel=0,"",IF(LEN(INDEX(Opt_Overview!$C$7:$M$38,MATCH($A71,Opt_Overview!$A$7:$A$38,0),option_sel))=0,"",INDEX(Opt_Overview!$C$7:$M$38,MATCH($A71,Opt_Overview!$A$7:$A$38,0),option_sel))),"")
A72: eua_price_2027 | B72: EUR/tCO2 | C72: 65 | D72: 88 | E72: 105 | F72: 2 | G72: 2 | H72: =INDEX(C72:E72,1,CHOOSE(scenario,F72,2,G72)) -> 88 | J72: =IF(I72<>"",I72,IF(O72<>"",O72,H72)) -> 88 | K72: ESTIMATE | L72: A-POL-01;A-POL-02;A-POL-03;POL-44 | M72: Interpolated between policy anchor years 2027/2030/2034 | N72: fixed | O72: =IFERROR(IF(option_sel=0,"",IF(LEN(INDEX(Opt_Overview!$C$7:$M$38,MATCH($A72,Opt_Overview!$A$7:$A$38,0),option_sel))=0,"",INDEX(Opt_Overview!$C$7:$M$38,MATCH($A72,Opt_Overview!$A$7:$A$38,0),option_sel))),"")
A73: eua_price_2028 | B73: EUR/tCO2 | C73: 67 | D73: 91 | E73: 113 | F73: 2 | G73: 2 | H73: =INDEX(C73:E73,1,CHOOSE(scenario,F73,2,G73)) -> 91 | J73: =IF(I73<>"",I73,IF(O73<>"",O73,H73)) -> 91 | K73: ESTIMATE | L73: A-POL-01;A-POL-02;A-POL-03;POL-44 | M73: Interpolated between policy anchor years 2027/2030/2034 | N73: fixed | O73: =IFERROR(IF(option_sel=0,"",IF(LEN(INDEX(Opt_Overview!$C$7:$M$38,MATCH($A73,Opt_Overview!$A$7:$A$38,0),option_sel))=0,"",INDEX(Opt_Overview!$C$7:$M$38,MATCH($A73,Opt_Overview!$A$7:$A$38,0),option_sel))),"")
... A108: road_haulage_rate | B108: EUR/t.km | C108: 0.18 | D108: 0.25 | E108: 0.35 | F108: 3 | G108: 1 | H108: =INDEX(C108:E108,1,CHOOSE(scenario,F108,2,G108)) -> 0.25 | J108: =IF(I108<>"",I108,IF(O108<>"",O108,H108)) -> 0.25 | K108: ESTIMATE | L108: A-TEC-32;TEC-41 | M108: Full load per loaded km | N108: cost | O108: =IFERROR(IF(option_sel=0,"",IF(LEN(INDEX(Opt_Overview!$C$7:$M$38,MATCH($A108,Opt_Overview!$A$7:$A$38,0),option_sel))=0,"",INDEX(Opt_Overview!$C$7:$M$38,MATCH($A108,Opt_Overview!$A$7:$A$38,0),option_sel))),"")
A109: road_handling_per_t | B109: EUR/t | C109: 1.5 | D109: 2 | E109: 3 | F109: 3 | G109: 1 | H109: =INDEX(C109:E109,1,CHOOSE(scenario,F109,2,G109)) -> 2 | J109: =IF(I109<>"",I109,IF(O109<>"",O109,H109)) -> 2 | K109: ESTIMATE | L109: A-TEC-32 | N109: cost | O109: =IFERROR(IF(option_sel=0,"",IF(LEN(INDEX(Opt_Overview!$C$7:$M$38,MATCH($A109,Opt_Overview!$A$7:$A$38,0),option_sel))=0,"",INDEX(Opt_Overview!$C$7:$M$38,MATCH($A109,Opt_Overview!$A$7:$A$38,0),option_sel))),"")
A110: price_rca_coarse_delivered | B110: EUR/t | C110: 14.2 | D110: 24.5 | E110: 45.5 | F110: 2 | G110: 2 | H110: =INDEX(C110:E110,1,CHOOSE(scenario,F110,2,G110)) -> 24.5 | J110: =IF(I110<>"",I110,IF(O110<>"",O110,H110)) -> 24.5 | K110: ESTIMATE | L110: derived | M110: '= ex-works + km x rate + handling. Breakeven vs gravel EUR 32: ~EUR 29/t delivered (before premium) | N110: fixed | O110: =IFERROR(IF(option_sel=0,"",IF(LEN(INDEX(Opt_Overview!$C$7:$M$38,MATCH($A110,Opt_Overview!$A$7:$A$38,0),option_sel))=0,"",INDEX(Opt_Overview!$C$7:$M$38,MATCH($A110,Opt_Overview!$A$7:$A$38,0),option_sel))),"")
A111: barge_rate | B111: EUR/t.km | C111: 0.015 | D111: 0.03 | E111: 0.05 | F111: 2 | G111: 2 | H111: =INDEX(C111:E111,1,CHOOSE(scenario,F111,2,G111)) -> 0.03 | J111: =IF(I111<>"",I111,IF(O111<>"",O111,H111)) -> 0.03 | K111: ESTIMATE | L111: A-TEC-33;TEC-41 | M111: Option: RCA from waterside crushers | N111: fixed | O111: =IFERROR(IF(option_sel=0,"",IF(LEN(INDEX(Opt_Overview!$C$7:$M$38,MATCH($A111,Opt_Overview!$A$7:$A$38,0),option_sel))=0,"",INDEX(Opt_Overview!$C$7:$M$38,MATCH($A111,Opt_Overview!$A$7:$A$38,0),option_sel))),"")
A112: barge_transshipment_per_t | B112: EUR/t | C112: 1.5 | D112: 2.5 | E112: 4 | F112: 2 | G112: 2 | H112: =INDEX(C112:E112,1,CHOOSE(scenario,F112,2,G112)) -> 2.5 | J112: =IF(I112<>"",I112,IF(O112<>"",O112,H112)) -> 2.5 | K112: ESTIMATE | L112: A-TEC-33 | N112: fixed | O112: =IFERROR(IF(option_sel=0,"",IF(LEN(INDEX(Opt_Overview!$C$7:$M$38,MATCH($A112,Opt_Overview!$A$7:$A$38,0),option_sel))=0,"",INDEX(Opt_Overview!$C$7:$M$38,MATCH($A112,Opt_Overview!$A$7:$A$38,0),option_sel))),"")
A113: price_rca_fine_exworks | B113: EUR/t | C113: 3 | D113: 8 | E113: 15 | F113: 3 | G113: 1 | H113: =INDEX(C113:E113,1,CHOOSE(scenario,F113,2,G113)) -> 8 | J113: =IF(I113<>"",I113,IF(O113<>"",O113,H113)) -> 8 | K113: ASSUMPTION | L113: A-CST-15 | M113: Certified recycled 0/4; thin market | N113: cost | O113: =IFERROR(IF(option_sel=0,"",IF(LEN(INDEX(Opt_Overview!$C$7:$M$38,MATCH($A113,Opt_Overview!$A$7:$A$38,0),option_sel))=0,"",INDEX(Opt_Overview!$C$7:$M$38,MATCH($A113,Opt_Overview!$A$7:$A$38,0),option_sel))),"")
A114: price_superplasticiser | B114: EUR/kg | C114: 1 | D114: 1.4 | E114: 2 | F114: 3 | G114: 1 | H114: =INDEX(C114:E114,1,CHOOSE(scenario,F114,2,G114)) -> 1.4 | J114: =IF(I114<>"",I114,IF(O114<>"",O114,H114)) -> 1.4 | K114: ASSUMPTION | L114: CST-11;CST-13;A-CST-10 | M114: Liquid PCE, bulk | N114: cost | O114: =IFERROR(IF(option_sel=0,"",IF(LEN(INDEX(Opt_Overview!$C$7:$M$38,MATCH($A114,Opt_Overview!$A$7:$A$38,0),option_sel))=0,"",INDEX(Opt_Overview!$C$7:$M$38,MATCH($A114,Opt_Overview!$A$7:$A$38,0),option_sel))),"")
A115: price_water | B115: EUR/m3 | C115: 0.8 | D115: 1.2 | E115: 2 | F115: 3 | G115: 1 | H115: =INDEX(C115:E115,1,CHOOSE(scenario,F115,2,G115)) -> 1.2 | J115: =IF(I115<>"",I115,IF(O115<>"",O115,H115)) -> 1.2 | K115: ASSUMPTION | L115: A-CST-16 | M115: Mains/ground water; part from recycled wash water | N115: cost | O115: =IFERROR(IF(option_sel=0,"",IF(LEN(INDEX(Opt_Overview!$C$7:$M$38,MATCH($A115,Opt_Overview!$A$7:$A$38,0),option_sel))=0,"",INDEX(Opt_Overview!$C$7:$M$38,MATCH($A115,Opt_Overview!$A$7:$A$38,0),option_sel))),"")
A116: rca_lot_testing | B116: EUR/t RCA | C116: 0.5 | D116: 0.8 | E116: 1.5 | F116: 3 | G116: 1 | H116: =INDEX(C116:E116,1,CHOOSE(scenario,F116,2,G116)) -> 0.8 | J116: =IF(I116<>"",I116,IF(O116<>"",O116,H116)) -> 0.8 | K116: ASSUMPTION | L116: A-CST-17 | M116: Density/WA, EN 933-11, sulphate/chloride per ~500 t lot | N116: cost | O116: =IFERROR(IF(option_sel=0,"",IF(LEN(INDEX(Opt_Overview!$C$7:$M$38,MATCH($A116,Opt_Overview!$A$7:$A$38,0),option_sel))=0,"",INDEX(Opt_Overview!$C$7:$M$38,MATCH($A116,Opt_Overview!$A$7:$A$38,0),option_sel))),"")
A117: rca_handling_prewetting | B117: EUR/t RCA | C117: 0.5 | D117: 1 | E117: 2 | F117: 3 | G117: 1 | H117: =INDEX(C117:E117,1,CHOOSE(scenario,F117,2,G117)) -> 1 | J117: =IF(I117<>"",I117,IF(O117<>"",O117,H117)) -> 1 | K117: ASSUMPTION | L117: A-CST-18 | M117: Separate bins per source, sprinkling, extra loader moves, moisture control | N117: cost | O117: =IFERROR(IF(option_sel=0,"",IF(LEN(INDEX(Opt_Overview!$C$7:$M$38,MATCH($A117,Opt_Overview!$A$7:$A$38,0),option_sel))=0,"",INDEX(Opt_Overview!$C$7:$M$38,MATCH($A117,Opt_Overview!$A$7:$A$38,0),option_sel))),"")
A118: electricity_use | B118: kWh/m3 | C118: 3.5 | D118: 3.6 | E118: 4.5 | F118: 3 | G118: 1 | H118: =INDEX(C118:E118,1,CHOOSE(scenario,F118,2,G118)) -> 3.6 | J118: =IF(I118<>"",I118,IF(O118<>"",O118,H118)) -> 3.6 | K118: VERIFIED | L118: A-TEC-38;TEC-04 | M118: NMD A3 | N118: cost | O118: =IFERROR(IF(option_sel=0,"",IF(LEN(INDEX(Opt_Overview!$C$7:$M$38,MATCH($A118,Opt_Overview!$A$7:$A$38,0),option_sel))=0,"",INDEX(Opt_Overview!$C$7:$M$38,MATCH($A118,Opt_Overview!$A$7:$A$38,0),option_sel))),"")
A119: price_electricity | B119: EUR/kWh | C119: 0.16 | D119: 0.2 | E119: 0.26 | F119: 3 | G119: 1 | H119: =INDEX(C119:E119,1,CHOOSE(scenario,F119,2,G119)) -> 0.2 | J119: =IF(I119<>"",I119,IF(O119<>"",O119,H119)) -> 0.2 | K119: ESTIMATE | L119: CST-04;CST-05 | M119: CBS 2026-H1 non-household 500-2000 MWh EUR 0.245 incl. VAT and tax -> ~0.20 excl. VAT | N119: cost | O119: =IFERROR(IF(option_sel=0,"",IF(LEN(INDEX(Opt_Overview!$C$7:$M$38,MATCH($A119,Opt_Overview!$A$7:$A$38,0),option_sel))=0,"",INDEX(Opt_Overview!$C$7:$M$38,MATCH($A119,Opt_Overview!$A$7:$A$38,0),option_sel))),"")
A120: diesel_use_plant | B120: l/m3 | C120: 0.1 | D120: 0.12 | E120: 0.25 | F120: 3 | G120: 1 | H120: =INDEX(C120:E120,1,CHOOSE(scenario,F120,2,G120)) -> 0.12 | J120: =IF(I120<>"",I120,IF(O120<>"",O120,H120)) -> 0.12 | K120: VERIFIED | L120: A-TEC-38;TEC-83 | M120: Loader + heating; high incl. winter heating oil | N120: cost | O120: =IFERROR(IF(option_sel=0,"",IF(LEN(INDEX(Opt_Overview!$C$7:$M$38,MATCH($A120,Opt_Overview!$A$7:$A$38,0),option_sel))=0,"",INDEX(Opt_Overview!$C$7:$M$38,MATCH($A120,Opt_Overview!$A$7:$A$38,0),option_sel))),"")
A121: price_diesel | B121: EUR/l | C121: 1.3 | D121: 1.55 | E121: 1.8 | F121: 3 | G121: 1 | H121: =INDEX(C121:E121,1,CHOOSE(scenario,F121,2,G121)) -> 1.55 | J121: =IF(I121<>"",I121,IF(O121<>"",O121,H121)) -> 1.55 | K121: ASSUMPTION | L121: A-CST-19 | M121: Excl. VAT, bulk | N121: cost | O121: =IFERROR(IF(option_sel=0,"",IF(LEN(INDEX(Opt_Overview!$C$7:$M$38,MATCH($A121,Opt_Overview!$A$7:$A$38,0),option_sel))=0,"",INDEX(Opt_Overview!$C$7:$M$38,MATCH($A121,Opt_Overview!$A$7:$A$38,0),option_sel))),"")
A122: staff_production_fte | B122: FTE | C122: 6 | D122: 7 | E122: 9 | F122: 3 | G122: 1 | H122: =INDEX(C122:E122,1,CHOOSE(scenario,F122,2,G122)) -> 7 | J122: =IF(I122<>"",I122,IF(O122<>"",O122,H122)) -> 7 | K122: ASSUMPTION | L122: A-TEC-25;A-CST-20 | M122: Batchers 2, loader 2, lab 1.5, maintenance 1, ~0.5 plant mgmt | N122: cost | O122: =IFERROR(IF(option_sel=0,"",IF(LEN(INDEX(Opt_Overview!$C$7:$M$38,MATCH($A122,Opt_Overview!$A$7:$A$38,0),option_sel))=0,"",INDEX(Opt_Overview!$C$7:$M$38,MATCH($A122,Opt_Overview!$A$7:$A$38,0),option_sel))),"")
A123: cost_per_fte_production | B123: EUR/yr | C123: 62000 | D123: 70000 | E123: 78000 | F123: 3 | G123: 1 | H123: =INDEX(C123:E123,1,CHOOSE(scenario,F123,2,G123)) -> 70000 | J123: =IF(I123<>"",I123,IF(O123<>"",O123,H123)) -> 70000 | K123: ESTIMATE | L123: CST-06;CST-07;A-CST-21 | M123: CAO Mortelbedrijven 2026 garantieloon EUR 3,394-3,770/month; x12 x1.08 holiday x~1.3 employer cost + overtime/shift | N123: cost | O123: =IFERROR(IF(option_sel=0,"",IF(LEN(INDEX(Opt_Overview!$C$7:$M$38,MATCH($A123,Opt_Overview!$A$7:$A$38,0),option_sel))=0,"",INDEX(Opt_Overview!$C$7:$M$38,MATCH($A123,Opt_Overview!$A$7:$A$38,0),option_sel))),"")
A124: staff_sga_fte | B124: FTE | C124: 2 | D124: 3 | E124: 4 | F124: 3 | G124: 1 | H124: =INDEX(C124:E124,1,CHOOSE(scenario,F124,2,G124)) -> 3 | J124: =IF(I124<>"",I124,IF(O124<>"",O124,H124)) -> 3 | K124: ASSUMPTION | L124: A-TEC-25;A-CST-20 | M124: Manager, sales/technical sales, planner/admin | N124: cost | O124: =IFERROR(IF(option_sel=0,"",IF(LEN(INDEX(Opt_Overview!$C$7:$M$38,MATCH($A124,Opt_Overview!$A$7:$A$38,0),option_sel))=0,"",INDEX(Opt_Overview!$C$7:$M$38,MATCH($A124,Opt_Overview!$A$7:$A$38,0),option_sel))),"")
A125: cost_per_fte_sga | B125: EUR/yr | C125: 80000 | D125: 90000 | E125: 110000 | F125: 3 | G125: 1 | H125: =INDEX(C125:E125,1,CHOOSE(scenario,F125,2,G125)) -> 90000 | J125: =IF(I125<>"",I125,IF(O125<>"",O125,H125)) -> 90000 | K125: ASSUMPTION | L125: A-CST-21 | N125: cost | O125: =IFERROR(IF(option_sel=0,"",IF(LEN(INDEX(Opt_Overview!$C$7:$M$38,MATCH($A125,Opt_Overview!$A$7:$A$38,0),option_sel))=0,"",INDEX(Opt_Overview!$C$7:$M$38,MATCH($A125,Opt_Overview!$A$7:$A$38,0),option_sel))),"")
A126: real_wage_growth | B126: %/yr | C126: 0 | D126: 0.5 | E126: 1 | F126: 3 | G126: 1 | H126: =INDEX(C126:E126,1,CHOOSE(scenario,F126,2,G126)) -> 0.5 | J126: =IF(I126<>"",I126,IF(O126<>"",O126,H126)) -> 0.5 | K126: ESTIMATE | L126: CST-07 | M126: CBS: real cao wage +0.8% (Q3 2026) | N126: cost | O126: =IFERROR(IF(option_sel=0,"",IF(LEN(INDEX(Opt_Overview!$C$7:$M$38,MATCH($A126,Opt_Overview!$A$7:$A$38,0),option_sel))=0,"",INDEX(Opt_Overview!$C$7:$M$38,MATCH($A126,Opt_Overview!$A$7:$A$38,0),option_sel))),"")
A127: maintenance_pct_of_capex | B127: %/yr | C127: 1.5 | D127: 2.5 | E127: 4 | F127: 3 | G127: 1 | H127: =INDEX(C127:E127,1,CHOOSE(scenario,F127,2,G127)) -> 2.5 | J127: =IF(I127<>"",I127,IF(O127<>"",O127,H127)) -> 2.5 | K127: ASSUMPTION | L127: A-CST-22 | M127: On plant equipment + civil; incl. mixer liners/blades (TEC-57) | N127: cost | O127: =IFERROR(IF(option_sel=0,"",IF(LEN(INDEX(Opt_Overview!$C$7:$M$38,MATCH($A127,Opt_Overview!$A$7:$A$38,0),option_sel))=0,"",INDEX(Opt_Overview!$C$7:$M$38,MATCH($A127,Opt_Overview!$A$7:$A$38,0),option_sel))),"")
A128: certification_testing_fixed | B128: EUR/yr | C128: 30000 | D128: 50000 | E128: 80000 | F128: 3 | G128: 1 | H128: =INDEX(C128:E128,1,CHOOSE(scenario,F128,2,G128)) -> 50000 | J128: =IF(I128<>"",I128,IF(O128<>"",O128,H128)) -> 50000 | K128: ASSUMPTION | L128: CST-20;CST-03;CST-21;A-CST-23 | M128: KOMO BRL 1801 audits, CSC, NMD fees, external cube/lab tests, LCA updates | N128: cost | O128: =IFERROR(IF(option_sel=0,"",IF(LEN(INDEX(Opt_Overview!$C$7:$M$38,MATCH($A128,Opt_Overview!$A$7:$A$38,0),option_sel))=0,"",INDEX(Opt_Overview!$C$7:$M$38,MATCH($A128,Opt_Overview!$A$7:$A$38,0),option_sel))),"")
A129: site_area | B129: m2 | C129: 10000 | D129: 15000 | E129: 25000 | F129: 3 | G129: 1 | H129: =INDEX(C129:E129,1,CHOOSE(scenario,F129,2,G129)) -> 15000 | J129: =IF(I129<>"",I129,IF(O129<>"",O129,H129)) -> 15000 | K129: ASSUMPTION | L129: A-TEC-22 | N129: cost | O129: =IFERROR(IF(option_sel=0,"",IF(LEN(INDEX(Opt_Overview!$C$7:$M$38,MATCH($A129,Opt_Overview!$A$7:$A$38,0),option_sel))=0,"",INDEX(Opt_Overview!$C$7:$M$38,MATCH($A129,Opt_Overview!$A$7:$A$38,0),option_sel))),"")
A130: site_lease_rate | B130: EUR/m2/yr | C130: 6 | D130: 10 | E130: 15 | F130: 3 | G130: 1 | H130: =INDEX(C130:E130,1,CHOOSE(scenario,F130,2,G130)) -> 10 | J130: =IF(I130<>"",I130,IF(O130<>"",O130,H130)) -> 10 | K130: ESTIMATE | L130: CST-09;CST-10;A-CST-24 | M130: Rotterdam erfpacht canon 3.81% x ground value ~EUR 150-300/m2; waterside premium | N130: cost | O130: =IFERROR(IF(option_sel=0,"",IF(LEN(INDEX(Opt_Overview!$C$7:$M$38,MATCH($A130,Opt_Overview!$A$7:$A$38,0),option_sel))=0,"",INDEX(Opt_Overview!$C$7:$M$38,MATCH($A130,Opt_Overview!$A$7:$A$38,0),option_sel))),"")
A131: sga_fixed_non_staff | B131: EUR/yr | C131: 200000 | D131: 300000 | E131: 450000 | F131: 3 | G131: 1 | H131: =INDEX(C131:E131,1,CHOOSE(scenario,F131,2,G131)) -> 300000 | J131: =IF(I131<>"",I131,IF(O131<>"",O131,H131)) -> 300000 | K131: ASSUMPTION | L131: A-CST-25 | M131: Insurance, ERP/dispatch IT, audit, legal, marketing, vehicles, office | N131: cost | O131: =IFERROR(IF(option_sel=0,"",IF(LEN(INDEX(Opt_Overview!$C$7:$M$38,MATCH($A131,Opt_Overview!$A$7:$A$38,0),option_sel))=0,"",INDEX(Opt_Overview!$C$7:$M$38,MATCH($A131,Opt_Overview!$A$7:$A$38,0),option_sel))),"")
A132: bad_debt_pct_revenue | B132: % | C132: 0.3 | D132: 0.5 | E132: 1 | F132: 3 | G132: 1 | H132: =INDEX(C132:E132,1,CHOOSE(scenario,F132,2,G132)) -> 0.5 | J132: =IF(I132<>"",I132,IF(O132<>"",O132,H132)) -> 0.5 | K132: ASSUMPTION | L132: A-CST-26 | N132: cost | O132: =IFERROR(IF(option_sel=0,"",IF(LEN(INDEX(Opt_Overview!$C$7:$M$38,MATCH($A132,Opt_Overview!$A$7:$A$38,0),option_sel))=0,"",INDEX(Opt_Overview!$C$7:$M$38,MATCH($A132,Opt_Overview!$A$7:$A$38,0),option_sel))),"")
A133: delivery_fixed_per_m3 | B133: EUR/m3 | C133: 7 | D133: 9 | E133: 11 | F133: 3 | G133: 1 | H133: =INDEX(C133:E133,1,CHOOSE(scenario,F133,2,G133)) -> 9 | J133: =IF(I133<>"",I133,IF(O133<>"",O133,H133)) -> 9 | K133: ESTIMATE | L133: A-TEC-28 | M133: Subcontracted truck mixers; check: EUR 110/h, 10 m3, 50 min fixed, 45 km/h -> EUR 18.9/m3 at 20 km | N133: cost | O133: =IFERROR(IF(option_sel=0,"",IF(LEN(INDEX(Opt_Overview!$C$7:$M$38,MATCH($A133,Opt_Overview!$A$7:$A$38,0),option_sel))=0,"",INDEX(Opt_Overview!$C$7:$M$38,MATCH($A133,Opt_Overview!$A$7:$A$38,0),option_sel))),"")
A134: delivery_variable_per_km_oneway | B134: EUR/m3/km | C134: 0.4 | D134: 0.5 | E134: 0.6 | F134: 3 | G134: 1 | H134: =INDEX(C134:E134,1,CHOOSE(scenario,F134,2,G134)) -> 0.5 | J134: =IF(I134<>"",I134,IF(O134<>"",O134,H134)) -> 0.5 | K134: ESTIMATE | L134: A-TEC-28 | N134: cost | O134: =IFERROR(IF(option_sel=0,"",IF(LEN(INDEX(Opt_Overview!$C$7:$M$38,MATCH($A134,Opt_Overview!$A$7:$A$38,0),option_sel))=0,"",INDEX(Opt_Overview!$C$7:$M$38,MATCH($A134,Opt_Overview!$A$7:$A$38,0),option_sel))),"")
A135: delivery_avg_distance_oneway | B135: km | C135: 10 | D135: 20 | E135: 35 | F135: 3 | G135: 1 | H135: =INDEX(C135:E135,1,CHOOSE(scenario,F135,2,G135)) -> 20 | J135: =IF(I135<>"",I135,IF(O135<>"",O135,H135)) -> 20 | K135: ESTIMATE | L135: A-TEC-29;A-CST-27 | M135: Mean distance in a 30 km disc = 2R/3 = 20 km | N135: cost | O135: =IFERROR(IF(option_sel=0,"",IF(LEN(INDEX(Opt_Overview!$C$7:$M$38,MATCH($A135,Opt_Overview!$A$7:$A$38,0),option_sel))=0,"",INDEX(Opt_Overview!$C$7:$M$38,MATCH($A135,Opt_Overview!$A$7:$A$38,0),option_sel))),"")
...

Sheet UnitEconomics
A1: Unit economics - EUR per m3 delivered, circular vs standard (conventional) mix in the same plant
A3: Year index shown (1..10; 3 = 2029, first full-output year) | C3: 3 | D3: =2026+C3 -> 2029
A4: Fixed costs are spread equally over all m3 of that year. Delivery is subcontracted.
A6: Line (EUR/m3) | C6: Circular | D6: Standard CEM III/B | E6: Plant average | F6: Circular - standard
A7: Price (delivered) | C7: =INDEX(Revenue!$D$21:$M$21,1,$C$3) -> 137.38799 | D7: =INDEX(Revenue!$D$22:$M$22,1,$C$3) -> 135.75888 | E7: =(INDEX(Revenue!$D$25:$M$25,1,$C$3)+INDEX(Revenue!$D$26:$M$26,1,$C$3))/INDEX(Revenue!$D$8:$M$8,1,$C$3) -> 136.73634 | F7: =C7-D7 -> 1.6291066
A8: Cement | C8: =INDEX(Opex!$D$13:$M$13,1,$C$3) -> 36.7445 | D8: =INDEX(Opex!$D$21:$M$21,1,$C$3) -> 35.0486 | E8: =(INDEX(Revenue!$D$9:$M$9,1,$C$3)/INDEX(Revenue!$D$8:$M$8,1,$C$3))*C8+(1-(INDEX(Revenue!$D$9:$M$9,1,$C$3)/INDEX(Revenue!$D$8:$M$8,1,$C$3)))*D8 -> 36.06614 | F8: =C8-D8 -> 1.6959
A9: Gravel | C9: =INDEX(Opex!$D$14:$M$14,1,$C$3) -> 19.84 | D9: =INDEX(Opex!$D$22:$M$22,1,$C$3) -> 39.712 | E9: =(INDEX(Revenue!$D$9:$M$9,1,$C$3)/INDEX(Revenue!$D$8:$M$8,1,$C$3))*C9+(1-(INDEX(Revenue!$D$9:$M$9,1,$C$3)/INDEX(Revenue!$D$8:$M$8,1,$C$3)))*D9 -> 27.7888 | F9: =C9-D9 -> -19.872
A10: Recycled aggregate (delivered) | C10: =INDEX(Opex!$D$15:$M$15,1,$C$3) -> 13.72 | D10: =INDEX(Opex!$D$23:$M$23,1,$C$3) -> 0 | E10: =(INDEX(Revenue!$D$9:$M$9,1,$C$3)/INDEX(Revenue!$D$8:$M$8,1,$C$3))*C10+(1-(INDEX(Revenue!$D$9:$M$9,1,$C$3)/INDEX(Revenue!$D$8:$M$8,1,$C$3)))*D10 -> 8.232 | F10: =C10-D10 -> 13.72
A11: Sand | C11: =INDEX(Opex!$D$16:$M$16,1,$C$3) -> 11.97 | D11: =INDEX(Opex!$D$24:$M$24,1,$C$3) -> 12.141 | E11: =(INDEX(Revenue!$D$9:$M$9,1,$C$3)/INDEX(Revenue!$D$8:$M$8,1,$C$3))*C11+(1-(INDEX(Revenue!$D$9:$M$9,1,$C$3)/INDEX(Revenue!$D$8:$M$8,1,$C$3)))*D11 -> 12.0384 | F11: =C11-D11 -> -0.171
A12: Admixture (superplasticiser) | C12: =INDEX(Opex!$D$17:$M$17,1,$C$3) -> 4.095 | D12: =INDEX(Opex!$D$25:$M$25,1,$C$3) -> 3.038 | E12: =(INDEX(Revenue!$D$9:$M$9,1,$C$3)/INDEX(Revenue!$D$8:$M$8,1,$C$3))*C12+(1-(INDEX(Revenue!$D$9:$M$9,1,$C$3)/INDEX(Revenue!$D$8:$M$8,1,$C$3)))*D12 -> 3.6722 | F12: =C12-D12 -> 1.057
A13: Water | C13: =INDEX(Opex!$D$18:$M$18,1,$C$3) -> 0.2316 | D13: =INDEX(Opex!$D$26:$M$26,1,$C$3) -> 0.198 | E13: =(INDEX(Revenue!$D$9:$M$9,1,$C$3)/INDEX(Revenue!$D$8:$M$8,1,$C$3))*C13+(1-(INDEX(Revenue!$D$9:$M$9,1,$C$3)/INDEX(Revenue!$D$8:$M$8,1,$C$3)))*D13 -> 0.21816 | F13: =C13-D13 -> 0.0336
A14: RCA testing & handling | C14: =Opex!$C$8 -> 1.008 | D14: =0 -> 0 | E14: =(INDEX(Revenue!$D$9:$M$9,1,$C$3)/INDEX(Revenue!$D$8:$M$8,1,$C$3))*C14+(1-(INDEX(Revenue!$D$9:$M$9,1,$C$3)/INDEX(Revenue!$D$8:$M$8,1,$C$3)))*D14 -> 0.6048 | F14: =C14-D14 -> 1.008
A15: Energy | C15: =Opex!$C$9 -> 0.906 | D15: =Opex!$C$9 -> 0.906 | E15: =(INDEX(Revenue!$D$9:$M$9,1,$C$3)/INDEX(Revenue!$D$8:$M$8,1,$C$3))*C15+(1-(INDEX(Revenue!$D$9:$M$9,1,$C$3)/INDEX(Revenue!$D$8:$M$8,1,$C$3)))*D15 -> 0.906 | F15: =C15-D15 -> 0
A16: Variable cost delta (hook) | C16: =opt_cost_delta_per_m3 -> 0 | D16: =opt_cost_delta_per_m3 -> 0 | E16: =(INDEX(Revenue!$D$9:$M$9,1,$C$3)/INDEX(Revenue!$D$8:$M$8,1,$C$3))*C16+(1-(INDEX(Revenue!$D$9:$M$9,1,$C$3)/INDEX(Revenue!$D$8:$M$8,1,$C$3)))*D16 -> 0 | F16: =C16-D16 -> 0
A17: Circular-only cost delta (option) | C17: =IF(INDEX(Revenue!$D$9:$M$9,1,$C$3)>0,INDEX(Opex!$D$39:$M$39,1,$C$3)/INDEX(Revenue!$D$9:$M$9,1,$C$3),0) -> 0 | D17: =0 -> 0 | E17: =(INDEX(Revenue!$D$9:$M$9,1,$C$3)/INDEX(Revenue!$D$8:$M$8,1,$C$3))*C17+(1-(INDEX(Revenue!$D$9:$M$9,1,$C$3)/INDEX(Revenue!$D$8:$M$8,1,$C$3)))*D17 -> 0 | F17: =C17-D17 -> 0
A18: On-site crushing net cost per m3 (negative = net income, option A+B) | C18: =-(INDEX(Opex!$D$65:$M$65,1,$C$3)-INDEX(Revenue!$D$40:$M$40,1,$C$3)*bad_debt_pct_revenue/100)/INDEX(Revenue!$D$8:$M$8,1,$C$3) -> 0 | D18: =-(INDEX(Opex!$D$65:$M$65,1,$C$3)-INDEX(Revenue!$D$40:$M$40,1,$C$3)*bad_debt_pct_revenue/100)/INDEX(Revenue!$D$8:$M$8,1,$C$3) -> 0 | E18: =(INDEX(Revenue!$D$9:$M$9,1,$C$3)/INDEX(Revenue!$D$8:$M$8,1,$C$3))*C18+(1-(INDEX(Revenue!$D$9:$M$9,1,$C$3)/INDEX(Revenue!$D$8:$M$8,1,$C$3)))*D18 -> 0 | F18: =C18-D18 -> 0
A19: Production labour | C19: =INDEX(Opex!$D$48:$M$48,1,$C$3)/INDEX(Revenue!$D$8:$M$8,1,$C$3) -> 7.1055259 | D19: =INDEX(Opex!$D$48:$M$48,1,$C$3)/INDEX(Revenue!$D$8:$M$8,1,$C$3) -> 7.1055259 | E19: =(INDEX(Revenue!$D$9:$M$9,1,$C$3)/INDEX(Revenue!$D$8:$M$8,1,$C$3))*C19+(1-(INDEX(Revenue!$D$9:$M$9,1,$C$3)/INDEX(Revenue!$D$8:$M$8,1,$C$3)))*D19 -> 7.1055259 | F19: =C19-D19 -> 0
A20: Maintenance & wear | C20: =INDEX(Opex!$D$49:$M$49,1,$C$3)/INDEX(Revenue!$D$8:$M$8,1,$C$3) -> 1.7857143 | D20: =INDEX(Opex!$D$49:$M$49,1,$C$3)/INDEX(Revenue!$D$8:$M$8,1,$C$3) -> 1.7857143 | E20: =(INDEX(Revenue!$D$9:$M$9,1,$C$3)/INDEX(Revenue!$D$8:$M$8,1,$C$3))*C20+(1-(INDEX(Revenue!$D$9:$M$9,1,$C$3)/INDEX(Revenue!$D$8:$M$8,1,$C$3)))*D20 -> 1.7857143 | F20: =C20-D20 -> 0
A21: Certification & testing | C21: =INDEX(Opex!$D$50:$M$50,1,$C$3)/INDEX(Revenue!$D$8:$M$8,1,$C$3) -> 0.71428571 | D21: =INDEX(Opex!$D$50:$M$50,1,$C$3)/INDEX(Revenue!$D$8:$M$8,1,$C$3) -> 0.71428571 | E21: =(INDEX(Revenue!$D$9:$M$9,1,$C$3)/INDEX(Revenue!$D$8:$M$8,1,$C$3))*C21+(1-(INDEX(Revenue!$D$9:$M$9,1,$C$3)/INDEX(Revenue!$D$8:$M$8,1,$C$3)))*D21 -> 0.71428571 | F21: =C21-D21 -> 0
A22: Site lease | C22: =INDEX(Opex!$D$51:$M$51,1,$C$3)/INDEX(Revenue!$D$8:$M$8,1,$C$3) -> 2.1428571 | D22: =INDEX(Opex!$D$51:$M$51,1,$C$3)/INDEX(Revenue!$D$8:$M$8,1,$C$3) -> 2.1428571 | E22: =(INDEX(Revenue!$D$9:$M$9,1,$C$3)/INDEX(Revenue!$D$8:$M$8,1,$C$3))*C22+(1-(INDEX(Revenue!$D$9:$M$9,1,$C$3)/INDEX(Revenue!$D$8:$M$8,1,$C$3)))*D22 -> 2.1428571 | F22: =C22-D22 -> 0
A23: SG&A staff | C23: =INDEX(Opex!$D$52:$M$52,1,$C$3)/INDEX(Revenue!$D$8:$M$8,1,$C$3) -> 3.9152898 | D23: =INDEX(Opex!$D$52:$M$52,1,$C$3)/INDEX(Revenue!$D$8:$M$8,1,$C$3) -> 3.9152898 | E23: =(INDEX(Revenue!$D$9:$M$9,1,$C$3)/INDEX(Revenue!$D$8:$M$8,1,$C$3))*C23+(1-(INDEX(Revenue!$D$9:$M$9,1,$C$3)/INDEX(Revenue!$D$8:$M$8,1,$C$3)))*D23 -> 3.9152898 | F23: =C23-D23 -> 0
A24: SG&A non-staff | C24: =INDEX(Opex!$D$53:$M$53,1,$C$3)/INDEX(Revenue!$D$8:$M$8,1,$C$3) -> 4.2857143 | D24: =INDEX(Opex!$D$53:$M$53,1,$C$3)/INDEX(Revenue!$D$8:$M$8,1,$C$3) -> 4.2857143 | E24: =(INDEX(Revenue!$D$9:$M$9,1,$C$3)/INDEX(Revenue!$D$8:$M$8,1,$C$3))*C24+(1-(INDEX(Revenue!$D$9:$M$9,1,$C$3)/INDEX(Revenue!$D$8:$M$8,1,$C$3)))*D24 -> 4.2857143 | F24: =C24-D24 -> 0
A25: Extra fixed (hook) | C25: =INDEX(Opex!$D$54:$M$54,1,$C$3)/INDEX(Revenue!$D$8:$M$8,1,$C$3) -> 0 | D25: =INDEX(Opex!$D$54:$M$54,1,$C$3)/INDEX(Revenue!$D$8:$M$8,1,$C$3) -> 0 | E25: =(INDEX(Revenue!$D$9:$M$9,1,$C$3)/INDEX(Revenue!$D$8:$M$8,1,$C$3))*C25+(1-(INDEX(Revenue!$D$9:$M$9,1,$C$3)/INDEX(Revenue!$D$8:$M$8,1,$C$3)))*D25 -> 0 | F25: =C25-D25 -> 0
A26: Delivery (truck mixer) | C26: =Opex!$C$10 -> 19 | D26: =Opex!$C$10 -> 19 | E26: =(INDEX(Revenue!$D$9:$M$9,1,$C$3)/INDEX(Revenue!$D$8:$M$8,1,$C$3))*C26+(1-(INDEX(Revenue!$D$9:$M$9,1,$C$3)/INDEX(Revenue!$D$8:$M$8,1,$C$3)))*D26 -> 19 | F26: =C26-D26 -> 0
A27: Bad debt | C27: =C7*bad_debt_pct_revenue/100 -> 0.68693993 | D27: =D7*bad_debt_pct_revenue/100 -> 0.6787944 | E27: =(INDEX(Revenue!$D$9:$M$9,1,$C$3)/INDEX(Revenue!$D$8:$M$8,1,$C$3))*C27+(1-(INDEX(Revenue!$D$9:$M$9,1,$C$3)/INDEX(Revenue!$D$8:$M$8,1,$C$3)))*D27 -> 0.68368172 | F27: =C27-D27 -> 0.0081455328
A28: Cash cost (before depreciation) | C28: =SUM(C8:C27) -> 128.15143 | D28: =SUM(D8:D27) -> 130.67178 | E28: =SUM(E8:E27) -> 129.15957 | F28: =C28-D28 -> -2.5203545
A29: EBITDA margin | C29: =C7-C28 -> 9.2365596 | D29: =D7-D28 -> 5.0870985 | E29: =E7-E28 -> 7.5767751 | F29: =C29-D29 -> 4.149461
A30: Depreciation & amortisation | C30: =INDEX(Capex!$D$29:$M$29,1,$C$3)/INDEX(Revenue!$D$8:$M$8,1,$C$3) -> 3.6571429 | D30: =INDEX(Capex!$D$29:$M$29,1,$C$3)/INDEX(Revenue!$D$8:$M$8,1,$C$3) -> 3.6571429 | E30: =(INDEX(Revenue!$D$9:$M$9,1,$C$3)/INDEX(Revenue!$D$8:$M$8,1,$C$3))*C30+(1-(INDEX(Revenue!$D$9:$M$9,1,$C$3)/INDEX(Revenue!$D$8:$M$8,1,$C$3)))*D30 -> 3.6571429 | F30: =C30-D30 -> 0
A31: Total cost incl. depreciation | C31: =C28+C30 -> 131.80857 | D31: =D28+D30 -> 134.32892 | E31: =E28+E30 -> 132.81671 | F31: =C31-D31 -> -2.5203545
A32: EBIT margin | C32: =C7-C31 -> 5.5794167 | D32: =D7-D31 -> 1.4299557 | E32: =E7-E31 -> 3.9196323 | F32: =C32-D32 -> 4.149461
A33: Memo: capital recovery charge (10 yr annuity at r) | C33: =Valuation!$B$21/INDEX(Revenue!$D$8:$M$8,1,$C$3) -> 11.70946 | D33: =Valuation!$B$21/INDEX(Revenue!$D$8:$M$8,1,$C$3) -> 11.70946 | E33: =(INDEX(Revenue!$D$9:$M$9,1,$C$3)/INDEX(Revenue!$D$8:$M$8,1,$C$3))*C33+(1-(INDEX(Revenue!$D$9:$M$9,1,$C$3)/INDEX(Revenue!$D$8:$M$8,1,$C$3)))*D33 -> 11.70946 | F33: =C33-D33 -> 0
A34: Memo: EBITDA margin after capital charge | C34: =C29-C33 -> -2.4729003 | D34: =D29-D33 -> -6.6223613 | E34: =E29-E33 -> -4.1326847 | F34: =C34-D34 -> 4.149461
A36: Check: plant-average EBITDA x volume - P&L EBITDA (0 unless hook revenue) | E36: =E29*INDEX(Revenue!$D$8:$M$8,1,$C$3)-(INDEX(PnL!$D$35:$M$35,1,$C$3)-INDEX(Revenue!$D$27:$M$27,1,$C$3)) -> 0
A37: EBITDA margin as % of price | C37: =C29/C7 -> 0.067229747 | D37: =D29/D7 -> 0.037471571 | E37: =E29/E7 -> 0.055411567

Sheet Capex
A1: Capex, one-off start-up costs, grant, depreciation, salvage (EUR, real 2026)
A2: t=0 (2026) = permitting & construction year. All initial spend in t=0.
A3: Year | B3: unit | C3: =2026+C4 -> 2026 | D3: =2026+D4 -> 2027 | E3: =2026+E4 -> 2028 | F3: =2026+F4 -> 2029 | G3: =2026+G4 -> 2030 | H3: =2026+H4 -> 2031 | I3: =2026+I4 -> 2032 | J3: =2026+J4 -> 2033 | ... M3: =2026+M4 -> 2036
A4: t (year index) | C4: 0 | D4: 1 | E4: 2 | F4: 3 | G4: 4 | H4: 5 | I4: 6 | J4: 7 | K4: 8 | L4: 9 | M4: 10
A6: Initial investment (t = 0)
A7: Plant equipment (batching plant, mixer, bins, silos, lab) - in build year (2026 + delay) | B7: EUR | C7: =IF(C$4=opt_start_delay,capex_plant_equipment*1000000,0) -> 4000000 | D7: =IF(D$4=opt_start_delay,capex_plant_equipment*1000000,0) -> 0 | E7: =IF(E$4=opt_start_delay,capex_plant_equipment*1000000,0) -> 0 | F7: =IF(F$4=opt_start_delay,capex_plant_equipment*1000000,0) -> 0 | G7: =IF(G$4=opt_start_delay,capex_plant_equipment*1000000,0) -> 0 | H7: =IF(H$4=opt_start_delay,capex_plant_equipment*1000000,0) -> 0 | I7: =IF(I$4=opt_start_delay,capex_plant_equipment*1000000,0) -> 0 | J7: =IF(J$4=opt_start_delay,capex_plant_equipment*1000000,0) -> 0 | ... M7: =IF(M$4=opt_start_delay,capex_plant_equipment*1000000,0) -> 0
A8: Site preparation & civil works - in build year | B8: EUR | C8: =IF(C$4=opt_start_delay,capex_site_prep_civil*1000000,0) -> 1000000 | D8: =IF(D$4=opt_start_delay,capex_site_prep_civil*1000000,0) -> 0 | E8: =IF(E$4=opt_start_delay,capex_site_prep_civil*1000000,0) -> 0 | F8: =IF(F$4=opt_start_delay,capex_site_prep_civil*1000000,0) -> 0 | G8: =IF(G$4=opt_start_delay,capex_site_prep_civil*1000000,0) -> 0 | H8: =IF(H$4=opt_start_delay,capex_site_prep_civil*1000000,0) -> 0 | I8: =IF(I$4=opt_start_delay,capex_site_prep_civil*1000000,0) -> 0 | J8: =IF(J$4=opt_start_delay,capex_site_prep_civil*1000000,0) -> 0 | ... M8: =IF(M$4=opt_start_delay,capex_site_prep_civil*1000000,0) -> 0
A9: Permits, studies, engineering (amortised) - always 2026 | B9: EUR | C9: =capex_permits_engineering*1000000 -> 500000 | D9: 0 | E9: 0 | F9: 0 | G9: 0 | H9: 0 | I9: 0 | J9: 0 | K9: 0 | L9: 0 | M9: 0
A10: Option hook: extra capex - in build year | B10: EUR | C10: =IF(C$4=opt_start_delay,opt_extra_capex_y0,0) -> 0 | D10: =IF(D$4=opt_start_delay,opt_extra_capex_y0,0) -> 0 | E10: =IF(E$4=opt_start_delay,opt_extra_capex_y0,0) -> 0 | F10: =IF(F$4=opt_start_delay,opt_extra_capex_y0,0) -> 0 | G10: =IF(G$4=opt_start_delay,opt_extra_capex_y0,0) -> 0 | H10: =IF(H$4=opt_start_delay,opt_extra_capex_y0,0) -> 0 | I10: =IF(I$4=opt_start_delay,opt_extra_capex_y0,0) -> 0 | J10: =IF(J$4=opt_start_delay,opt_extra_capex_y0,0) -> 0 | ... M10: =IF(M$4=opt_start_delay,opt_extra_capex_y0,0) -> 0
A11: Land purchase (0 = leased) - in build year | B11: EUR | C11: =IF(C$4=opt_start_delay,land_purchase*1000000,0) -> 0 | D11: =IF(D$4=opt_start_delay,land_purchase*1000000,0) -> 0 | E11: =IF(E$4=opt_start_delay,land_purchase*1000000,0) -> 0 | F11: =IF(F$4=opt_start_delay,land_purchase*1000000,0) -> 0 | G11: =IF(G$4=opt_start_delay,land_purchase*1000000,0) -> 0 | H11: =IF(H$4=opt_start_delay,land_purchase*1000000,0) -> 0 | I11: =IF(I$4=opt_start_delay,land_purchase*1000000,0) -> 0 | J11: =IF(J$4=opt_start_delay,land_purchase*1000000,0) -> 0 | ... M11: =IF(M$4=opt_start_delay,land_purchase*1000000,0) -> 0
A12: Option A+B: year index of crushing-line capex (year before first crushing) | B12: t | C12: =MIN(10,MAX(0,ROUND(opt_crusher_start_year-2026,0)-1)) -> 0
A13: Option A+B: crushing-line capex | B13: EUR | C13: =IF(C$4=$C$12,opt_crusher_capex,0) -> 0 | D13: =IF(D$4=$C$12,opt_crusher_capex,0) -> 0 | E13: =IF(E$4=$C$12,opt_crusher_capex,0) -> 0 | F13: =IF(F$4=$C$12,opt_crusher_capex,0) -> 0 | G13: =IF(G$4=$C$12,opt_crusher_capex,0) -> 0 | H13: =IF(H$4=$C$12,opt_crusher_capex,0) -> 0 | I13: =IF(I$4=$C$12,opt_crusher_capex,0) -> 0 | J13: =IF(J$4=$C$12,opt_crusher_capex,0) -> 0 | ... M13: =IF(M$4=$C$12,opt_crusher_capex,0) -> 0
A14: Total initial capex | B14: EUR | C14: =C7+C8+C9+C10+C11+C13 -> 5500000 | D14: =D7+D8+D9+D10+D11+D13 -> 0 | E14: =E7+E8+E9+E10+E11+E13 -> 0 | F14: =F7+F8+F9+F10+F11+F13 -> 0 | G14: =G7+G8+G9+G10+G11+G13 -> 0 | H14: =H7+H8+H9+H10+H11+H13 -> 0 | I14: =I7+I8+I9+I10+I11+I13 -> 0 | J14: =J7+J8+J9+J10+J11+J13 -> 0 | ... M14: =M7+M8+M9+M10+M11+M13 -> 0
A15: Physical assets (plant + civil) - base for maintenance, sustaining capex, salvage | B15: EUR | C15: =SUM(Capex!$C$7:$M$7)+SUM(Capex!$C$8:$M$8) -> 5000000
A17: One-off items in t = 0 (expensed / income, not capex)
A18: Start-up costs expensed: LCA/EPD + pre-opening (build year) | B18: EUR | C18: =IF(C$4=opt_start_delay,capex_lca_epd_one_off+capex_preopening_costs,0) -> 380000 | D18: =IF(D$4=opt_start_delay,capex_lca_epd_one_off+capex_preopening_costs,0) -> 0 | E18: =IF(E$4=opt_start_delay,capex_lca_epd_one_off+capex_preopening_costs,0) -> 0 | F18: =IF(F$4=opt_start_delay,capex_lca_epd_one_off+capex_preopening_costs,0) -> 0 | G18: =IF(G$4=opt_start_delay,capex_lca_epd_one_off+capex_preopening_costs,0) -> 0 | H18: =IF(H$4=opt_start_delay,capex_lca_epd_one_off+capex_preopening_costs,0) -> 0 | I18: =IF(I$4=opt_start_delay,capex_lca_epd_one_off+capex_preopening_costs,0) -> 0 | J18: =IF(J$4=opt_start_delay,capex_lca_epd_one_off+capex_preopening_costs,0) -> 0 | ... M18: =IF(M$4=opt_start_delay,capex_lca_epd_one_off+capex_preopening_costs,0) -> 0
A19: Grant DEI+/VEKI (taxable income in build year) | B19: EUR | C19: =IF(C$4=opt_start_delay,grant_dei_veki_first_plant*1000000,0) -> 400000 | D19: =IF(D$4=opt_start_delay,grant_dei_veki_first_plant*1000000,0) -> 0 | E19: =IF(E$4=opt_start_delay,grant_dei_veki_first_plant*1000000,0) -> 0 | F19: =IF(F$4=opt_start_delay,grant_dei_veki_first_plant*1000000,0) -> 0 | G19: =IF(G$4=opt_start_delay,grant_dei_veki_first_plant*1000000,0) -> 0 | H19: =IF(H$4=opt_start_delay,grant_dei_veki_first_plant*1000000,0) -> 0 | I19: =IF(I$4=opt_start_delay,grant_dei_veki_first_plant*1000000,0) -> 0 | J19: =IF(J$4=opt_start_delay,grant_dei_veki_first_plant*1000000,0) -> 0 | ... M19: =IF(M$4=opt_start_delay,grant_dei_veki_first_plant*1000000,0) -> 0
A20: MIA extra tax deduction (gives the stated net value at top rate); plant in build year, crusher in its capex year | B20: EUR | C20: =IF(C$4=opt_start_delay,mia_eligible_share_of_capex/100*$C$15*mia_net_value_pct_eligible_capex/tax_rate_vpb_high_bracket,0)+IF(C$4=$C$12,opt_crusher_mia_share_pct/100*opt_crusher_capex*mia_net_value_pct_eligible_capex/tax_rate_vpb_high_bracket,0) -> 360465.12 | D20: =IF(D$4=opt_start_delay,mia_eligible_share_of_capex/100*$C$15*mia_net_value_pct_eligible_capex/tax_rate_vpb_high_bracket,0)+IF(D$4=$C$12,opt_crusher_mia_share_pct/100*opt_crusher_capex*mia_net_value_pct_eligible_capex/tax_rate_vpb_high_bracket,0) -> 0 | E20: =IF(E$4=opt_start_delay,mia_eligible_share_of_capex/100*$C$15*mia_net_value_pct_eligible_capex/tax_rate_vpb_high_bracket,0)+IF(E$4=$C$12,opt_crusher_mia_share_pct/100*opt_crusher_capex*mia_net_value_pct_eligible_capex/tax_rate_vpb_high_bracket,0) -> 0 | F20: =IF(F$4=opt_start_delay,mia_eligible_share_of_capex/100*$C$15*mia_net_value_pct_eligible_capex/tax_rate_vpb_high_bracket,0)+IF(F$4=$C$12,opt_crusher_mia_share_pct/100*opt_crusher_capex*mia_net_value_pct_eligible_capex/tax_rate_vpb_high_bracket,0) -> 0 | G20: =IF(G$4=opt_start_delay,mia_eligible_share_of_capex/100*$C$15*mia_net_value_pct_eligible_capex/tax_rate_vpb_high_bracket,0)+IF(G$4=$C$12,opt_crusher_mia_share_pct/100*opt_crusher_capex*mia_net_value_pct_eligible_capex/tax_rate_vpb_high_bracket,0) -> 0 | H20: =IF(H$4=opt_start_delay,mia_eligible_share_of_capex/100*$C$15*mia_net_value_pct_eligible_capex/tax_rate_vpb_high_bracket,0)+IF(H$4=$C$12,opt_crusher_mia_share_pct/100*opt_crusher_capex*mia_net_value_pct_eligible_capex/tax_rate_vpb_high_bracket,0) -> 0 | I20: =IF(I$4=opt_start_delay,mia_eligible_share_of_capex/100*$C$15*mia_net_value_pct_eligible_capex/tax_rate_vpb_high_bracket,0)+IF(I$4=$C$12,opt_crusher_mia_share_pct/100*opt_crusher_capex*mia_net_value_pct_eligible_capex/tax_rate_vpb_high_bracket,0) -> 0 | J20: =IF(J$4=opt_start_delay,mia_eligible_share_of_capex/100*$C$15*mia_net_value_pct_eligible_capex/tax_rate_vpb_high_bracket,0)+IF(J$4=$C$12,opt_crusher_mia_share_pct/100*opt_crusher_capex*mia_net_value_pct_eligible_capex/tax_rate_vpb_high_bracket,0) -> 0 | ... M20: =IF(M$4=opt_start_delay,mia_eligible_share_of_capex/100*$C$15*mia_net_value_pct_eligible_capex/tax_rate_vpb_high_bracket,0)+IF(M$4=$C$12,opt_crusher_mia_share_pct/100*opt_crusher_capex*mia_net_value_pct_eligible_capex/tax_rate_vpb_high_bracket,0) -> 0
A22: Sustaining capex and depreciation
A23: Sustaining capex (% of physical assets per operating year) | B23: EUR | C23: =IF(C$4>=(1+opt_start_delay),sustaining_capex_pct_of_capex/100*$C$15,0) -> 0 | D23: =IF(D$4>=(1+opt_start_delay),sustaining_capex_pct_of_capex/100*$C$15,0) -> 50000 | E23: =IF(E$4>=(1+opt_start_delay),sustaining_capex_pct_of_capex/100*$C$15,0) -> 50000 | F23: =IF(F$4>=(1+opt_start_delay),sustaining_capex_pct_of_capex/100*$C$15,0) -> 50000 | G23: =IF(G$4>=(1+opt_start_delay),sustaining_capex_pct_of_capex/100*$C$15,0) -> 50000 | H23: =IF(H$4>=(1+opt_start_delay),sustaining_capex_pct_of_capex/100*$C$15,0) -> 50000 | I23: =IF(I$4>=(1+opt_start_delay),sustaining_capex_pct_of_capex/100*$C$15,0) -> 50000 | J23: =IF(J$4>=(1+opt_start_delay),sustaining_capex_pct_of_capex/100*$C$15,0) -> 50000 | ... M23: =IF(M$4>=(1+opt_start_delay),sustaining_capex_pct_of_capex/100*$C$15,0) -> 50000
A24: Depreciation plant equipment (+ hook capex), from first operating year | B24: EUR | C24: =IF(AND(C$4>=(1+opt_start_delay),C$4<(1+opt_start_delay)+lifetime_plant_equipment),(SUM(Capex!$C$7:$M$7)+SUM(Capex!$C$10:$M$10))/lifetime_plant_equipment,0) -> 0 | D24: =IF(AND(D$4>=(1+opt_start_delay),D$4<(1+opt_start_delay)+lifetime_plant_equipment),(SUM(Capex!$C$7:$M$7)+SUM(Capex!$C$10:$M$10))/lifetime_plant_equipment,0) -> 160000 | E24: =IF(AND(E$4>=(1+opt_start_delay),E$4<(1+opt_start_delay)+lifetime_plant_equipment),(SUM(Capex!$C$7:$M$7)+SUM(Capex!$C$10:$M$10))/lifetime_plant_equipment,0) -> 160000 | F24: =IF(AND(F$4>=(1+opt_start_delay),F$4<(1+opt_start_delay)+lifetime_plant_equipment),(SUM(Capex!$C$7:$M$7)+SUM(Capex!$C$10:$M$10))/lifetime_plant_equipment,0) -> 160000 | G24: =IF(AND(G$4>=(1+opt_start_delay),G$4<(1+opt_start_delay)+lifetime_plant_equipment),(SUM(Capex!$C$7:$M$7)+SUM(Capex!$C$10:$M$10))/lifetime_plant_equipment,0) -> 160000 | H24: =IF(AND(H$4>=(1+opt_start_delay),H$4<(1+opt_start_delay)+lifetime_plant_equipment),(SUM(Capex!$C$7:$M$7)+SUM(Capex!$C$10:$M$10))/lifetime_plant_equipment,0) -> 160000 | I24: =IF(AND(I$4>=(1+opt_start_delay),I$4<(1+opt_start_delay)+lifetime_plant_equipment),(SUM(Capex!$C$7:$M$7)+SUM(Capex!$C$10:$M$10))/lifetime_plant_equipment,0) -> 160000 | J24: =IF(AND(J$4>=(1+opt_start_delay),J$4<(1+opt_start_delay)+lifetime_plant_equipment),(SUM(Capex!$C$7:$M$7)+SUM(Capex!$C$10:$M$10))/lifetime_plant_equipment,0) -> 160000 | ... M24: =IF(AND(M$4>=(1+opt_start_delay),M$4<(1+opt_start_delay)+lifetime_plant_equipment),(SUM(Capex!$C$7:$M$7)+SUM(Capex!$C$10:$M$10))/lifetime_plant_equipment,0) -> 160000
A25: Depreciation civil works | B25: EUR | C25: =IF(AND(C$4>=(1+opt_start_delay),C$4<(1+opt_start_delay)+lifetime_civil_works),SUM(Capex!$C$8:$M$8)/lifetime_civil_works,0) -> 0 | D25: =IF(AND(D$4>=(1+opt_start_delay),D$4<(1+opt_start_delay)+lifetime_civil_works),SUM(Capex!$C$8:$M$8)/lifetime_civil_works,0) -> 40000 | E25: =IF(AND(E$4>=(1+opt_start_delay),E$4<(1+opt_start_delay)+lifetime_civil_works),SUM(Capex!$C$8:$M$8)/lifetime_civil_works,0) -> 40000 | F25: =IF(AND(F$4>=(1+opt_start_delay),F$4<(1+opt_start_delay)+lifetime_civil_works),SUM(Capex!$C$8:$M$8)/lifetime_civil_works,0) -> 40000 | G25: =IF(AND(G$4>=(1+opt_start_delay),G$4<(1+opt_start_delay)+lifetime_civil_works),SUM(Capex!$C$8:$M$8)/lifetime_civil_works,0) -> 40000 | H25: =IF(AND(H$4>=(1+opt_start_delay),H$4<(1+opt_start_delay)+lifetime_civil_works),SUM(Capex!$C$8:$M$8)/lifetime_civil_works,0) -> 40000 | I25: =IF(AND(I$4>=(1+opt_start_delay),I$4<(1+opt_start_delay)+lifetime_civil_works),SUM(Capex!$C$8:$M$8)/lifetime_civil_works,0) -> 40000 | J25: =IF(AND(J$4>=(1+opt_start_delay),J$4<(1+opt_start_delay)+lifetime_civil_works),SUM(Capex!$C$8:$M$8)/lifetime_civil_works,0) -> 40000 | ... M25: =IF(AND(M$4>=(1+opt_start_delay),M$4<(1+opt_start_delay)+lifetime_civil_works),SUM(Capex!$C$8:$M$8)/lifetime_civil_works,0) -> 40000
A26: Amortisation permits & engineering | B26: EUR | C26: =IF(AND(C$4>=(1+opt_start_delay),C$4<(1+opt_start_delay)+lifetime_permits_engineering),$C$9/lifetime_permits_engineering,0) -> 0 | D26: =IF(AND(D$4>=(1+opt_start_delay),D$4<(1+opt_start_delay)+lifetime_permits_engineering),$C$9/lifetime_permits_engineering,0) -> 50000 | E26: =IF(AND(E$4>=(1+opt_start_delay),E$4<(1+opt_start_delay)+lifetime_permits_engineering),$C$9/lifetime_permits_engineering,0) -> 50000 | F26: =IF(AND(F$4>=(1+opt_start_delay),F$4<(1+opt_start_delay)+lifetime_permits_engineering),$C$9/lifetime_permits_engineering,0) -> 50000 | G26: =IF(AND(G$4>=(1+opt_start_delay),G$4<(1+opt_start_delay)+lifetime_permits_engineering),$C$9/lifetime_permits_engineering,0) -> 50000 | H26: =IF(AND(H$4>=(1+opt_start_delay),H$4<(1+opt_start_delay)+lifetime_permits_engineering),$C$9/lifetime_permits_engineering,0) -> 50000 | I26: =IF(AND(I$4>=(1+opt_start_delay),I$4<(1+opt_start_delay)+lifetime_permits_engineering),$C$9/lifetime_permits_engineering,0) -> 50000 | J26: =IF(AND(J$4>=(1+opt_start_delay),J$4<(1+opt_start_delay)+lifetime_permits_engineering),$C$9/lifetime_permits_engineering,0) -> 50000 | ... M26: =IF(AND(M$4>=(1+opt_start_delay),M$4<(1+opt_start_delay)+lifetime_permits_engineering),$C$9/lifetime_permits_engineering,0) -> 50000
A27: Depreciation crushing line (option A+B) | B27: EUR | C27: =IF(AND(C$4>=$C$12+1,C$4<$C$12+1+hybrid_crusher_lifetime),opt_crusher_capex/hybrid_crusher_lifetime,0) -> 0 | D27: =IF(AND(D$4>=$C$12+1,D$4<$C$12+1+hybrid_crusher_lifetime),opt_crusher_capex/hybrid_crusher_lifetime,0) -> 0 | E27: =IF(AND(E$4>=$C$12+1,E$4<$C$12+1+hybrid_crusher_lifetime),opt_crusher_capex/hybrid_crusher_lifetime,0) -> 0 | F27: =IF(AND(F$4>=$C$12+1,F$4<$C$12+1+hybrid_crusher_lifetime),opt_crusher_capex/hybrid_crusher_lifetime,0) -> 0 | G27: =IF(AND(G$4>=$C$12+1,G$4<$C$12+1+hybrid_crusher_lifetime),opt_crusher_capex/hybrid_crusher_lifetime,0) -> 0 | H27: =IF(AND(H$4>=$C$12+1,H$4<$C$12+1+hybrid_crusher_lifetime),opt_crusher_capex/hybrid_crusher_lifetime,0) -> 0 | I27: =IF(AND(I$4>=$C$12+1,I$4<$C$12+1+hybrid_crusher_lifetime),opt_crusher_capex/hybrid_crusher_lifetime,0) -> 0 | J27: =IF(AND(J$4>=$C$12+1,J$4<$C$12+1+hybrid_crusher_lifetime),opt_crusher_capex/hybrid_crusher_lifetime,0) -> 0 | ... M27: =IF(AND(M$4>=$C$12+1,M$4<$C$12+1+hybrid_crusher_lifetime),opt_crusher_capex/hybrid_crusher_lifetime,0) -> 0
A28: Depreciation sustaining capex (plant life) | B28: EUR | C28: =SUM($C$23:C23)/lifetime_plant_equipment -> 0 | D28: =SUM($C$23:D23)/lifetime_plant_equipment -> 2000 | E28: =SUM($C$23:E23)/lifetime_plant_equipment -> 4000 | F28: =SUM($C$23:F23)/lifetime_plant_equipment -> 6000 | G28: =SUM($C$23:G23)/lifetime_plant_equipment -> 8000 | H28: =SUM($C$23:H23)/lifetime_plant_equipment -> 10000 | I28: =SUM($C$23:I23)/lifetime_plant_equipment -> 12000 | J28: =SUM($C$23:J23)/lifetime_plant_equipment -> 14000 | ... M28: =SUM($C$23:M23)/lifetime_plant_equipment -> 20000
A29: Total depreciation & amortisation | B29: EUR | C29: =C24+C25+C26+C27+C28 -> 0 | D29: =D24+D25+D26+D27+D28 -> 252000 | E29: =E24+E25+E26+E27+E28 -> 254000 | F29: =F24+F25+F26+F27+F28 -> 256000 | G29: =G24+G25+G26+G27+G28 -> 258000 | H29: =H24+H25+H26+H27+H28 -> 260000 | I29: =I24+I25+I26+I27+I28 -> 262000 | J29: =J24+J25+J26+J27+J28 -> 264000 | ... M29: =M24+M25+M26+M27+M28 -> 270000
A30: Memo: net book value end of year (excl. land) | B30: EUR | C30: =SUM($C$14:C14)-SUM($C$11:C11)+SUM($C$23:C23)-SUM($C$29:C29) -> 5500000 | D30: =SUM($C$14:D14)-SUM($C$11:D11)+SUM($C$23:D23)-SUM($C$29:D29) -> 5298000 | E30: =SUM($C$14:E14)-SUM($C$11:E11)+SUM($C$23:E23)-SUM($C$29:E29) -> 5094000 | F30: =SUM($C$14:F14)-SUM($C$11:F11)+SUM($C$23:F23)-SUM($C$29:F29) -> 4888000 | G30: =SUM($C$14:G14)-SUM($C$11:G11)+SUM($C$23:G23)-SUM($C$29:G29) -> 4680000 | H30: =SUM($C$14:H14)-SUM($C$11:H11)+SUM($C$23:H23)-SUM($C$29:H29) -> 4470000 | I30: =SUM($C$14:I14)-SUM($C$11:I11)+SUM($C$23:I23)-SUM($C$29:I29) -> 4258000 | J30: =SUM($C$14:J14)-SUM($C$11:J11)+SUM($C$23:J23)-SUM($C$29:J29) -> 4044000 | ... M30: =SUM($C$14:M14)-SUM($C$11:M11)+SUM($C$23:M23)-SUM($C$29:M29) -> 3390000
A31: Salvage value in t=10 (= the ONLY terminal value; plant+civil and crushing line) | B31: EUR | C31: =IF(C$4=10,salvage_value_yr10_pct_of_plant_civil_capex/100*$C$15+opt_crusher_salvage_pct/100*opt_crusher_capex,0) -> 0 | D31: =IF(D$4=10,salvage_value_yr10_pct_of_plant_civil_capex/100*$C$15+opt_crusher_salvage_pct/100*opt_crusher_capex,0) -> 0 | E31: =IF(E$4=10,salvage_value_yr10_pct_of_plant_civil_capex/100*$C$15+opt_crusher_salvage_pct/100*opt_crusher_capex,0) -> 0 | F31: =IF(F$4=10,salvage_value_yr10_pct_of_plant_civil_capex/100*$C$15+opt_crusher_salvage_pct/100*opt_crusher_capex,0) -> 0 | G31: =IF(G$4=10,salvage_value_yr10_pct_of_plant_civil_capex/100*$C$15+opt_crusher_salvage_pct/100*opt_crusher_capex,0) -> 0 | H31: =IF(H$4=10,salvage_value_yr10_pct_of_plant_civil_capex/100*$C$15+opt_crusher_salvage_pct/100*opt_crusher_capex,0) -> 0 | I31: =IF(I$4=10,salvage_value_yr10_pct_of_plant_civil_capex/100*$C$15+opt_crusher_salvage_pct/100*opt_crusher_capex,0) -> 0 | J31: =IF(J$4=10,salvage_value_yr10_pct_of_plant_civil_capex/100*$C$15+opt_crusher_salvage_pct/100*opt_crusher_capex,0) -> 0 | ... M31: =IF(M$4=10,salvage_value_yr10_pct_of_plant_civil_capex/100*$C$15+opt_crusher_salvage_pct/100*opt_crusher_capex,0) -> 1250000

Sheet Revenue
A1: Volume, prices and revenue
A2: Plant-average price over all strength classes (Agent 5). Premium only on circular volume.
A3: Year | B3: unit | C3: =2026+C4 -> 2026 | D3: =2026+D4 -> 2027 | E3: =2026+E4 -> 2028 | F3: =2026+F4 -> 2029 | G3: =2026+G4 -> 2030 | H3: =2026+H4 -> 2031 | I3: =2026+I4 -> 2032 | J3: =2026+J4 -> 2033 | ... M3: =2026+M4 -> 2036
A4: t (year index) | C4: 0 | D4: 1 | E4: 2 | F4: 3 | G4: 4 | H4: 5 | I4: 6 | J4: 7 | K4: 8 | L4: 9 | M4: 10
A6: Volume
A7: Utilisation of steady-state output (ramp-up) | B7: % | C7: =IF(C$4<1+opt_start_delay,0,IF(C$4=1+opt_start_delay,ramp_year1_pct_of_steady/100,IF(C$4=2+opt_start_delay,ramp_year2_pct_of_steady/100,ramp_year3plus_pct_of_steady/100))) -> 0 | D7: =IF(D$4<1+opt_start_delay,0,IF(D$4=1+opt_start_delay,ramp_year1_pct_of_steady/100,IF(D$4=2+opt_start_delay,ramp_year2_pct_of_steady/100,ramp_year3plus_pct_of_steady/100))) -> 0.5 | E7: =IF(E$4<1+opt_start_delay,0,IF(E$4=1+opt_start_delay,ramp_year1_pct_of_steady/100,IF(E$4=2+opt_start_delay,ramp_year2_pct_of_steady/100,ramp_year3plus_pct_of_steady/100))) -> 0.79 | F7: =IF(F$4<1+opt_start_delay,0,IF(F$4=1+opt_start_delay,ramp_year1_pct_of_steady/100,IF(F$4=2+opt_start_delay,ramp_year2_pct_of_steady/100,ramp_year3plus_pct_of_steady/100))) -> 1 | G7: =IF(G$4<1+opt_start_delay,0,IF(G$4=1+opt_start_delay,ramp_year1_pct_of_steady/100,IF(G$4=2+opt_start_delay,ramp_year2_pct_of_steady/100,ramp_year3plus_pct_of_steady/100))) -> 1 | H7: =IF(H$4<1+opt_start_delay,0,IF(H$4=1+opt_start_delay,ramp_year1_pct_of_steady/100,IF(H$4=2+opt_start_delay,ramp_year2_pct_of_steady/100,ramp_year3plus_pct_of_steady/100))) -> 1 | I7: =IF(I$4<1+opt_start_delay,0,IF(I$4=1+opt_start_delay,ramp_year1_pct_of_steady/100,IF(I$4=2+opt_start_delay,ramp_year2_pct_of_steady/100,ramp_year3plus_pct_of_steady/100))) -> 1 | J7: =IF(J$4<1+opt_start_delay,0,IF(J$4=1+opt_start_delay,ramp_year1_pct_of_steady/100,IF(J$4=2+opt_start_delay,ramp_year2_pct_of_steady/100,ramp_year3plus_pct_of_steady/100))) -> 1 | ... M7: =IF(M$4<1+opt_start_delay,0,IF(M$4=1+opt_start_delay,ramp_year1_pct_of_steady/100,IF(M$4=2+opt_start_delay,ramp_year2_pct_of_steady/100,ramp_year3plus_pct_of_steady/100))) -> 1
A8: Volume sold | B8: m3 | C8: =output_steady_state*C7 -> 0 | D8: =output_steady_state*D7 -> 35000 | E8: =output_steady_state*E7 -> 55300 | F8: =output_steady_state*F7 -> 70000 | G8: =output_steady_state*G7 -> 70000 | H8: =output_steady_state*H7 -> 70000 | I8: =output_steady_state*I7 -> 70000 | J8: =output_steady_state*J7 -> 70000 | ... M8: =output_steady_state*M7 -> 70000
A9: of which circular mixes (50% coarse RCA) | B9: m3 | C9: =C8*circular_share_of_volume/100 -> 0 | D9: =D8*circular_share_of_volume/100 -> 21000 | E9: =E8*circular_share_of_volume/100 -> 33180 | F9: =F8*circular_share_of_volume/100 -> 42000 | G9: =G8*circular_share_of_volume/100 -> 42000 | H9: =H8*circular_share_of_volume/100 -> 42000 | I9: =I8*circular_share_of_volume/100 -> 42000 | J9: =J8*circular_share_of_volume/100 -> 42000 | ... M9: =M8*circular_share_of_volume/100 -> 42000
A10: of which standard CEM III/B mixes | B10: m3 | C10: =C8-C9 -> 0 | D10: =D8-D9 -> 14000 | E10: =E8-E9 -> 22120 | F10: =F8-F9 -> 28000 | G10: =G8-G9 -> 28000 | H10: =H8-H9 -> 28000 | I10: =I8-I9 -> 28000 | J10: =J8-J9 -> 28000 | ... M10: =M8-M9 -> 28000
A12: Cement price path (CEM III/B, delivered)
A13: Carbon cost in CEM III/B price (ETS/CBAM) | B13: EUR/t | C13: =carbon_cost_cem3b_2026 -> 3.8 | D13: =carbon_cost_cem3b_2027 -> 4.3 | E13: =carbon_cost_cem3b_2028 -> 5.2 | F13: =carbon_cost_cem3b_2029 -> 7.4 | G13: =carbon_cost_cem3b_2030 -> 12.1 | H13: =carbon_cost_cem3b_2031 -> 14.8 | I13: =carbon_cost_cem3b_2032 -> 17.9 | J13: =carbon_cost_cem3b_2033 -> 21.5 | K13: =carbon_cost_cem3b_2034 -> 25.6 | L13: =carbon_cost_cem3b_2035 -> 25.6 | M13: =carbon_cost_cem3b_2036 -> 25.6
A14: Slag-scarcity uplift from 2031 | B14: EUR/t | C14: =IF(C$3>=2031,cem3b_slag_scarcity_uplift_2031plus/100*price_cem3b_2026_delivered,0) -> 0 | D14: =IF(D$3>=2031,cem3b_slag_scarcity_uplift_2031plus/100*price_cem3b_2026_delivered,0) -> 0 | E14: =IF(E$3>=2031,cem3b_slag_scarcity_uplift_2031plus/100*price_cem3b_2026_delivered,0) -> 0 | F14: =IF(F$3>=2031,cem3b_slag_scarcity_uplift_2031plus/100*price_cem3b_2026_delivered,0) -> 0 | G14: =IF(G$3>=2031,cem3b_slag_scarcity_uplift_2031plus/100*price_cem3b_2026_delivered,0) -> 0 | H14: =IF(H$3>=2031,cem3b_slag_scarcity_uplift_2031plus/100*price_cem3b_2026_delivered,0) -> 11 | I14: =IF(I$3>=2031,cem3b_slag_scarcity_uplift_2031plus/100*price_cem3b_2026_delivered,0) -> 11 | J14: =IF(J$3>=2031,cem3b_slag_scarcity_uplift_2031plus/100*price_cem3b_2026_delivered,0) -> 11 | ... M14: =IF(M$3>=2031,cem3b_slag_scarcity_uplift_2031plus/100*price_cem3b_2026_delivered,0) -> 11
A15: CEM III/B price | B15: EUR/t | C15: =price_cem3b_2026_delivered+cement_carbon_passthrough/100*(C13-$C$13)+C14 -> 110 | D15: =price_cem3b_2026_delivered+cement_carbon_passthrough/100*(D13-$C$13)+D14 -> 110.425 | E15: =price_cem3b_2026_delivered+cement_carbon_passthrough/100*(E13-$C$13)+E14 -> 111.19 | F15: =price_cem3b_2026_delivered+cement_carbon_passthrough/100*(F13-$C$13)+F14 -> 113.06 | G15: =price_cem3b_2026_delivered+cement_carbon_passthrough/100*(G13-$C$13)+G14 -> 117.055 | H15: =price_cem3b_2026_delivered+cement_carbon_passthrough/100*(H13-$C$13)+H14 -> 130.35 | I15: =price_cem3b_2026_delivered+cement_carbon_passthrough/100*(I13-$C$13)+I14 -> 132.985 | J15: =price_cem3b_2026_delivered+cement_carbon_passthrough/100*(J13-$C$13)+J14 -> 136.045 | ... M15: =price_cem3b_2026_delivered+cement_carbon_passthrough/100*(M13-$C$13)+M14 -> 139.53
A16: Market-wide binder cost increase vs 2026 (avg mix) | B16: EUR/m3 | C16: =mix_plant_avg_binder_conv/1000*(C15-price_cem3b_2026_delivered) -> 0 | D16: =mix_plant_avg_binder_conv/1000*(D15-price_cem3b_2026_delivered) -> 0.13175 | E16: =mix_plant_avg_binder_conv/1000*(E15-price_cem3b_2026_delivered) -> 0.3689 | F16: =mix_plant_avg_binder_conv/1000*(F15-price_cem3b_2026_delivered) -> 0.9486 | G16: =mix_plant_avg_binder_conv/1000*(G15-price_cem3b_2026_delivered) -> 2.18705 | H16: =mix_plant_avg_binder_conv/1000*(H15-price_cem3b_2026_delivered) -> 6.3085 | I16: =mix_plant_avg_binder_conv/1000*(I15-price_cem3b_2026_delivered) -> 7.12535 | J16: =mix_plant_avg_binder_conv/1000*(J15-price_cem3b_2026_delivered) -> 8.07395 | ... M16: =mix_plant_avg_binder_conv/1000*(M15-price_cem3b_2026_delivered) -> 9.1543
A18: Prices (delivered, plant average)
A19: Market price, plant average (incl. pass-through of binder cost) | B19: EUR/m3 | C19: =price_plant_avg_all_classes*(1+price_real_escalation/100)^C$4+concrete_price_passthrough_of_market_binder_cost/100*C16+opt_price_delta_per_m3 -> 135 | D19: =price_plant_avg_all_classes*(1+price_real_escalation/100)^D$4+concrete_price_passthrough_of_market_binder_cost/100*D16+opt_price_delta_per_m3 -> 135.1054 | E19: =price_plant_avg_all_classes*(1+price_real_escalation/100)^E$4+concrete_price_passthrough_of_market_binder_cost/100*E16+opt_price_delta_per_m3 -> 135.29512 | F19: =price_plant_avg_all_classes*(1+price_real_escalation/100)^F$4+concrete_price_passthrough_of_market_binder_cost/100*F16+opt_price_delta_per_m3 -> 135.75888 | G19: =price_plant_avg_all_classes*(1+price_real_escalation/100)^G$4+concrete_price_passthrough_of_market_binder_cost/100*G16+opt_price_delta_per_m3 -> 136.74964 | H19: =price_plant_avg_all_classes*(1+price_real_escalation/100)^H$4+concrete_price_passthrough_of_market_binder_cost/100*H16+opt_price_delta_per_m3 -> 140.0468 | I19: =price_plant_avg_all_classes*(1+price_real_escalation/100)^I$4+concrete_price_passthrough_of_market_binder_cost/100*I16+opt_price_delta_per_m3 -> 140.70028 | J19: =price_plant_avg_all_classes*(1+price_real_escalation/100)^J$4+concrete_price_passthrough_of_market_binder_cost/100*J16+opt_price_delta_per_m3 -> 141.45916 | ... M19: =price_plant_avg_all_classes*(1+price_real_escalation/100)^M$4+concrete_price_passthrough_of_market_binder_cost/100*M16+opt_price_delta_per_m3 -> 142.32344
A20: Blended green premium on circular volume | B20: % | C20: =public_share_of_sales/100*green_premium_public/100+(1-public_share_of_sales/100)*green_premium_private/100 -> 0.012
A21: Price circular mixes (+ option: circular-only delta from its start year) | B21: EUR/m3 | C21: =C19*(1+$C$20)+IF(C$3>=opt_circ_delta_start_year,opt_circ_price_delta_per_m3,0) -> 136.62 | D21: =D19*(1+$C$20)+IF(D$3>=opt_circ_delta_start_year,opt_circ_price_delta_per_m3,0) -> 136.72666 | E21: =E19*(1+$C$20)+IF(E$3>=opt_circ_delta_start_year,opt_circ_price_delta_per_m3,0) -> 136.91866 | F21: =F19*(1+$C$20)+IF(F$3>=opt_circ_delta_start_year,opt_circ_price_delta_per_m3,0) -> 137.38799 | G21: =G19*(1+$C$20)+IF(G$3>=opt_circ_delta_start_year,opt_circ_price_delta_per_m3,0) -> 138.39064 | H21: =H19*(1+$C$20)+IF(H$3>=opt_circ_delta_start_year,opt_circ_price_delta_per_m3,0) -> 141.72736 | I21: =I19*(1+$C$20)+IF(I$3>=opt_circ_delta_start_year,opt_circ_price_delta_per_m3,0) -> 142.38868 | J21: =J19*(1+$C$20)+IF(J$3>=opt_circ_delta_start_year,opt_circ_price_delta_per_m3,0) -> 143.15667 | ... M21: =M19*(1+$C$20)+IF(M$3>=opt_circ_delta_start_year,opt_circ_price_delta_per_m3,0) -> 144.03132
A22: Price standard mixes | B22: EUR/m3 | C22: =C19 -> 135 | D22: =D19 -> 135.1054 | E22: =E19 -> 135.29512 | F22: =F19 -> 135.75888 | G22: =G19 -> 136.74964 | H22: =H19 -> 140.0468 | I22: =I19 -> 140.70028 | J22: =J19 -> 141.45916 | ... M22: =M19 -> 142.32344
A24: Revenue
A25: Revenue circular mixes | B25: EUR | C25: =C9*C21 -> 0 | D25: =D9*D21 -> 2871260 | E25: =E9*E21 -> 4542961.2 | F25: =F9*F21 -> 5770295.4 | G25: =G9*G21 -> 5812406.7 | H25: =H9*H21 -> 5952549.2 | I25: =I9*I21 -> 5980324.7 | J25: =J9*J21 -> 6012580.1 | ... M25: =M9*M21 -> 6049315.5
A26: Revenue standard mixes | B26: EUR | C26: =C10*C22 -> 0 | D26: =D10*D22 -> 1891475.6 | E26: =E10*E22 -> 2992728.1 | F26: =F10*F22 -> 3801248.6 | G26: =G10*G22 -> 3828989.9 | H26: =H10*H22 -> 3921310.4 | I26: =I10*I22 -> 3939607.8 | J26: =J10*J22 -> 3960856.5 | ... M26: =M10*M22 -> 3985056.3
A27: Option hook: extra revenue | B27: EUR | C27: =IF(C$4>=1+opt_start_delay,opt_extra_revenue_per_yr,0) -> 0 | D27: =IF(D$4>=1+opt_start_delay,opt_extra_revenue_per_yr,0) -> 0 | E27: =IF(E$4>=1+opt_start_delay,opt_extra_revenue_per_yr,0) -> 0 | F27: =IF(F$4>=1+opt_start_delay,opt_extra_revenue_per_yr,0) -> 0 | G27: =IF(G$4>=1+opt_start_delay,opt_extra_revenue_per_yr,0) -> 0 | H27: =IF(H$4>=1+opt_start_delay,opt_extra_revenue_per_yr,0) -> 0 | I27: =IF(I$4>=1+opt_start_delay,opt_extra_revenue_per_yr,0) -> 0 | J27: =IF(J$4>=1+opt_start_delay,opt_extra_revenue_per_yr,0) -> 0 | ... M27: =IF(M$4>=1+opt_start_delay,opt_extra_revenue_per_yr,0) -> 0
A29: Option A+B: on-site rubble acceptance and crushing (0 unless opt_crusher_on = 1)
A30: Crushing active (operating year and >= crusher start year) | B30: - | C30: =opt_crusher_on*IF(C$4>=1+opt_start_delay,1,0)*IF(C$3>=opt_crusher_start_year,1,0) -> 0 | D30: =opt_crusher_on*IF(D$4>=1+opt_start_delay,1,0)*IF(D$3>=opt_crusher_start_year,1,0) -> 0 | E30: =opt_crusher_on*IF(E$4>=1+opt_start_delay,1,0)*IF(E$3>=opt_crusher_start_year,1,0) -> 0 | F30: =opt_crusher_on*IF(F$4>=1+opt_start_delay,1,0)*IF(F$3>=opt_crusher_start_year,1,0) -> 0 | G30: =opt_crusher_on*IF(G$4>=1+opt_start_delay,1,0)*IF(G$3>=opt_crusher_start_year,1,0) -> 0 | H30: =opt_crusher_on*IF(H$4>=1+opt_start_delay,1,0)*IF(H$3>=opt_crusher_start_year,1,0) -> 0 | I30: =opt_crusher_on*IF(I$4>=1+opt_start_delay,1,0)*IF(I$3>=opt_crusher_start_year,1,0) -> 0 | J30: =opt_crusher_on*IF(J$4>=1+opt_start_delay,1,0)*IF(J$3>=opt_crusher_start_year,1,0) -> 0 | ... M30: =opt_crusher_on*IF(M$4>=1+opt_start_delay,1,0)*IF(M$3>=opt_crusher_start_year,1,0) -> 0
A31: Rubble intake (scales with ramp-up) | B31: t | C31: =opt_rubble_intake_tpy*C7*C30 -> 0 | D31: =opt_rubble_intake_tpy*D7*D30 -> 0 | E31: =opt_rubble_intake_tpy*E7*E30 -> 0 | F31: =opt_rubble_intake_tpy*F7*F30 -> 0 | G31: =opt_rubble_intake_tpy*G7*G30 -> 0 | H31: =opt_rubble_intake_tpy*H7*H30 -> 0 | I31: =opt_rubble_intake_tpy*I7*I30 -> 0 | J31: =opt_rubble_intake_tpy*J7*J30 -> 0 | ... M31: =opt_rubble_intake_tpy*M7*M30 -> 0
A32: Coarse RCA produced | B32: t | C32: =C31*hybrid_yield_coarse/100 -> 0 | D32: =D31*hybrid_yield_coarse/100 -> 0 | E32: =E31*hybrid_yield_coarse/100 -> 0 | F32: =F31*hybrid_yield_coarse/100 -> 0 | G32: =G31*hybrid_yield_coarse/100 -> 0 | H32: =H31*hybrid_yield_coarse/100 -> 0 | I32: =I31*hybrid_yield_coarse/100 -> 0 | J32: =J31*hybrid_yield_coarse/100 -> 0 | ... M32: =M31*hybrid_yield_coarse/100 -> 0
A33: Coarse RCA needed by the plant | B33: t | C33: =C9*mix_circ_rca_coarse/1000+C10*mix_conv_cem3b_rca_coarse/1000 -> 0 | D33: =D9*mix_circ_rca_coarse/1000+D10*mix_conv_cem3b_rca_coarse/1000 -> 11760 | E33: =E9*mix_circ_rca_coarse/1000+E10*mix_conv_cem3b_rca_coarse/1000 -> 18580.8 | F33: =F9*mix_circ_rca_coarse/1000+F10*mix_conv_cem3b_rca_coarse/1000 -> 23520 | G33: =G9*mix_circ_rca_coarse/1000+G10*mix_conv_cem3b_rca_coarse/1000 -> 23520 | H33: =H9*mix_circ_rca_coarse/1000+H10*mix_conv_cem3b_rca_coarse/1000 -> 23520 | I33: =I9*mix_circ_rca_coarse/1000+I10*mix_conv_cem3b_rca_coarse/1000 -> 23520 | J33: =J9*mix_circ_rca_coarse/1000+J10*mix_conv_cem3b_rca_coarse/1000 -> 23520 | ... M33: =M9*mix_circ_rca_coarse/1000+M10*mix_conv_cem3b_rca_coarse/1000 -> 23520
A34: Own RCA used in the plant (replaces purchased RCA) | B34: t | C34: =MIN(C32,C33) -> 0 | D34: =MIN(D32,D33) -> 0 | E34: =MIN(E32,E33) -> 0 | F34: =MIN(F32,F33) -> 0 | G34: =MIN(G32,G33) -> 0 | H34: =MIN(H32,H33) -> 0 | I34: =MIN(I32,I33) -> 0 | J34: =MIN(J32,J33) -> 0 | ... M34: =MIN(M32,M33) -> 0
A35: Surplus coarse RCA sold ex-works | B35: t | C35: =C32-C34 -> 0 | D35: =D32-D34 -> 0 | E35: =E32-E34 -> 0 | F35: =F32-F34 -> 0 | G35: =G32-G34 -> 0 | H35: =H32-H34 -> 0 | I35: =I32-I34 -> 0 | J35: =J32-J34 -> 0 | ... M35: =M32-M34 -> 0
A36: Gate fee received | B36: EUR | C36: =C31*hybrid_gate_fee_received -> 0 | D36: =D31*hybrid_gate_fee_received -> 0 | E36: =E31*hybrid_gate_fee_received -> 0 | F36: =F31*hybrid_gate_fee_received -> 0 | G36: =G31*hybrid_gate_fee_received -> 0 | H36: =H31*hybrid_gate_fee_received -> 0 | I36: =I31*hybrid_gate_fee_received -> 0 | J36: =J31*hybrid_gate_fee_received -> 0 | ... M36: =M31*hybrid_gate_fee_received -> 0
A37: Crusher sand 0/4 sold | B37: EUR | C37: =C31*hybrid_yield_sand_0_4/100*hybrid_price_crusher_sand -> 0 | D37: =D31*hybrid_yield_sand_0_4/100*hybrid_price_crusher_sand -> 0 | E37: =E31*hybrid_yield_sand_0_4/100*hybrid_price_crusher_sand -> 0 | F37: =F31*hybrid_yield_sand_0_4/100*hybrid_price_crusher_sand -> 0 | G37: =G31*hybrid_yield_sand_0_4/100*hybrid_price_crusher_sand -> 0 | H37: =H31*hybrid_yield_sand_0_4/100*hybrid_price_crusher_sand -> 0 | I37: =I31*hybrid_yield_sand_0_4/100*hybrid_price_crusher_sand -> 0 | J37: =J31*hybrid_yield_sand_0_4/100*hybrid_price_crusher_sand -> 0 | ... M37: =M31*hybrid_yield_sand_0_4/100*hybrid_price_crusher_sand -> 0
A38: Steel scrap sold | B38: EUR | C38: =C31*hybrid_yield_steel/100*hybrid_price_steel_scrap -> 0 | D38: =D31*hybrid_yield_steel/100*hybrid_price_steel_scrap -> 0 | E38: =E31*hybrid_yield_steel/100*hybrid_price_steel_scrap -> 0 | F38: =F31*hybrid_yield_steel/100*hybrid_price_steel_scrap -> 0 | G38: =G31*hybrid_yield_steel/100*hybrid_price_steel_scrap -> 0 | H38: =H31*hybrid_yield_steel/100*hybrid_price_steel_scrap -> 0 | I38: =I31*hybrid_yield_steel/100*hybrid_price_steel_scrap -> 0 | J38: =J31*hybrid_yield_steel/100*hybrid_price_steel_scrap -> 0 | ... M38: =M31*hybrid_yield_steel/100*hybrid_price_steel_scrap -> 0
A39: Surplus RCA sold (at RCA ex-works price) | B39: EUR | C39: =C35*price_rca_coarse_exworks -> 0 | D39: =D35*price_rca_coarse_exworks -> 0 | E39: =E35*price_rca_coarse_exworks -> 0 | F39: =F35*price_rca_coarse_exworks -> 0 | G39: =G35*price_rca_coarse_exworks -> 0 | H39: =H35*price_rca_coarse_exworks -> 0 | I39: =I35*price_rca_coarse_exworks -> 0 | J39: =J35*price_rca_coarse_exworks -> 0 | ... M39: =M35*price_rca_coarse_exworks -> 0
A40: Revenue on-site crushing | B40: EUR | C40: =C36+C37+C38+C39 -> 0 | D40: =D36+D37+D38+D39 -> 0 | E40: =E36+E37+E38+E39 -> 0 | F40: =F36+F37+F38+F39 -> 0 | G40: =G36+G37+G38+G39 -> 0 | H40: =H36+H37+H38+H39 -> 0 | I40: =I36+I37+I38+I39 -> 0 | J40: =J36+J37+J38+J39 -> 0 | ... M40: =M36+M37+M38+M39 -> 0
A42: Total revenue | B42: EUR | C42: =C25+C26+C27+C40 -> 0 | D42: =D25+D26+D27+D40 -> 4762735.6 | E42: =E25+E26+E27+E40 -> 7535689.2 | F42: =F25+F26+F27+F40 -> 9571544.1 | G42: =G25+G26+G27+G40 -> 9641396.6 | H42: =H25+H26+H27+H40 -> 9873859.6 | I42: =I25+I26+I27+I40 -> 9919932.5 | J42: =J25+J26+J27+J40 -> 9973436.6 | ... M42: =M25+M26+M27+M40 -> 10034372
A43: Memo: average realised price | B43: EUR/m3 | C43: =IF(C8>0,(C25+C26)/C8,0) -> 0 | D43: =IF(D8>0,(D25+D26)/D8,0) -> 136.07816 | E43: =IF(E8>0,(E25+E26)/E8,0) -> 136.26924 | F43: =IF(F8>0,(F25+F26)/F8,0) -> 136.73634 | G43: =IF(G8>0,(G25+G26)/G8,0) -> 137.73424 | H43: =IF(H8>0,(H25+H26)/H8,0) -> 141.05514 | I43: =IF(I8>0,(I25+I26)/I8,0) -> 141.71332 | J43: =IF(J8>0,(J25+J26)/J8,0) -> 142.47767 | ... M43: =IF(M8>0,(M25+M26)/M8,0) -> 143.34817

Sheet Opex
A1: Operating costs (EUR, real 2026)
A2: Materials priced per m3 from the recipes; fixed costs from operating year 1.
A3: Year | B3: unit | C3: =2026+C4 -> 2026 | D3: =2026+D4 -> 2027 | E3: =2026+E4 -> 2028 | F3: =2026+F4 -> 2029 | G3: =2026+G4 -> 2030 | H3: =2026+H4 -> 2031 | I3: =2026+I4 -> 2032 | J3: =2026+J4 -> 2033 | ... M3: =2026+M4 -> 2036
A4: t (year index) | C4: 0 | D4: 1 | E4: 2 | F4: 3 | G4: 4 | H4: 5 | I4: 6 | J4: 7 | K4: 8 | L4: 9 | M4: 10
A6: Unit inputs
A7: RCA coarse delivered = ex-works + km x rate + handling | B7: EUR/t | C7: =price_rca_coarse_exworks+rca_transport_distance*road_haulage_rate+road_handling_per_t -> 24.5
A8: RCA lot testing + handling/pre-wetting (circular only) | B8: EUR/m3 | C8: =mix_circ_rca_coarse/1000*(rca_lot_testing+rca_handling_prewetting) -> 1.008
A9: Energy (electricity + diesel) | B9: EUR/m3 | C9: =electricity_use*price_electricity+diesel_use_plant*price_diesel -> 0.906
A10: Delivery by subcontracted truck mixer | B10: EUR/m3 | C10: =delivery_fixed_per_m3+delivery_variable_per_km_oneway*delivery_avg_distance_oneway -> 19
A12: Raw materials per m3 - CIRCULAR mix (plant-average binder)
A13: Cement CEM III/B | B13: EUR/m3 | C13: =mix_plant_avg_binder_circ/1000*Revenue!C15 -> 35.75 | D13: =mix_plant_avg_binder_circ/1000*Revenue!D15 -> 35.888125 | E13: =mix_plant_avg_binder_circ/1000*Revenue!E15 -> 36.13675 | F13: =mix_plant_avg_binder_circ/1000*Revenue!F15 -> 36.7445 | G13: =mix_plant_avg_binder_circ/1000*Revenue!G15 -> 38.042875 | H13: =mix_plant_avg_binder_circ/1000*Revenue!H15 -> 42.36375 | I13: =mix_plant_avg_binder_circ/1000*Revenue!I15 -> 43.220125 | J13: =mix_plant_avg_binder_circ/1000*Revenue!J15 -> 44.214625 | ... M13: =mix_plant_avg_binder_circ/1000*Revenue!M15 -> 45.34725
A14: Gravel | B14: EUR/m3 | C14: =mix_circ_gravel/1000*price_gravel_delivered -> 19.84 | D14: =mix_circ_gravel/1000*price_gravel_delivered -> 19.84 | E14: =mix_circ_gravel/1000*price_gravel_delivered -> 19.84 | F14: =mix_circ_gravel/1000*price_gravel_delivered -> 19.84 | G14: =mix_circ_gravel/1000*price_gravel_delivered -> 19.84 | H14: =mix_circ_gravel/1000*price_gravel_delivered -> 19.84 | I14: =mix_circ_gravel/1000*price_gravel_delivered -> 19.84 | J14: =mix_circ_gravel/1000*price_gravel_delivered -> 19.84 | ... M14: =mix_circ_gravel/1000*price_gravel_delivered -> 19.84
A15: Recycled aggregate (coarse delivered + fine ex-works) | B15: EUR/m3 | C15: =mix_circ_rca_coarse/1000*$C$7+mix_circ_rca_fine/1000*price_rca_fine_exworks -> 13.72 | D15: =mix_circ_rca_coarse/1000*$C$7+mix_circ_rca_fine/1000*price_rca_fine_exworks -> 13.72 | E15: =mix_circ_rca_coarse/1000*$C$7+mix_circ_rca_fine/1000*price_rca_fine_exworks -> 13.72 | F15: =mix_circ_rca_coarse/1000*$C$7+mix_circ_rca_fine/1000*price_rca_fine_exworks -> 13.72 | G15: =mix_circ_rca_coarse/1000*$C$7+mix_circ_rca_fine/1000*price_rca_fine_exworks -> 13.72 | H15: =mix_circ_rca_coarse/1000*$C$7+mix_circ_rca_fine/1000*price_rca_fine_exworks -> 13.72 | I15: =mix_circ_rca_coarse/1000*$C$7+mix_circ_rca_fine/1000*price_rca_fine_exworks -> 13.72 | J15: =mix_circ_rca_coarse/1000*$C$7+mix_circ_rca_fine/1000*price_rca_fine_exworks -> 13.72 | ... M15: =mix_circ_rca_coarse/1000*$C$7+mix_circ_rca_fine/1000*price_rca_fine_exworks -> 13.72
A16: Sand | B16: EUR/m3 | C16: =mix_circ_sand/1000*price_sand_delivered -> 11.97 | D16: =mix_circ_sand/1000*price_sand_delivered -> 11.97 | E16: =mix_circ_sand/1000*price_sand_delivered -> 11.97 | F16: =mix_circ_sand/1000*price_sand_delivered -> 11.97 | G16: =mix_circ_sand/1000*price_sand_delivered -> 11.97 | H16: =mix_circ_sand/1000*price_sand_delivered -> 11.97 | I16: =mix_circ_sand/1000*price_sand_delivered -> 11.97 | J16: =mix_circ_sand/1000*price_sand_delivered -> 11.97 | ... M16: =mix_circ_sand/1000*price_sand_delivered -> 11.97
A17: Superplasticiser | B17: EUR/m3 | C17: =mix_plant_avg_binder_circ*mix_circ_superplasticiser_pct_binder/100*price_superplasticiser -> 4.095 | D17: =mix_plant_avg_binder_circ*mix_circ_superplasticiser_pct_binder/100*price_superplasticiser -> 4.095 | E17: =mix_plant_avg_binder_circ*mix_circ_superplasticiser_pct_binder/100*price_superplasticiser -> 4.095 | F17: =mix_plant_avg_binder_circ*mix_circ_superplasticiser_pct_binder/100*price_superplasticiser -> 4.095 | G17: =mix_plant_avg_binder_circ*mix_circ_superplasticiser_pct_binder/100*price_superplasticiser -> 4.095 | H17: =mix_plant_avg_binder_circ*mix_circ_superplasticiser_pct_binder/100*price_superplasticiser -> 4.095 | I17: =mix_plant_avg_binder_circ*mix_circ_superplasticiser_pct_binder/100*price_superplasticiser -> 4.095 | J17: =mix_plant_avg_binder_circ*mix_circ_superplasticiser_pct_binder/100*price_superplasticiser -> 4.095 | ... M17: =mix_plant_avg_binder_circ*mix_circ_superplasticiser_pct_binder/100*price_superplasticiser -> 4.095
A18: Water (effective + absorption) | B18: EUR/m3 | C18: =(mix_circ_water_effective+mix_circ_water_absorption)/1000*price_water -> 0.2316 | D18: =(mix_circ_water_effective+mix_circ_water_absorption)/1000*price_water -> 0.2316 | E18: =(mix_circ_water_effective+mix_circ_water_absorption)/1000*price_water -> 0.2316 | F18: =(mix_circ_water_effective+mix_circ_water_absorption)/1000*price_water -> 0.2316 | G18: =(mix_circ_water_effective+mix_circ_water_absorption)/1000*price_water -> 0.2316 | H18: =(mix_circ_water_effective+mix_circ_water_absorption)/1000*price_water -> 0.2316 | I18: =(mix_circ_water_effective+mix_circ_water_absorption)/1000*price_water -> 0.2316 | J18: =(mix_circ_water_effective+mix_circ_water_absorption)/1000*price_water -> 0.2316 | ... M18: =(mix_circ_water_effective+mix_circ_water_absorption)/1000*price_water -> 0.2316
A19: Raw materials circular | B19: EUR/m3 | C19: =C13+C14+C15+C16+C17+C18 -> 85.6066 | D19: =D13+D14+D15+D16+D17+D18 -> 85.744725 | E19: =E13+E14+E15+E16+E17+E18 -> 85.99335 | F19: =F13+F14+F15+F16+F17+F18 -> 86.6011 | G19: =G13+G14+G15+G16+G17+G18 -> 87.899475 | H19: =H13+H14+H15+H16+H17+H18 -> 92.22035 | I19: =I13+I14+I15+I16+I17+I18 -> 93.076725 | J19: =J13+J14+J15+J16+J17+J18 -> 94.071225 | ... M19: =M13+M14+M15+M16+M17+M18 -> 95.20385
A20: Raw materials per m3 - STANDARD CEM III/B mix
A21: Cement CEM III/B | B21: EUR/m3 | C21: =mix_plant_avg_binder_conv/1000*Revenue!C15 -> 34.1 | D21: =mix_plant_avg_binder_conv/1000*Revenue!D15 -> 34.23175 | E21: =mix_plant_avg_binder_conv/1000*Revenue!E15 -> 34.4689 | F21: =mix_plant_avg_binder_conv/1000*Revenue!F15 -> 35.0486 | G21: =mix_plant_avg_binder_conv/1000*Revenue!G15 -> 36.28705 | H21: =mix_plant_avg_binder_conv/1000*Revenue!H15 -> 40.4085 | I21: =mix_plant_avg_binder_conv/1000*Revenue!I15 -> 41.22535 | J21: =mix_plant_avg_binder_conv/1000*Revenue!J15 -> 42.17395 | ... M21: =mix_plant_avg_binder_conv/1000*Revenue!M15 -> 43.2543
A22: Gravel | B22: EUR/m3 | C22: =mix_conv_cem3b_gravel/1000*price_gravel_delivered -> 39.712 | D22: =mix_conv_cem3b_gravel/1000*price_gravel_delivered -> 39.712 | E22: =mix_conv_cem3b_gravel/1000*price_gravel_delivered -> 39.712 | F22: =mix_conv_cem3b_gravel/1000*price_gravel_delivered -> 39.712 | G22: =mix_conv_cem3b_gravel/1000*price_gravel_delivered -> 39.712 | H22: =mix_conv_cem3b_gravel/1000*price_gravel_delivered -> 39.712 | I22: =mix_conv_cem3b_gravel/1000*price_gravel_delivered -> 39.712 | J22: =mix_conv_cem3b_gravel/1000*price_gravel_delivered -> 39.712 | ... M22: =mix_conv_cem3b_gravel/1000*price_gravel_delivered -> 39.712
A23: Recycled aggregate | B23: EUR/m3 | C23: =mix_conv_cem3b_rca_coarse/1000*$C$7 -> 0 | D23: =mix_conv_cem3b_rca_coarse/1000*$C$7 -> 0 | E23: =mix_conv_cem3b_rca_coarse/1000*$C$7 -> 0 | F23: =mix_conv_cem3b_rca_coarse/1000*$C$7 -> 0 | G23: =mix_conv_cem3b_rca_coarse/1000*$C$7 -> 0 | H23: =mix_conv_cem3b_rca_coarse/1000*$C$7 -> 0 | I23: =mix_conv_cem3b_rca_coarse/1000*$C$7 -> 0 | J23: =mix_conv_cem3b_rca_coarse/1000*$C$7 -> 0 | ... M23: =mix_conv_cem3b_rca_coarse/1000*$C$7 -> 0
A24: Sand | B24: EUR/m3 | C24: =mix_conv_cem3b_sand/1000*price_sand_delivered -> 12.141 | D24: =mix_conv_cem3b_sand/1000*price_sand_delivered -> 12.141 | E24: =mix_conv_cem3b_sand/1000*price_sand_delivered -> 12.141 | F24: =mix_conv_cem3b_sand/1000*price_sand_delivered -> 12.141 | G24: =mix_conv_cem3b_sand/1000*price_sand_delivered -> 12.141 | H24: =mix_conv_cem3b_sand/1000*price_sand_delivered -> 12.141 | I24: =mix_conv_cem3b_sand/1000*price_sand_delivered -> 12.141 | J24: =mix_conv_cem3b_sand/1000*price_sand_delivered -> 12.141 | ... M24: =mix_conv_cem3b_sand/1000*price_sand_delivered -> 12.141
A25: Superplasticiser | B25: EUR/m3 | C25: =mix_plant_avg_binder_conv*mix_conv_cem3b_superplasticiser_pct_binder/100*price_superplasticiser -> 3.038 | D25: =mix_plant_avg_binder_conv*mix_conv_cem3b_superplasticiser_pct_binder/100*price_superplasticiser -> 3.038 | E25: =mix_plant_avg_binder_conv*mix_conv_cem3b_superplasticiser_pct_binder/100*price_superplasticiser -> 3.038 | F25: =mix_plant_avg_binder_conv*mix_conv_cem3b_superplasticiser_pct_binder/100*price_superplasticiser -> 3.038 | G25: =mix_plant_avg_binder_conv*mix_conv_cem3b_superplasticiser_pct_binder/100*price_superplasticiser -> 3.038 | H25: =mix_plant_avg_binder_conv*mix_conv_cem3b_superplasticiser_pct_binder/100*price_superplasticiser -> 3.038 | I25: =mix_plant_avg_binder_conv*mix_conv_cem3b_superplasticiser_pct_binder/100*price_superplasticiser -> 3.038 | J25: =mix_plant_avg_binder_conv*mix_conv_cem3b_superplasticiser_pct_binder/100*price_superplasticiser -> 3.038 | ... M25: =mix_plant_avg_binder_conv*mix_conv_cem3b_superplasticiser_pct_binder/100*price_superplasticiser -> 3.038
A26: Water | B26: EUR/m3 | C26: =(mix_conv_cem3b_water_effective+mix_conv_cem3b_water_absorption)/1000*price_water -> 0.198 | D26: =(mix_conv_cem3b_water_effective+mix_conv_cem3b_water_absorption)/1000*price_water -> 0.198 | E26: =(mix_conv_cem3b_water_effective+mix_conv_cem3b_water_absorption)/1000*price_water -> 0.198 | F26: =(mix_conv_cem3b_water_effective+mix_conv_cem3b_water_absorption)/1000*price_water -> 0.198 | G26: =(mix_conv_cem3b_water_effective+mix_conv_cem3b_water_absorption)/1000*price_water -> 0.198 | H26: =(mix_conv_cem3b_water_effective+mix_conv_cem3b_water_absorption)/1000*price_water -> 0.198 | I26: =(mix_conv_cem3b_water_effective+mix_conv_cem3b_water_absorption)/1000*price_water -> 0.198 | J26: =(mix_conv_cem3b_water_effective+mix_conv_cem3b_water_absorption)/1000*price_water -> 0.198 | ... M26: =(mix_conv_cem3b_water_effective+mix_conv_cem3b_water_absorption)/1000*price_water -> 0.198
A27: Raw materials standard | B27: EUR/m3 | C27: =C21+C22+C23+C24+C25+C26 -> 89.189 | D27: =D21+D22+D23+D24+D25+D26 -> 89.32075 | E27: =E21+E22+E23+E24+E25+E26 -> 89.5579 | F27: =F21+F22+F23+F24+F25+F26 -> 90.1376 | G27: =G21+G22+G23+G24+G25+G26 -> 91.37605 | H27: =H21+H22+H23+H24+H25+H26 -> 95.4975 | I27: =I21+I22+I23+I24+I25+I26 -> 96.31435 | J27: =J21+J22+J23+J24+J25+J26 -> 97.26295 | ... M27: =M21+M22+M23+M24+M25+M26 -> 98.3433
A29: Indices
A30: Operating year flag | B30: - | C30: =IF(C$4>=1+opt_start_delay,1,0) -> 0 | D30: =IF(D$4>=1+opt_start_delay,1,0) -> 1 | E30: =IF(E$4>=1+opt_start_delay,1,0) -> 1 | F30: =IF(F$4>=1+opt_start_delay,1,0) -> 1 | G30: =IF(G$4>=1+opt_start_delay,1,0) -> 1 | H30: =IF(H$4>=1+opt_start_delay,1,0) -> 1 | I30: =IF(I$4>=1+opt_start_delay,1,0) -> 1 | J30: =IF(J$4>=1+opt_start_delay,1,0) -> 1 | ... M30: =IF(M$4>=1+opt_start_delay,1,0) -> 1
A31: Real wage index | B31: x | C31: =(1+real_wage_growth/100)^C$4 -> 1 | D31: =(1+real_wage_growth/100)^D$4 -> 1.005 | E31: =(1+real_wage_growth/100)^E$4 -> 1.010025 | F31: =(1+real_wage_growth/100)^F$4 -> 1.0150751 | G31: =(1+real_wage_growth/100)^G$4 -> 1.0201505 | H31: =(1+real_wage_growth/100)^H$4 -> 1.0252513 | I31: =(1+real_wage_growth/100)^I$4 -> 1.0303775 | J31: =(1+real_wage_growth/100)^J$4 -> 1.0355294 | ... M31: =(1+real_wage_growth/100)^M$4 -> 1.0511401
A33: Variable costs (EUR/yr)
A34: Raw materials | B34: EUR | C34: =Revenue!C9*C19+Revenue!C10*C27 -> 0 | D34: =Revenue!D9*D19+Revenue!D10*D27 -> 3051129.7 | E34: =Revenue!E9*E19+Revenue!E10*E27 -> 4834280.1 | F34: =Revenue!F9*F19+Revenue!F10*F27 -> 6161099 | G34: =Revenue!G9*G19+Revenue!G10*G27 -> 6250307.3 | H34: =Revenue!H9*H19+Revenue!H10*H27 -> 6547184.7 | I34: =Revenue!I9*I19+Revenue!I10*I27 -> 6606024.2 | J34: =Revenue!J9*J19+Revenue!J10*J27 -> 6674354 | ... M34: =Revenue!M9*M19+Revenue!M10*M27 -> 6752174.1
A35: RCA testing & handling | B35: EUR | C35: =Revenue!C9*$C$8 -> 0 | D35: =Revenue!D9*$C$8 -> 21168 | E35: =Revenue!E9*$C$8 -> 33445.44 | F35: =Revenue!F9*$C$8 -> 42336 | G35: =Revenue!G9*$C$8 -> 42336 | H35: =Revenue!H9*$C$8 -> 42336 | I35: =Revenue!I9*$C$8 -> 42336 | J35: =Revenue!J9*$C$8 -> 42336 | ... M35: =Revenue!M9*$C$8 -> 42336
A36: Energy | B36: EUR | C36: =Revenue!C8*$C$9 -> 0 | D36: =Revenue!D8*$C$9 -> 31710 | E36: =Revenue!E8*$C$9 -> 50101.8 | F36: =Revenue!F8*$C$9 -> 63420 | G36: =Revenue!G8*$C$9 -> 63420 | H36: =Revenue!H8*$C$9 -> 63420 | I36: =Revenue!I8*$C$9 -> 63420 | J36: =Revenue!J8*$C$9 -> 63420 | ... M36: =Revenue!M8*$C$9 -> 63420
A37: Delivery (truck mixers) | B37: EUR | C37: =Revenue!C8*$C$10 -> 0 | D37: =Revenue!D8*$C$10 -> 665000 | E37: =Revenue!E8*$C$10 -> 1050700 | F37: =Revenue!F8*$C$10 -> 1330000 | G37: =Revenue!G8*$C$10 -> 1330000 | H37: =Revenue!H8*$C$10 -> 1330000 | I37: =Revenue!I8*$C$10 -> 1330000 | J37: =Revenue!J8*$C$10 -> 1330000 | ... M37: =Revenue!M8*$C$10 -> 1330000
A38: Option hook: variable cost delta | B38: EUR | C38: =Revenue!C8*opt_cost_delta_per_m3 -> 0 | D38: =Revenue!D8*opt_cost_delta_per_m3 -> 0 | E38: =Revenue!E8*opt_cost_delta_per_m3 -> 0 | F38: =Revenue!F8*opt_cost_delta_per_m3 -> 0 | G38: =Revenue!G8*opt_cost_delta_per_m3 -> 0 | H38: =Revenue!H8*opt_cost_delta_per_m3 -> 0 | I38: =Revenue!I8*opt_cost_delta_per_m3 -> 0 | J38: =Revenue!J8*opt_cost_delta_per_m3 -> 0 | ... M38: =Revenue!M8*opt_cost_delta_per_m3 -> 0
A39: Option: circular-only variable cost delta (from its start year) | B39: EUR | C39: =Revenue!C9*IF(C$3>=opt_circ_delta_start_year,1,0)*opt_circ_cost_delta_per_m3 -> 0 | D39: =Revenue!D9*IF(D$3>=opt_circ_delta_start_year,1,0)*opt_circ_cost_delta_per_m3 -> 0 | E39: =Revenue!E9*IF(E$3>=opt_circ_delta_start_year,1,0)*opt_circ_cost_delta_per_m3 -> 0 | F39: =Revenue!F9*IF(F$3>=opt_circ_delta_start_year,1,0)*opt_circ_cost_delta_per_m3 -> 0 | G39: =Revenue!G9*IF(G$3>=opt_circ_delta_start_year,1,0)*opt_circ_cost_delta_per_m3 -> 0 | H39: =Revenue!H9*IF(H$3>=opt_circ_delta_start_year,1,0)*opt_circ_cost_delta_per_m3 -> 0 | I39: =Revenue!I9*IF(I$3>=opt_circ_delta_start_year,1,0)*opt_circ_cost_delta_per_m3 -> 0 | J39: =Revenue!J9*IF(J$3>=opt_circ_delta_start_year,1,0)*opt_circ_cost_delta_per_m3 -> 0 | ... M39: =Revenue!M9*IF(M$3>=opt_circ_delta_start_year,1,0)*opt_circ_cost_delta_per_m3 -> 0
A40: A+B: own RCA replaces purchased RCA (credit) | B40: EUR | C40: =-Revenue!C34*$C$7 -> 0 | D40: =-Revenue!D34*$C$7 -> 0 | E40: =-Revenue!E34*$C$7 -> 0 | F40: =-Revenue!F34*$C$7 -> 0 | G40: =-Revenue!G34*$C$7 -> 0 | H40: =-Revenue!H34*$C$7 -> 0 | I40: =-Revenue!I34*$C$7 -> 0 | J40: =-Revenue!J34*$C$7 -> 0 | ... M40: =-Revenue!M34*$C$7 -> 0
A41: A+B: contaminant disposal | B41: EUR | C41: =Revenue!C31*hybrid_yield_contaminants/100*hybrid_cost_contaminant_disposal -> 0 | D41: =Revenue!D31*hybrid_yield_contaminants/100*hybrid_cost_contaminant_disposal -> 0 | E41: =Revenue!E31*hybrid_yield_contaminants/100*hybrid_cost_contaminant_disposal -> 0 | F41: =Revenue!F31*hybrid_yield_contaminants/100*hybrid_cost_contaminant_disposal -> 0 | G41: =Revenue!G31*hybrid_yield_contaminants/100*hybrid_cost_contaminant_disposal -> 0 | H41: =Revenue!H31*hybrid_yield_contaminants/100*hybrid_cost_contaminant_disposal -> 0 | I41: =Revenue!I31*hybrid_yield_contaminants/100*hybrid_cost_contaminant_disposal -> 0 | J41: =Revenue!J31*hybrid_yield_contaminants/100*hybrid_cost_contaminant_disposal -> 0 | ... M41: =Revenue!M31*hybrid_yield_contaminants/100*hybrid_cost_contaminant_disposal -> 0
A42: A+B: crusher diesel | B42: EUR | C42: =Revenue!C31*hybrid_crusher_diesel*price_diesel -> 0 | D42: =Revenue!D31*hybrid_crusher_diesel*price_diesel -> 0 | E42: =Revenue!E31*hybrid_crusher_diesel*price_diesel -> 0 | F42: =Revenue!F31*hybrid_crusher_diesel*price_diesel -> 0 | G42: =Revenue!G31*hybrid_crusher_diesel*price_diesel -> 0 | H42: =Revenue!H31*hybrid_crusher_diesel*price_diesel -> 0 | I42: =Revenue!I31*hybrid_crusher_diesel*price_diesel -> 0 | J42: =Revenue!J31*hybrid_crusher_diesel*price_diesel -> 0 | ... M42: =Revenue!M31*hybrid_crusher_diesel*price_diesel -> 0
A43: A+B: crusher wear | B43: EUR | C43: =Revenue!C31*hybrid_crusher_wear -> 0 | D43: =Revenue!D31*hybrid_crusher_wear -> 0 | E43: =Revenue!E31*hybrid_crusher_wear -> 0 | F43: =Revenue!F31*hybrid_crusher_wear -> 0 | G43: =Revenue!G31*hybrid_crusher_wear -> 0 | H43: =Revenue!H31*hybrid_crusher_wear -> 0 | I43: =Revenue!I31*hybrid_crusher_wear -> 0 | J43: =Revenue!J31*hybrid_crusher_wear -> 0 | ... M43: =Revenue!M31*hybrid_crusher_wear -> 0
A44: A+B: contract crushing | B44: EUR | C44: =Revenue!C31*opt_crusher_contract_rate -> 0 | D44: =Revenue!D31*opt_crusher_contract_rate -> 0 | E44: =Revenue!E31*opt_crusher_contract_rate -> 0 | F44: =Revenue!F31*opt_crusher_contract_rate -> 0 | G44: =Revenue!G31*opt_crusher_contract_rate -> 0 | H44: =Revenue!H31*opt_crusher_contract_rate -> 0 | I44: =Revenue!I31*opt_crusher_contract_rate -> 0 | J44: =Revenue!J31*opt_crusher_contract_rate -> 0 | ... M44: =Revenue!M31*opt_crusher_contract_rate -> 0
A45: Bad debt | B45: EUR | C45: =Revenue!C42*bad_debt_pct_revenue/100 -> 0 | D45: =Revenue!D42*bad_debt_pct_revenue/100 -> 23813.678 | E45: =Revenue!E42*bad_debt_pct_revenue/100 -> 37678.446 | F45: =Revenue!F42*bad_debt_pct_revenue/100 -> 47857.72 | G45: =Revenue!G42*bad_debt_pct_revenue/100 -> 48206.983 | H45: =Revenue!H42*bad_debt_pct_revenue/100 -> 49369.298 | I45: =Revenue!I42*bad_debt_pct_revenue/100 -> 49599.663 | J45: =Revenue!J42*bad_debt_pct_revenue/100 -> 49867.183 | ... M45: =Revenue!M42*bad_debt_pct_revenue/100 -> 50171.859
A46: Total variable costs | B46: EUR | C46: =C34+C35+C36+C37+C38+C39+C40+C41+C42+C43+C44+C45 -> 0 | D46: =D34+D35+D36+D37+D38+D39+D40+D41+D42+D43+D44+D45 -> 3792821.4 | E46: =E34+E35+E36+E37+E38+E39+E40+E41+E42+E43+E44+E45 -> 6006205.8 | F46: =F34+F35+F36+F37+F38+F39+F40+F41+F42+F43+F44+F45 -> 7644712.7 | G46: =G34+G35+G36+G37+G38+G39+G40+G41+G42+G43+G44+G45 -> 7734270.3 | H46: =H34+H35+H36+H37+H38+H39+H40+H41+H42+H43+H44+H45 -> 8032310 | I46: =I34+I35+I36+I37+I38+I39+I40+I41+I42+I43+I44+I45 -> 8091379.9 | J46: =J34+J35+J36+J37+J38+J39+J40+J41+J42+J43+J44+J45 -> 8159977.2 | ... M46: =M34+M35+M36+M37+M38+M39+M40+M41+M42+M43+M44+M45 -> 8238102
A47: Fixed costs (EUR/yr, from year 1)
A48: Production staff | B48: EUR | C48: =C30*staff_production_fte*cost_per_fte_production*C31 -> 0 | D48: =D30*staff_production_fte*cost_per_fte_production*D31 -> 492450 | E48: =E30*staff_production_fte*cost_per_fte_production*E31 -> 494912.25 | F48: =F30*staff_production_fte*cost_per_fte_production*F31 -> 497386.81 | G48: =G30*staff_production_fte*cost_per_fte_production*G31 -> 499873.75 | H48: =H30*staff_production_fte*cost_per_fte_production*H31 -> 502373.11 | I48: =I30*staff_production_fte*cost_per_fte_production*I31 -> 504884.98 | J48: =J30*staff_production_fte*cost_per_fte_production*J31 -> 507409.4 | ... M48: =M30*staff_production_fte*cost_per_fte_production*M31 -> 515058.66
A49: Maintenance & wear | B49: EUR | C49: =C30*maintenance_pct_of_capex/100*Capex!$C$15 -> 0 | D49: =D30*maintenance_pct_of_capex/100*Capex!$C$15 -> 125000 | E49: =E30*maintenance_pct_of_capex/100*Capex!$C$15 -> 125000 | F49: =F30*maintenance_pct_of_capex/100*Capex!$C$15 -> 125000 | G49: =G30*maintenance_pct_of_capex/100*Capex!$C$15 -> 125000 | H49: =H30*maintenance_pct_of_capex/100*Capex!$C$15 -> 125000 | I49: =I30*maintenance_pct_of_capex/100*Capex!$C$15 -> 125000 | J49: =J30*maintenance_pct_of_capex/100*Capex!$C$15 -> 125000 | ... M49: =M30*maintenance_pct_of_capex/100*Capex!$C$15 -> 125000
A50: Certification & testing (KOMO, CSC, NMD) | B50: EUR | C50: =C30*certification_testing_fixed -> 0 | D50: =D30*certification_testing_fixed -> 50000 | E50: =E30*certification_testing_fixed -> 50000 | F50: =F30*certification_testing_fixed -> 50000 | G50: =G30*certification_testing_fixed -> 50000 | H50: =H30*certification_testing_fixed -> 50000 | I50: =I30*certification_testing_fixed -> 50000 | J50: =J30*certification_testing_fixed -> 50000 | ... M50: =M30*certification_testing_fixed -> 50000
A51: Site lease | B51: EUR | C51: =C30*site_area*site_lease_rate -> 0 | D51: =D30*site_area*site_lease_rate -> 150000 | E51: =E30*site_area*site_lease_rate -> 150000 | F51: =F30*site_area*site_lease_rate -> 150000 | G51: =G30*site_area*site_lease_rate -> 150000 | H51: =H30*site_area*site_lease_rate -> 150000 | I51: =I30*site_area*site_lease_rate -> 150000 | J51: =J30*site_area*site_lease_rate -> 150000 | ... M51: =M30*site_area*site_lease_rate -> 150000
A52: SG&A staff | B52: EUR | C52: =C30*staff_sga_fte*cost_per_fte_sga*C31 -> 0 | D52: =D30*staff_sga_fte*cost_per_fte_sga*D31 -> 271350 | E52: =E30*staff_sga_fte*cost_per_fte_sga*E31 -> 272706.75 | F52: =F30*staff_sga_fte*cost_per_fte_sga*F31 -> 274070.28 | G52: =G30*staff_sga_fte*cost_per_fte_sga*G31 -> 275440.64 | H52: =H30*staff_sga_fte*cost_per_fte_sga*H31 -> 276817.84 | I52: =I30*staff_sga_fte*cost_per_fte_sga*I31 -> 278201.93 | J52: =J30*staff_sga_fte*cost_per_fte_sga*J31 -> 279592.94 | ... M52: =M30*staff_sga_fte*cost_per_fte_sga*M31 -> 283807.84
A53: SG&A non-staff | B53: EUR | C53: =C30*sga_fixed_non_staff -> 0 | D53: =D30*sga_fixed_non_staff -> 300000 | E53: =E30*sga_fixed_non_staff -> 300000 | F53: =F30*sga_fixed_non_staff -> 300000 | G53: =G30*sga_fixed_non_staff -> 300000 | H53: =H30*sga_fixed_non_staff -> 300000 | I53: =I30*sga_fixed_non_staff -> 300000 | J53: =J30*sga_fixed_non_staff -> 300000 | ... M53: =M30*sga_fixed_non_staff -> 300000
A54: Option hook: extra fixed opex | B54: EUR | C54: =C30*opt_extra_opex_per_yr -> 0 | D54: =D30*opt_extra_opex_per_yr -> 0 | E54: =E30*opt_extra_opex_per_yr -> 0 | F54: =F30*opt_extra_opex_per_yr -> 0 | G54: =G30*opt_extra_opex_per_yr -> 0 | H54: =H30*opt_extra_opex_per_yr -> 0 | I54: =I30*opt_extra_opex_per_yr -> 0 | J54: =J30*opt_extra_opex_per_yr -> 0 | ... M54: =M30*opt_extra_opex_per_yr -> 0
A55: A+B: crushing staff | B55: EUR | C55: =Revenue!C30*hybrid_crusher_staff_fte*cost_per_fte_production*C31 -> 0 | D55: =Revenue!D30*hybrid_crusher_staff_fte*cost_per_fte_production*D31 -> 0 | E55: =Revenue!E30*hybrid_crusher_staff_fte*cost_per_fte_production*E31 -> 0 | F55: =Revenue!F30*hybrid_crusher_staff_fte*cost_per_fte_production*F31 -> 0 | G55: =Revenue!G30*hybrid_crusher_staff_fte*cost_per_fte_production*G31 -> 0 | H55: =Revenue!H30*hybrid_crusher_staff_fte*cost_per_fte_production*H31 -> 0 | I55: =Revenue!I30*hybrid_crusher_staff_fte*cost_per_fte_production*I31 -> 0 | J55: =Revenue!J30*hybrid_crusher_staff_fte*cost_per_fte_production*J31 -> 0 | ... M55: =Revenue!M30*hybrid_crusher_staff_fte*cost_per_fte_production*M31 -> 0
A56: A+B: crusher maintenance | B56: EUR | C56: =Revenue!C30*hybrid_crusher_maintenance_pct_capex/100*opt_crusher_capex -> 0 | D56: =Revenue!D30*hybrid_crusher_maintenance_pct_capex/100*opt_crusher_capex -> 0 | E56: =Revenue!E30*hybrid_crusher_maintenance_pct_capex/100*opt_crusher_capex -> 0 | F56: =Revenue!F30*hybrid_crusher_maintenance_pct_capex/100*opt_crusher_capex -> 0 | G56: =Revenue!G30*hybrid_crusher_maintenance_pct_capex/100*opt_crusher_capex -> 0 | H56: =Revenue!H30*hybrid_crusher_maintenance_pct_capex/100*opt_crusher_capex -> 0 | I56: =Revenue!I30*hybrid_crusher_maintenance_pct_capex/100*opt_crusher_capex -> 0 | J56: =Revenue!J30*hybrid_crusher_maintenance_pct_capex/100*opt_crusher_capex -> 0 | ... M56: =Revenue!M30*hybrid_crusher_maintenance_pct_capex/100*opt_crusher_capex -> 0
A57: A+B: BRL 2506 certification | B57: EUR | C57: =Revenue!C30*hybrid_brl2506_certification -> 0 | D57: =Revenue!D30*hybrid_brl2506_certification -> 0 | E57: =Revenue!E30*hybrid_brl2506_certification -> 0 | F57: =Revenue!F30*hybrid_brl2506_certification -> 0 | G57: =Revenue!G30*hybrid_brl2506_certification -> 0 | H57: =Revenue!H30*hybrid_brl2506_certification -> 0 | I57: =Revenue!I30*hybrid_brl2506_certification -> 0 | J57: =Revenue!J30*hybrid_brl2506_certification -> 0 | ... M57: =Revenue!M30*hybrid_brl2506_certification -> 0
A58: A+B: extra site area lease | B58: EUR | C58: =Revenue!C30*hybrid_extra_site_area*site_lease_rate -> 0 | D58: =Revenue!D30*hybrid_extra_site_area*site_lease_rate -> 0 | E58: =Revenue!E30*hybrid_extra_site_area*site_lease_rate -> 0 | F58: =Revenue!F30*hybrid_extra_site_area*site_lease_rate -> 0 | G58: =Revenue!G30*hybrid_extra_site_area*site_lease_rate -> 0 | H58: =Revenue!H30*hybrid_extra_site_area*site_lease_rate -> 0 | I58: =Revenue!I30*hybrid_extra_site_area*site_lease_rate -> 0 | J58: =Revenue!J30*hybrid_extra_site_area*site_lease_rate -> 0 | ... M58: =Revenue!M30*hybrid_extra_site_area*site_lease_rate -> 0
A59: Total fixed costs | B59: EUR | C59: =C48+C49+C50+C51+C52+C53+C54+C55+C56+C57+C58 -> 0 | D59: =D48+D49+D50+D51+D52+D53+D54+D55+D56+D57+D58 -> 1388800 | E59: =E48+E49+E50+E51+E52+E53+E54+E55+E56+E57+E58 -> 1392619 | F59: =F48+F49+F50+F51+F52+F53+F54+F55+F56+F57+F58 -> 1396457.1 | G59: =G48+G49+G50+G51+G52+G53+G54+G55+G56+G57+G58 -> 1400314.4 | H59: =H48+H49+H50+H51+H52+H53+H54+H55+H56+H57+H58 -> 1404191 | I59: =I48+I49+I50+I51+I52+I53+I54+I55+I56+I57+I58 -> 1408086.9 | J59: =J48+J49+J50+J51+J52+J53+J54+J55+J56+J57+J58 -> 1412002.3 | ... M59: =M48+M49+M50+M51+M52+M53+M54+M55+M56+M57+M58 -> 1423866.5
A60: One-off start-up costs (t=0) | B60: EUR | C60: =Capex!C18 -> 380000 | D60: =Capex!D18 -> 0 | E60: =Capex!E18 -> 0 | F60: =Capex!F18 -> 0 | G60: =Capex!G18 -> 0 | H60: =Capex!H18 -> 0 | I60: =Capex!I18 -> 0 | J60: =Capex!J18 -> 0 | ... M60: =Capex!M18 -> 0
A61: TOTAL OPERATING COSTS | B61: EUR | C61: =C46+C59+C60 -> 380000 | D61: =D46+D59+D60 -> 5181621.4 | E61: =E46+E59+E60 -> 7398824.8 | F61: =F46+F59+F60 -> 9041169.8 | G61: =G46+G59+G60 -> 9134584.7 | H61: =H46+H59+H60 -> 9436501 | I61: =I46+I59+I60 -> 9499466.8 | J61: =J46+J59+J60 -> 9571979.6 | ... M61: =M46+M59+M60 -> 9661968.5
A62: Option A+B memo
A63: A+B variable costs (incl. RCA credit) | B63: EUR | C63: =C40+C41+C42+C43+C44 -> 0 | D63: =D40+D41+D42+D43+D44 -> 0 | E63: =E40+E41+E42+E43+E44 -> 0 | F63: =F40+F41+F42+F43+F44 -> 0 | G63: =G40+G41+G42+G43+G44 -> 0 | H63: =H40+H41+H42+H43+H44 -> 0 | I63: =I40+I41+I42+I43+I44 -> 0 | J63: =J40+J41+J42+J43+J44 -> 0 | ... M63: =M40+M41+M42+M43+M44 -> 0
A64: A+B fixed costs | B64: EUR | C64: =C55+C56+C57+C58 -> 0 | D64: =D55+D56+D57+D58 -> 0 | E64: =E55+E56+E57+E58 -> 0 | F64: =F55+F56+F57+F58 -> 0 | G64: =G55+G56+G57+G58 -> 0 | H64: =H55+H56+H57+H58 -> 0 | I64: =I55+I56+I57+I58 -> 0 | J64: =J55+J56+J57+J58 -> 0 | ... M64: =M55+M56+M57+M58 -> 0
A65: A+B net contribution (revenue - costs, incl. RCA credit; before bad debt) | B65: EUR | C65: =Revenue!C40-C63-C64 -> 0 | D65: =Revenue!D40-D63-D64 -> 0 | E65: =Revenue!E40-E63-E64 -> 0 | F65: =Revenue!F40-F63-F64 -> 0 | G65: =Revenue!G40-G63-G64 -> 0 | H65: =Revenue!H40-H63-H64 -> 0 | I65: =Revenue!I40-I63-I64 -> 0 | J65: =Revenue!J40-J63-J64 -> 0 | ... M65: =Revenue!M40-M63-M64 -> 0

Sheet PnL
A1: Profit & loss (EUR, real 2026)
A2: Unlevered: no debt, no interest.
A3: Year | B3: unit | C3: =2026+C4 -> 2026 | D3: =2026+D4 -> 2027 | E3: =2026+E4 -> 2028 | F3: =2026+F4 -> 2029 | G3: =2026+G4 -> 2030 | H3: =2026+H4 -> 2031 | I3: =2026+I4 -> 2032 | J3: =2026+J4 -> 2033 | ... M3: =2026+M4 -> 2036
A4: t (year index) | C4: 0 | D4: 1 | E4: 2 | F4: 3 | G4: 4 | H4: 5 | I4: 6 | J4: 7 | K4: 8 | L4: 9 | M4: 10
A6: Revenue circular mixes | B6: EUR | C6: =Revenue!C25 -> 0 | D6: =Revenue!D25 -> 2871260 | E6: =Revenue!E25 -> 4542961.2 | F6: =Revenue!F25 -> 5770295.4 | G6: =Revenue!G25 -> 5812406.7 | H6: =Revenue!H25 -> 5952549.2 | I6: =Revenue!I25 -> 5980324.7 | J6: =Revenue!J25 -> 6012580.1 | ... M6: =Revenue!M25 -> 6049315.5
A7: Revenue standard mixes | B7: EUR | C7: =Revenue!C26 -> 0 | D7: =Revenue!D26 -> 1891475.6 | E7: =Revenue!E26 -> 2992728.1 | F7: =Revenue!F26 -> 3801248.6 | G7: =Revenue!G26 -> 3828989.9 | H7: =Revenue!H26 -> 3921310.4 | I7: =Revenue!I26 -> 3939607.8 | J7: =Revenue!J26 -> 3960856.5 | ... M7: =Revenue!M26 -> 3985056.3
A8: Other revenue (option hook) | B8: EUR | C8: =Revenue!C27 -> 0 | D8: =Revenue!D27 -> 0 | E8: =Revenue!E27 -> 0 | F8: =Revenue!F27 -> 0 | G8: =Revenue!G27 -> 0 | H8: =Revenue!H27 -> 0 | I8: =Revenue!I27 -> 0 | J8: =Revenue!J27 -> 0 | ... M8: =Revenue!M27 -> 0
A9: On-site crushing revenue (option A+B) | B9: EUR | C9: =Revenue!C40 -> 0 | D9: =Revenue!D40 -> 0 | E9: =Revenue!E40 -> 0 | F9: =Revenue!F40 -> 0 | G9: =Revenue!G40 -> 0 | H9: =Revenue!H40 -> 0 | I9: =Revenue!I40 -> 0 | J9: =Revenue!J40 -> 0 | ... M9: =Revenue!M40 -> 0
A10: REVENUE | B10: EUR | C10: =C6+C7+C8+C9 -> 0 | D10: =D6+D7+D8+D9 -> 4762735.6 | E10: =E6+E7+E8+E9 -> 7535689.2 | F10: =F6+F7+F8+F9 -> 9571544.1 | G10: =G6+G7+G8+G9 -> 9641396.6 | H10: =H6+H7+H8+H9 -> 9873859.6 | I10: =I6+I7+I8+I9 -> 9919932.5 | J10: =J6+J7+J8+J9 -> 9973436.6 | ... M10: =M6+M7+M8+M9 -> 10034372
A11: - Raw materials | B11: EUR | C11: =-Opex!C34 -> 0 | D11: =-Opex!D34 -> -3051129.7 | E11: =-Opex!E34 -> -4834280.1 | F11: =-Opex!F34 -> -6161099 | G11: =-Opex!G34 -> -6250307.3 | H11: =-Opex!H34 -> -6547184.7 | I11: =-Opex!I34 -> -6606024.2 | J11: =-Opex!J34 -> -6674354 | ... M11: =-Opex!M34 -> -6752174.1
A12: - RCA testing & handling | B12: EUR | C12: =-Opex!C35 -> 0 | D12: =-Opex!D35 -> -21168 | E12: =-Opex!E35 -> -33445.44 | F12: =-Opex!F35 -> -42336 | G12: =-Opex!G35 -> -42336 | H12: =-Opex!H35 -> -42336 | I12: =-Opex!I35 -> -42336 | J12: =-Opex!J35 -> -42336 | ... M12: =-Opex!M35 -> -42336
A13: - Energy | B13: EUR | C13: =-Opex!C36 -> 0 | D13: =-Opex!D36 -> -31710 | E13: =-Opex!E36 -> -50101.8 | F13: =-Opex!F36 -> -63420 | G13: =-Opex!G36 -> -63420 | H13: =-Opex!H36 -> -63420 | I13: =-Opex!I36 -> -63420 | J13: =-Opex!J36 -> -63420 | ... M13: =-Opex!M36 -> -63420
A14: - Delivery | B14: EUR | C14: =-Opex!C37 -> 0 | D14: =-Opex!D37 -> -665000 | E14: =-Opex!E37 -> -1050700 | F14: =-Opex!F37 -> -1330000 | G14: =-Opex!G37 -> -1330000 | H14: =-Opex!H37 -> -1330000 | I14: =-Opex!I37 -> -1330000 | J14: =-Opex!J37 -> -1330000 | ... M14: =-Opex!M37 -> -1330000
A15: - Variable cost delta (hook) | B15: EUR | C15: =-Opex!C38 -> 0 | D15: =-Opex!D38 -> 0 | E15: =-Opex!E38 -> 0 | F15: =-Opex!F38 -> 0 | G15: =-Opex!G38 -> 0 | H15: =-Opex!H38 -> 0 | I15: =-Opex!I38 -> 0 | J15: =-Opex!J38 -> 0 | ... M15: =-Opex!M38 -> 0
A16: - Circular-only cost delta (option) | B16: EUR | C16: =-Opex!C39 -> 0 | D16: =-Opex!D39 -> 0 | E16: =-Opex!E39 -> 0 | F16: =-Opex!F39 -> 0 | G16: =-Opex!G39 -> 0 | H16: =-Opex!H39 -> 0 | I16: =-Opex!I39 -> 0 | J16: =-Opex!J39 -> 0 | ... M16: =-Opex!M39 -> 0
A17: - A+B: own RCA credit | B17: EUR | C17: =-Opex!C40 -> 0 | D17: =-Opex!D40 -> 0 | E17: =-Opex!E40 -> 0 | F17: =-Opex!F40 -> 0 | G17: =-Opex!G40 -> 0 | H17: =-Opex!H40 -> 0 | I17: =-Opex!I40 -> 0 | J17: =-Opex!J40 -> 0 | ... M17: =-Opex!M40 -> 0
A18: - A+B: contaminant disposal | B18: EUR | C18: =-Opex!C41 -> 0 | D18: =-Opex!D41 -> 0 | E18: =-Opex!E41 -> 0 | F18: =-Opex!F41 -> 0 | G18: =-Opex!G41 -> 0 | H18: =-Opex!H41 -> 0 | I18: =-Opex!I41 -> 0 | J18: =-Opex!J41 -> 0 | ... M18: =-Opex!M41 -> 0
A19: - A+B: crusher diesel | B19: EUR | C19: =-Opex!C42 -> 0 | D19: =-Opex!D42 -> 0 | E19: =-Opex!E42 -> 0 | F19: =-Opex!F42 -> 0 | G19: =-Opex!G42 -> 0 | H19: =-Opex!H42 -> 0 | I19: =-Opex!I42 -> 0 | J19: =-Opex!J42 -> 0 | ... M19: =-Opex!M42 -> 0
A20: - A+B: crusher wear | B20: EUR | C20: =-Opex!C43 -> 0 | D20: =-Opex!D43 -> 0 | E20: =-Opex!E43 -> 0 | F20: =-Opex!F43 -> 0 | G20: =-Opex!G43 -> 0 | H20: =-Opex!H43 -> 0 | I20: =-Opex!I43 -> 0 | J20: =-Opex!J43 -> 0 | ... M20: =-Opex!M43 -> 0
A21: - A+B: contract crushing | B21: EUR | C21: =-Opex!C44 -> 0 | D21: =-Opex!D44 -> 0 | E21: =-Opex!E44 -> 0 | F21: =-Opex!F44 -> 0 | G21: =-Opex!G44 -> 0 | H21: =-Opex!H44 -> 0 | I21: =-Opex!I44 -> 0 | J21: =-Opex!J44 -> 0 | ... M21: =-Opex!M44 -> 0
A22: - Bad debt | B22: EUR | C22: =-Opex!C45 -> 0 | D22: =-Opex!D45 -> -23813.678 | E22: =-Opex!E45 -> -37678.446 | F22: =-Opex!F45 -> -47857.72 | G22: =-Opex!G45 -> -48206.983 | H22: =-Opex!H45 -> -49369.298 | I22: =-Opex!I45 -> -49599.663 | J22: =-Opex!J45 -> -49867.183 | ... M22: =-Opex!M45 -> -50171.859
A23: - Production staff | B23: EUR | C23: =-Opex!C48 -> 0 | D23: =-Opex!D48 -> -492450 | E23: =-Opex!E48 -> -494912.25 | F23: =-Opex!F48 -> -497386.81 | G23: =-Opex!G48 -> -499873.75 | H23: =-Opex!H48 -> -502373.11 | I23: =-Opex!I48 -> -504884.98 | J23: =-Opex!J48 -> -507409.4 | ... M23: =-Opex!M48 -> -515058.66
A24: - Maintenance | B24: EUR | C24: =-Opex!C49 -> 0 | D24: =-Opex!D49 -> -125000 | E24: =-Opex!E49 -> -125000 | F24: =-Opex!F49 -> -125000 | G24: =-Opex!G49 -> -125000 | H24: =-Opex!H49 -> -125000 | I24: =-Opex!I49 -> -125000 | J24: =-Opex!J49 -> -125000 | ... M24: =-Opex!M49 -> -125000
A25: - Certification & testing | B25: EUR | C25: =-Opex!C50 -> 0 | D25: =-Opex!D50 -> -50000 | E25: =-Opex!E50 -> -50000 | F25: =-Opex!F50 -> -50000 | G25: =-Opex!G50 -> -50000 | H25: =-Opex!H50 -> -50000 | I25: =-Opex!I50 -> -50000 | J25: =-Opex!J50 -> -50000 | ... M25: =-Opex!M50 -> -50000
A26: - Site lease | B26: EUR | C26: =-Opex!C51 -> 0 | D26: =-Opex!D51 -> -150000 | E26: =-Opex!E51 -> -150000 | F26: =-Opex!F51 -> -150000 | G26: =-Opex!G51 -> -150000 | H26: =-Opex!H51 -> -150000 | I26: =-Opex!I51 -> -150000 | J26: =-Opex!J51 -> -150000 | ... M26: =-Opex!M51 -> -150000
A27: - SG&A staff | B27: EUR | C27: =-Opex!C52 -> 0 | D27: =-Opex!D52 -> -271350 | E27: =-Opex!E52 -> -272706.75 | F27: =-Opex!F52 -> -274070.28 | G27: =-Opex!G52 -> -275440.64 | H27: =-Opex!H52 -> -276817.84 | I27: =-Opex!I52 -> -278201.93 | J27: =-Opex!J52 -> -279592.94 | ... M27: =-Opex!M52 -> -283807.84
A28: - SG&A non-staff | B28: EUR | C28: =-Opex!C53 -> 0 | D28: =-Opex!D53 -> -300000 | E28: =-Opex!E53 -> -300000 | F28: =-Opex!F53 -> -300000 | G28: =-Opex!G53 -> -300000 | H28: =-Opex!H53 -> -300000 | I28: =-Opex!I53 -> -300000 | J28: =-Opex!J53 -> -300000 | ... M28: =-Opex!M53 -> -300000
A29: - Extra fixed opex (hook) | B29: EUR | C29: =-Opex!C54 -> 0 | D29: =-Opex!D54 -> 0 | E29: =-Opex!E54 -> 0 | F29: =-Opex!F54 -> 0 | G29: =-Opex!G54 -> 0 | H29: =-Opex!H54 -> 0 | I29: =-Opex!I54 -> 0 | J29: =-Opex!J54 -> 0 | ... M29: =-Opex!M54 -> 0
A30: - A+B: crushing staff | B30: EUR | C30: =-Opex!C55 -> 0 | D30: =-Opex!D55 -> 0 | E30: =-Opex!E55 -> 0 | F30: =-Opex!F55 -> 0 | G30: =-Opex!G55 -> 0 | H30: =-Opex!H55 -> 0 | I30: =-Opex!I55 -> 0 | J30: =-Opex!J55 -> 0 | ... M30: =-Opex!M55 -> 0
A31: - A+B: crusher maintenance | B31: EUR | C31: =-Opex!C56 -> 0 | D31: =-Opex!D56 -> 0 | E31: =-Opex!E56 -> 0 | F31: =-Opex!F56 -> 0 | G31: =-Opex!G56 -> 0 | H31: =-Opex!H56 -> 0 | I31: =-Opex!I56 -> 0 | J31: =-Opex!J56 -> 0 | ... M31: =-Opex!M56 -> 0
A32: - A+B: BRL 2506 certification | B32: EUR | C32: =-Opex!C57 -> 0 | D32: =-Opex!D57 -> 0 | E32: =-Opex!E57 -> 0 | F32: =-Opex!F57 -> 0 | G32: =-Opex!G57 -> 0 | H32: =-Opex!H57 -> 0 | I32: =-Opex!I57 -> 0 | J32: =-Opex!J57 -> 0 | ... M32: =-Opex!M57 -> 0
A33: - A+B: extra site lease | B33: EUR | C33: =-Opex!C58 -> 0 | D33: =-Opex!D58 -> 0 | E33: =-Opex!E58 -> 0 | F33: =-Opex!F58 -> 0 | G33: =-Opex!G58 -> 0 | H33: =-Opex!H58 -> 0 | I33: =-Opex!I58 -> 0 | J33: =-Opex!J58 -> 0 | ... M33: =-Opex!M58 -> 0
A34: - One-off start-up costs | B34: EUR | C34: =-Opex!C60 -> -380000 | D34: =-Opex!D60 -> 0 | E34: =-Opex!E60 -> 0 | F34: =-Opex!F60 -> 0 | G34: =-Opex!G60 -> 0 | H34: =-Opex!H60 -> 0 | I34: =-Opex!I60 -> 0 | J34: =-Opex!J60 -> 0 | ... M34: =-Opex!M60 -> 0
A35: EBITDA | B35: EUR | C35: =C10+C11+C12+C13+C14+C15+C16+C17+C18+C19+C20+C21+C22+C23+C24+C25+C26+C27+C28+C29+C30+C31+C32+C33+C34 -> -380000 | D35: =D10+D11+D12+D13+D14+D15+D16+D17+D18+D19+D20+D21+D22+D23+D24+D25+D26+D27+D28+D29+D30+D31+D32+D33+D34 -> -418885.84 | E35: =E10+E11+E12+E13+E14+E15+E16+E17+E18+E19+E20+E21+E22+E23+E24+E25+E26+E27+E28+E29+E30+E31+E32+E33+E34 -> 136864.45 | F35: =F10+F11+F12+F13+F14+F15+F16+F17+F18+F19+F20+F21+F22+F23+F24+F25+F26+F27+F28+F29+F30+F31+F32+F33+F34 -> 530374.26 | G35: =G10+G11+G12+G13+G14+G15+G16+G17+G18+G19+G20+G21+G22+G23+G24+G25+G26+G27+G28+G29+G30+G31+G32+G33+G34 -> 506811.9 | H35: =H10+H11+H12+H13+H14+H15+H16+H17+H18+H19+H20+H21+H22+H23+H24+H25+H26+H27+H28+H29+H30+H31+H32+H33+H34 -> 437358.64 | I35: =I10+I11+I12+I13+I14+I15+I16+I17+I18+I19+I20+I21+I22+I23+I24+I25+I26+I27+I28+I29+I30+I31+I32+I33+I34 -> 420465.72 | J35: =J10+J11+J12+J13+J14+J15+J16+J17+J18+J19+J20+J21+J22+J23+J24+J25+J26+J27+J28+J29+J30+J31+J32+J33+J34 -> 401457.04 | ... M35: =M10+M11+M12+M13+M14+M15+M16+M17+M18+M19+M20+M21+M22+M23+M24+M25+M26+M27+M28+M29+M30+M31+M32+M33+M34 -> 372403.35
A36: EBITDA margin | B36: % | C36: =IF(C10<>0,C35/C10,0) -> 0 | D36: =IF(D10<>0,D35/D10,0) -> -0.087950682 | E36: =IF(E10<>0,E35/E10,0) -> 0.018162168 | F36: =IF(F10<>0,F35/F10,0) -> 0.055411567 | G36: =IF(G10<>0,G35/G10,0) -> 0.052566233 | H36: =IF(H10<>0,H35/H10,0) -> 0.044294598 | I36: =IF(I10<>0,I35/I10,0) -> 0.042385946 | J36: =IF(J10<>0,J35/J10,0) -> 0.040252629 | ... M36: =IF(M10<>0,M35/M10,0) -> 0.037112772
A37: - Depreciation & amortisation | B37: EUR | C37: =-Capex!C29 -> 0 | D37: =-Capex!D29 -> -252000 | E37: =-Capex!E29 -> -254000 | F37: =-Capex!F29 -> -256000 | G37: =-Capex!G29 -> -258000 | H37: =-Capex!H29 -> -260000 | I37: =-Capex!I29 -> -262000 | J37: =-Capex!J29 -> -264000 | ... M37: =-Capex!M29 -> -270000
A38: EBIT | B38: EUR | C38: =C35+C37 -> -380000 | D38: =D35+D37 -> -670885.84 | E38: =E35+E37 -> -117135.55 | F38: =F35+F37 -> 274374.26 | G38: =G35+G37 -> 248811.9 | H38: =H35+H37 -> 177358.64 | I38: =I35+I37 -> 158465.72 | J38: =J35+J37 -> 137457.04 | ... M38: =M35+M37 -> 102403.35
A39: + Grant income | B39: EUR | C39: =Capex!C19 -> 400000 | D39: =Capex!D19 -> 0 | E39: =Capex!E19 -> 0 | F39: =Capex!F19 -> 0 | G39: =Capex!G19 -> 0 | H39: =Capex!H19 -> 0 | I39: =Capex!I19 -> 0 | J39: =Capex!J19 -> 0 | ... M39: =Capex!M19 -> 0
A40: PROFIT BEFORE TAX | B40: EUR | C40: =C38+C39 -> 20000 | D40: =D38+D39 -> -670885.84 | E40: =E38+E39 -> -117135.55 | F40: =F38+F39 -> 274374.26 | G40: =G38+G39 -> 248811.9 | H40: =H38+H39 -> 177358.64 | I40: =I38+I39 -> 158465.72 | J40: =J38+J39 -> 137457.04 | ... M40: =M38+M39 -> 102403.35
A41: Corporate income tax (Vpb)
A42: MIA deduction | B42: EUR | C42: =Capex!C20 -> 360465.12 | D42: =Capex!D20 -> 0 | E42: =Capex!E20 -> 0 | F42: =Capex!F20 -> 0 | G42: =Capex!G20 -> 0 | H42: =Capex!H20 -> 0 | I42: =Capex!I20 -> 0 | J42: =Capex!J20 -> 0 | ... M42: =Capex!M20 -> 0
A43: Taxable result before loss offset | B43: EUR | C43: =C40-C42 -> -340465.12 | D43: =D40-D42 -> -670885.84 | E43: =E40-E42 -> -117135.55 | F43: =F40-F42 -> 274374.26 | G43: =G40-G42 -> 248811.9 | H43: =H40-H42 -> 177358.64 | I43: =I40-I42 -> 158465.72 | J43: =J40-J42 -> 137457.04 | ... M43: =M40-M42 -> 102403.35
A44: Taxable profit after loss offset | B44: EUR | C44: =MAX(0,C43) -> 0 | D44: =MAX(0,D43-C45) -> 0 | E44: =MAX(0,E43-D45) -> 0 | F44: =MAX(0,F43-E45) -> 0 | G44: =MAX(0,G43-F45) -> 0 | H44: =MAX(0,H43-G45) -> 0 | I44: =MAX(0,I43-H45) -> 0 | J44: =MAX(0,J43-I45) -> 0 | K44: =MAX(0,K43-J45) -> 0 | ... M44: =MAX(0,M43-L45) -> 102403.35
A45: Tax-loss pool carried forward (end of year) | B45: EUR | C45: =MAX(0,-C43) -> 340465.12 | D45: =MAX(0,C45-D43) -> 1011351 | E45: =MAX(0,D45-E43) -> 1128486.5 | F45: =MAX(0,E45-F43) -> 854112.24 | G45: =MAX(0,F45-G43) -> 605300.34 | H45: =MAX(0,G45-H43) -> 427941.7 | I45: =MAX(0,H45-I43) -> 269475.98 | J45: =MAX(0,I45-J43) -> 132018.94 | K45: =MAX(0,J45-K43) -> 17686.438 | ... M45: =MAX(0,L45-M43) -> 0
A46: Corporate income tax | B46: EUR | C46: =MIN(C44,tax_vpb_low_bracket_limit)*tax_rate_vpb_low_bracket/100+MAX(0,C44-tax_vpb_low_bracket_limit)*tax_rate_vpb_high_bracket/100 -> 0 | D46: =MIN(D44,tax_vpb_low_bracket_limit)*tax_rate_vpb_low_bracket/100+MAX(0,D44-tax_vpb_low_bracket_limit)*tax_rate_vpb_high_bracket/100 -> 0 | E46: =MIN(E44,tax_vpb_low_bracket_limit)*tax_rate_vpb_low_bracket/100+MAX(0,E44-tax_vpb_low_bracket_limit)*tax_rate_vpb_high_bracket/100 -> 0 | F46: =MIN(F44,tax_vpb_low_bracket_limit)*tax_rate_vpb_low_bracket/100+MAX(0,F44-tax_vpb_low_bracket_limit)*tax_rate_vpb_high_bracket/100 -> 0 | G46: =MIN(G44,tax_vpb_low_bracket_limit)*tax_rate_vpb_low_bracket/100+MAX(0,G44-tax_vpb_low_bracket_limit)*tax_rate_vpb_high_bracket/100 -> 0 | H46: =MIN(H44,tax_vpb_low_bracket_limit)*tax_rate_vpb_low_bracket/100+MAX(0,H44-tax_vpb_low_bracket_limit)*tax_rate_vpb_high_bracket/100 -> 0 | I46: =MIN(I44,tax_vpb_low_bracket_limit)*tax_rate_vpb_low_bracket/100+MAX(0,I44-tax_vpb_low_bracket_limit)*tax_rate_vpb_high_bracket/100 -> 0 | J46: =MIN(J44,tax_vpb_low_bracket_limit)*tax_rate_vpb_low_bracket/100+MAX(0,J44-tax_vpb_low_bracket_limit)*tax_rate_vpb_high_bracket/100 -> 0 | ... M46: =MIN(M44,tax_vpb_low_bracket_limit)*tax_rate_vpb_low_bracket/100+MAX(0,M44-tax_vpb_low_bracket_limit)*tax_rate_vpb_high_bracket/100 -> 19456.637
A47: NET INCOME | B47: EUR | C47: =C40-C46 -> 20000 | D47: =D40-D46 -> -670885.84 | E47: =E40-E46 -> -117135.55 | F47: =F40-F46 -> 274374.26 | G47: =G40-G46 -> 248811.9 | H47: =H40-H46 -> 177358.64 | I47: =I40-I46 -> 158465.72 | J47: =J40-J46 -> 137457.04 | ... M47: =M40-M46 -> 82946.717
A48: Checks (must be 0)
A49: Check: revenue lines - Revenue sheet total | B49: EUR | C49: =C10-Revenue!C42 -> 0 | D49: =D10-Revenue!D42 -> 0 | E49: =E10-Revenue!E42 -> 0 | F49: =F10-Revenue!F42 -> 0 | G49: =G10-Revenue!G42 -> 0 | H49: =H10-Revenue!H42 -> 0 | I49: =I10-Revenue!I42 -> 0 | J49: =J10-Revenue!J42 -> 0 | ... M49: =M10-Revenue!M42 -> 0
A50: Check: sum of cost lines + Opex total | B50: EUR | C50: =C11+C12+C13+C14+C15+C16+C17+C18+C19+C20+C21+C22+C23+C24+C25+C26+C27+C28+C29+C30+C31+C32+C33+C34+Opex!C61 -> 0 | D50: =D11+D12+D13+D14+D15+D16+D17+D18+D19+D20+D21+D22+D23+D24+D25+D26+D27+D28+D29+D30+D31+D32+D33+D34+Opex!D61 -> 0 | E50: =E11+E12+E13+E14+E15+E16+E17+E18+E19+E20+E21+E22+E23+E24+E25+E26+E27+E28+E29+E30+E31+E32+E33+E34+Opex!E61 -> 0 | F50: =F11+F12+F13+F14+F15+F16+F17+F18+F19+F20+F21+F22+F23+F24+F25+F26+F27+F28+F29+F30+F31+F32+F33+F34+Opex!F61 -> 0 | G50: =G11+G12+G13+G14+G15+G16+G17+G18+G19+G20+G21+G22+G23+G24+G25+G26+G27+G28+G29+G30+G31+G32+G33+G34+Opex!G61 -> 0 | H50: =H11+H12+H13+H14+H15+H16+H17+H18+H19+H20+H21+H22+H23+H24+H25+H26+H27+H28+H29+H30+H31+H32+H33+H34+Opex!H61 -> 0 | I50: =I11+I12+I13+I14+I15+I16+I17+I18+I19+I20+I21+I22+I23+I24+I25+I26+I27+I28+I29+I30+I31+I32+I33+I34+Opex!I61 -> 0 | J50: =J11+J12+J13+J14+J15+J16+J17+J18+J19+J20+J21+J22+J23+J24+J25+J26+J27+J28+J29+J30+J31+J32+J33+J34+Opex!J61 -> 0 | ... M50: =M11+M12+M13+M14+M15+M16+M17+M18+M19+M20+M21+M22+M23+M24+M25+M26+M27+M28+M29+M30+M31+M32+M33+M34+Opex!M61 -> 0
A51: Check: EBITDA - (revenue - total opex) | B51: EUR | C51: =C35-(Revenue!C42-Opex!C61) -> 0 | D51: =D35-(Revenue!D42-Opex!D61) -> 0 | E51: =E35-(Revenue!E42-Opex!E61) -> 6.4028427e-10 | F51: =F35-(Revenue!F42-Opex!F61) -> 0 | G51: =G35-(Revenue!G42-Opex!G61) -> 0 | H51: =H35-(Revenue!H42-Opex!H61) -> 0 | I51: =I35-(Revenue!I42-Opex!I61) -> 0 | J51: =J35-(Revenue!J42-Opex!J61) -> 0 | ... M51: =M35-(Revenue!M42-Opex!M61) -> 0

Sheet CashFlow
A1: Free cash flow (unlevered, EUR real 2026)
A2: Terminal value = salvage only (t=10). Working capital is not released at the end.
A3: Year | B3: unit | C3: =2026+C4 -> 2026 | D3: =2026+D4 -> 2027 | E3: =2026+E4 -> 2028 | F3: =2026+F4 -> 2029 | G3: =2026+G4 -> 2030 | H3: =2026+H4 -> 2031 | I3: =2026+I4 -> 2032 | J3: =2026+J4 -> 2033 | ... M3: =2026+M4 -> 2036
A4: t (year index) | C4: 0 | D4: 1 | E4: 2 | F4: 3 | G4: 4 | H4: 5 | I4: 6 | J4: 7 | K4: 8 | L4: 9 | M4: 10
A6: EBITDA | B6: EUR | C6: =PnL!C35 -> -380000 | D6: =PnL!D35 -> -418885.84 | E6: =PnL!E35 -> 136864.45 | F6: =PnL!F35 -> 530374.26 | G6: =PnL!G35 -> 506811.9 | H6: =PnL!H35 -> 437358.64 | I6: =PnL!I35 -> 420465.72 | J6: =PnL!J35 -> 401457.04 | ... M6: =PnL!M35 -> 372403.35
A7: Grant received | B7: EUR | C7: =Capex!C19 -> 400000 | D7: =Capex!D19 -> 0 | E7: =Capex!E19 -> 0 | F7: =Capex!F19 -> 0 | G7: =Capex!G19 -> 0 | H7: =Capex!H19 -> 0 | I7: =Capex!I19 -> 0 | J7: =Capex!J19 -> 0 | ... M7: =Capex!M19 -> 0
A8: Tax paid (same year) | B8: EUR | C8: =-PnL!C46 -> 0 | D8: =-PnL!D46 -> 0 | E8: =-PnL!E46 -> 0 | F8: =-PnL!F46 -> 0 | G8: =-PnL!G46 -> 0 | H8: =-PnL!H46 -> 0 | I8: =-PnL!I46 -> 0 | J8: =-PnL!J46 -> 0 | ... M8: =-PnL!M46 -> -19456.637
A9: Working capital
A10: Receivables | B10: EUR | C10: =Revenue!C42*working_capital_receivable_days/365 -> 0 | D10: =Revenue!D42*working_capital_receivable_days/365 -> 782915.43 | E10: =Revenue!E42*working_capital_receivable_days/365 -> 1238743.4 | F10: =Revenue!F42*working_capital_receivable_days/365 -> 1573404.5 | G10: =Revenue!G42*working_capital_receivable_days/365 -> 1584887.1 | H10: =Revenue!H42*working_capital_receivable_days/365 -> 1623100.2 | I10: =Revenue!I42*working_capital_receivable_days/365 -> 1630673.8 | J10: =Revenue!J42*working_capital_receivable_days/365 -> 1639469 | ... M10: =Revenue!M42*working_capital_receivable_days/365 -> 1649485.8
A11: Inventory (raw materials) | B11: EUR | C11: =Opex!C34*working_capital_inventory_days/365 -> 0 | D11: =Opex!D34*working_capital_inventory_days/365 -> 83592.595 | E11: =Opex!E34*working_capital_inventory_days/365 -> 132446.03 | F11: =Opex!F34*working_capital_inventory_days/365 -> 168797.23 | G11: =Opex!G34*working_capital_inventory_days/365 -> 171241.3 | H11: =Opex!H34*working_capital_inventory_days/365 -> 179374.92 | I11: =Opex!I34*working_capital_inventory_days/365 -> 180986.97 | J11: =Opex!J34*working_capital_inventory_days/365 -> 182859.02 | ... M11: =Opex!M34*working_capital_inventory_days/365 -> 184991.07
A12: Payables (raw materials) | B12: EUR | C12: =Opex!C34*working_capital_payable_days/365 -> 0 | D12: =Opex!D34*working_capital_payable_days/365 -> 250777.79 | E12: =Opex!E34*working_capital_payable_days/365 -> 397338.09 | F12: =Opex!F34*working_capital_payable_days/365 -> 506391.7 | G12: =Opex!G34*working_capital_payable_days/365 -> 513723.89 | H12: =Opex!H34*working_capital_payable_days/365 -> 538124.77 | I12: =Opex!I34*working_capital_payable_days/365 -> 542960.9 | J12: =Opex!J34*working_capital_payable_days/365 -> 548577.05 | ... M12: =Opex!M34*working_capital_payable_days/365 -> 554973.21
A13: Net working capital | B13: EUR | C13: =C10+C11-C12 -> 0 | D13: =D10+D11-D12 -> 615730.24 | E13: =E10+E11-E12 -> 973851.38 | F13: =F10+F11-F12 -> 1235810 | G13: =G10+G11-G12 -> 1242404.5 | H13: =H10+H11-H12 -> 1264350.4 | I13: =I10+I11-I12 -> 1268699.9 | J13: =J10+J11-J12 -> 1273751 | ... M13: =M10+M11-M12 -> 1279503.6
A14: Change in working capital (cash out = negative) | B14: EUR | C14: =-C13 -> 0 | D14: =-(D13-C13) -> -615730.24 | E14: =-(E13-D13) -> -358121.13 | F14: =-(F13-E13) -> -261958.66 | G14: =-(G13-F13) -> -6594.481 | H14: =-(H13-G13) -> -21945.839 | I14: =-(I13-H13) -> -4349.5513 | J14: =-(J13-I13) -> -5051.0919 | K14: =-(K13-J13) -> -5752.6324 | ... M14: =-(M13-L13) -> 0
A15: Investment
A16: Initial capex | B16: EUR | C16: =-Capex!C14 -> -5500000 | D16: =-Capex!D14 -> 0 | E16: =-Capex!E14 -> 0 | F16: =-Capex!F14 -> 0 | G16: =-Capex!G14 -> 0 | H16: =-Capex!H14 -> 0 | I16: =-Capex!I14 -> 0 | J16: =-Capex!J14 -> 0 | ... M16: =-Capex!M14 -> 0
A17: Sustaining capex | B17: EUR | C17: =-Capex!C23 -> 0 | D17: =-Capex!D23 -> -50000 | E17: =-Capex!E23 -> -50000 | F17: =-Capex!F23 -> -50000 | G17: =-Capex!G23 -> -50000 | H17: =-Capex!H23 -> -50000 | I17: =-Capex!I23 -> -50000 | J17: =-Capex!J23 -> -50000 | ... M17: =-Capex!M23 -> -50000
A18: Salvage value (terminal value) | B18: EUR | C18: =Capex!C31 -> 0 | D18: =Capex!D31 -> 0 | E18: =Capex!E31 -> 0 | F18: =Capex!F31 -> 0 | G18: =Capex!G31 -> 0 | H18: =Capex!H31 -> 0 | I18: =Capex!I31 -> 0 | J18: =Capex!J31 -> 0 | ... M18: =Capex!M31 -> 1250000
A19: FREE CASH FLOW | B19: EUR | C19: =C6+C7+C8+C14+C16+C17+C18 -> -5480000 | D19: =D6+D7+D8+D14+D16+D17+D18 -> -1084616.1 | E19: =E6+E7+E8+E14+E16+E17+E18 -> -271256.68 | F19: =F6+F7+F8+F14+F16+F17+F18 -> 218415.6 | G19: =G6+G7+G8+G14+G16+G17+G18 -> 450217.42 | H19: =H6+H7+H8+H14+H16+H17+H18 -> 365412.8 | I19: =I6+I7+I8+I14+I16+I17+I18 -> 366116.17 | J19: =J6+J7+J8+J14+J16+J17+J18 -> 346405.95 | ... M19: =M6+M7+M8+M14+M16+M17+M18 -> 1552946.7
A20: Cumulative free cash flow | B20: EUR | C20: =SUM($C$19:C19) -> -5480000 | D20: =SUM($C$19:D19) -> -6564616.1 | E20: =SUM($C$19:E19) -> -6835872.8 | F20: =SUM($C$19:F19) -> -6617457.2 | G20: =SUM($C$19:G19) -> -6167239.7 | H20: =SUM($C$19:H19) -> -5801826.9 | I20: =SUM($C$19:I19) -> -5435710.8 | J20: =SUM($C$19:J19) -> -5089304.8 | ... M20: =SUM($C$19:M19) -> -2902631.8
A21: Discount factor | B21: x | C21: =1/(1+discount_rate_real/100)^C$4 -> 1 | D21: =1/(1+discount_rate_real/100)^D$4 -> 0.92592593 | E21: =1/(1+discount_rate_real/100)^E$4 -> 0.85733882 | F21: =1/(1+discount_rate_real/100)^F$4 -> 0.79383224 | G21: =1/(1+discount_rate_real/100)^G$4 -> 0.73502985 | H21: =1/(1+discount_rate_real/100)^H$4 -> 0.6805832 | I21: =1/(1+discount_rate_real/100)^I$4 -> 0.63016963 | J21: =1/(1+discount_rate_real/100)^J$4 -> 0.5834904 | ... M21: =1/(1+discount_rate_real/100)^M$4 -> 0.46319349
A22: Discounted free cash flow | B22: EUR | C22: =C19*C21 -> -5480000 | D22: =D19*D21 -> -1004274.2 | E22: =E19*E21 -> -232558.88 | F22: =F19*F21 -> 173385.34 | G22: =G19*G21 -> 330923.25 | H22: =H19*H21 -> 248693.81 | I22: =I19*I21 -> 230715.29 | J22: =J19*J21 -> 202124.54 | ... M22: =M19*M21 -> 719314.81
A23: Cumulative discounted FCF | B23: EUR | C23: =SUM($C$22:C22) -> -5480000 | D23: =SUM($C$22:D22) -> -6484274.2 | E23: =SUM($C$22:E22) -> -6716833 | F23: =SUM($C$22:F22) -> -6543447.7 | G23: =SUM($C$22:G22) -> -6212524.4 | H23: =SUM($C$22:H22) -> -5963830.6 | I23: =SUM($C$22:I22) -> -5733115.3 | J23: =SUM($C$22:J22) -> -5530990.8 | ... M23: =SUM($C$22:M22) -> -4481665.4
A24: Payback helpers (cash flow EXCLUDING salvage)
A25: FCF excl. salvage | B25: EUR | C25: =C19-C18 -> -5480000 | D25: =D19-D18 -> -1084616.1 | E25: =E19-E18 -> -271256.68 | F25: =F19-F18 -> 218415.6 | G25: =G19-G18 -> 450217.42 | H25: =H19-H18 -> 365412.8 | I25: =I19-I18 -> 366116.17 | J25: =J19-J18 -> 346405.95 | ... M25: =M19-M18 -> 302946.72
A26: Cumulative FCF excl. salvage | B26: EUR | C26: =SUM($C$25:C25) -> -5480000 | D26: =SUM($C$25:D25) -> -6564616.1 | E26: =SUM($C$25:E25) -> -6835872.8 | F26: =SUM($C$25:F25) -> -6617457.2 | G26: =SUM($C$25:G25) -> -6167239.7 | H26: =SUM($C$25:H25) -> -5801826.9 | I26: =SUM($C$25:I25) -> -5435710.8 | J26: =SUM($C$25:J25) -> -5089304.8 | ... M26: =SUM($C$25:M25) -> -4152631.8
A27: Cumulative discounted FCF excl. salvage | B27: EUR | C27: =SUMPRODUCT($C$25:C25,$C$21:C21) -> -5480000 | D27: =SUMPRODUCT($C$25:D25,$C$21:D21) -> -6484274.2 | E27: =SUMPRODUCT($C$25:E25,$C$21:E21) -> -6716833 | F27: =SUMPRODUCT($C$25:F25,$C$21:F21) -> -6543447.7 | G27: =SUMPRODUCT($C$25:G25,$C$21:G21) -> -6212524.4 | H27: =SUMPRODUCT($C$25:H25,$C$21:H21) -> -5963830.6 | I27: =SUMPRODUCT($C$25:I25,$C$21:I21) -> -5733115.3 | J27: =SUMPRODUCT($C$25:J25,$C$21:J21) -> -5530990.8 | ... M27: =SUMPRODUCT($C$25:M25,$C$21:M21) -> -5060657.3
A28: Payback crossing (year, interpolated) | B28: yr | D28: =IF(AND(C26<0,D26>=0),D$4-1+(-C26)/(D26-C26),"") | E28: =IF(AND(D26<0,E26>=0),E$4-1+(-D26)/(E26-D26),"") | F28: =IF(AND(E26<0,F26>=0),F$4-1+(-E26)/(F26-E26),"") | G28: =IF(AND(F26<0,G26>=0),G$4-1+(-F26)/(G26-F26),"") | H28: =IF(AND(G26<0,H26>=0),H$4-1+(-G26)/(H26-G26),"") | I28: =IF(AND(H26<0,I26>=0),I$4-1+(-H26)/(I26-H26),"") | J28: =IF(AND(I26<0,J26>=0),J$4-1+(-I26)/(J26-I26),"") | K28: =IF(AND(J26<0,K26>=0),K$4-1+(-J26)/(K26-J26),"") | ... M28: =IF(AND(L26<0,M26>=0),M$4-1+(-L26)/(M26-L26),"")
A29: Discounted payback crossing (year) | B29: yr | D29: =IF(AND(C27<0,D27>=0),D$4-1+(-C27)/(D27-C27),"") | E29: =IF(AND(D27<0,E27>=0),E$4-1+(-D27)/(E27-D27),"") | F29: =IF(AND(E27<0,F27>=0),F$4-1+(-E27)/(F27-E27),"") | G29: =IF(AND(F27<0,G27>=0),G$4-1+(-F27)/(G27-F27),"") | H29: =IF(AND(G27<0,H27>=0),H$4-1+(-G27)/(H27-G27),"") | I29: =IF(AND(H27<0,I27>=0),I$4-1+(-H27)/(I27-H27),"") | J29: =IF(AND(I27<0,J27>=0),J$4-1+(-I27)/(J27-I27),"") | K29: =IF(AND(J27<0,K27>=0),K$4-1+(-J27)/(K27-J27),"") | ... M29: =IF(AND(L27<0,M27>=0),M$4-1+(-L27)/(M27-L27),"")
A30: Reconciliation (must be 0)
A31: Check: FCF - (net income + D&A + dWC - capex - sustaining + salvage) | B31: EUR | C31: =C19-(PnL!C47+Capex!C29+C14+C16+C17+C18) -> 0 | D31: =D19-(PnL!D47+Capex!D29+D14+D16+D17+D18) -> 0 | E31: =E19-(PnL!E47+Capex!E29+E14+E16+E17+E18) -> 0 | F31: =F19-(PnL!F47+Capex!F29+F14+F16+F17+F18) -> 0 | G31: =G19-(PnL!G47+Capex!G29+G14+G16+G17+G18) -> 0 | H31: =H19-(PnL!H47+Capex!H29+H14+H16+H17+H18) -> 0 | I31: =I19-(PnL!I47+Capex!I29+I14+I16+I17+I18) -> 0 | J31: =J19-(PnL!J47+Capex!J29+J14+J16+J17+J18) -> 0 | ... M31: =M19-(PnL!M47+Capex!M29+M14+M16+M17+M18) -> 0
A32: Check: EBITDA + grant - tax - (net income + D&A) | B32: EUR | C32: =C6+C7+C8-(PnL!C47+Capex!C29) -> 0 | D32: =D6+D7+D8-(PnL!D47+Capex!D29) -> 0 | E32: =E6+E7+E8-(PnL!E47+Capex!E29) -> 0 | F32: =F6+F7+F8-(PnL!F47+Capex!F29) -> 0 | G32: =G6+G7+G8-(PnL!G47+Capex!G29) -> 0 | H32: =H6+H7+H8-(PnL!H47+Capex!H29) -> 0 | I32: =I6+I7+I8-(PnL!I47+Capex!I29) -> 0 | J32: =J6+J7+J8-(PnL!J47+Capex!J29) -> 0 | ... M32: =M6+M7+M8-(PnL!M47+Capex!M29) -> 0

Sheet Valuation
A1: Valuation & KPIs (active scenario)
A2: ="Active scenario: "&Inputs!D3 -> Active scenario: Base
A4: KPI | B4: value | C4: unit | D4: how it is calculated
A5: NPV at discount rate | B5: =SUMPRODUCT(CashFlow!$C$19:$M$19,CashFlow!$C$21:$M$21) -> -4481665.4 | C5: EUR | D5: sum of FCF x 1/(1+r)^t, t=0..10
A6: NPV cross-check with Excel NPV() | B6: =CashFlow!$C$19+NPV(discount_rate_real/100,CashFlow!$D$19:$M$19) -> -4481665.4 | C6: EUR | D6: t=0 + NPV(r, t1..t10)
A7: Discount rate (real) | B7: =discount_rate_real/100 -> 0.08 | C7: % | D7: input
A8: IRR (real) | B8: =IFERROR(IRR(CashFlow!$C$19:$M$19,0.1),IFERROR(IRR(CashFlow!$C$19:$M$19,-0.1),IFERROR(IRR(CashFlow!$C$19:$M$19,-0.3),"n/a"))) -> -0.070638263 | C8: % | D8: IRR of FCF t=0..10 incl. salvage
A9: Payback period (simple) | B9: =IF(COUNT(CashFlow!$D$28:$M$28)=0,"not reached",MIN(CashFlow!$D$28:$M$28)) -> not reached | C9: years from t=0 | D9: first year cumulative FCF (excl. salvage) >= 0, interpolated
A10: Discounted payback period | B10: =IF(COUNT(CashFlow!$D$29:$M$29)=0,"not reached",MIN(CashFlow!$D$29:$M$29)) -> not reached | C10: years from t=0 | D10: same on discounted FCF
A11: EBITDA in 3rd operating year (2029; 2030 if sales start 2028) | B11: =INDEX(PnL!$C$35:$M$35,1,opt_start_delay+4) -> 530374.26 | C11: EUR | D11: first year at full output (criterion 3)
A12: EBITDA year 1 (2027) | B12: =PnL!$D$35 -> -418885.84 | C12: EUR
A13: EBITDA year 10 (2036) | B13: =PnL!$M$35 -> 372403.35 | C13: EUR
A14: Funding need (peak cumulative negative FCF) | B14: =MAX(0,-MIN(CashFlow!$C$20:$M$20)) -> 6835872.8 | C14: EUR | D14: equity/debt needed before the plant pays for itself
A15: Initial capex | B15: =SUM(Capex!$C$14:$M$14) -> 5500000 | C15: EUR | D15: plant + civil + permits (+hooks, crushing line)
A16: NPV as % of initial capex | B16: =Valuation!$B$5/Valuation!$B$15 -> -0.81484825 | C16: % | D16: borderline test: -10% .. 0%
A17: Memo: NPV if working capital is released in 2036 | B17: =Valuation!$B$5+CashFlow!$M$13*CashFlow!$M$21 -> -3889007.6 | C17: EUR | D17: not used for the criteria (plan 2.1 allows salvage only)
A18: Revenue 3rd operating year | B18: =INDEX(Revenue!$C$42:$M$42,1,opt_start_delay+4) -> 9571544.1 | C18: EUR
A19: Contribution per m3, 3rd operating year | B19: =(INDEX(Revenue!$C$42:$M$42,1,opt_start_delay+4)-INDEX(Revenue!$C$27:$M$27,1,opt_start_delay+4)-INDEX(Revenue!$C$40:$M$40,1,opt_start_delay+4))/INDEX(Revenue!$C$8:$M$8,1,opt_start_delay+4)-(INDEX(Opex!$C$46:$M$46,1,opt_start_delay+4)-INDEX(Opex!$C$63:$M$63,1,opt_start_delay+4))/INDEX(Revenue!$C$8:$M$8,1,opt_start_delay+4) -> 27.526162 | C19: EUR/m3 | D19: concrete price - concrete variable costs (incl. bad debt, delivery)
A20: Break-even volume EBITDA = 0 (3rd-operating-year prices & fixed costs) | B20: =IF(Valuation!$B$19>0,(INDEX(Opex!$C$59:$M$59,1,opt_start_delay+4)-INDEX(Revenue!$C$27:$M$27,1,opt_start_delay+4)-INDEX(Opex!$C$65:$M$65,1,opt_start_delay+4))/Valuation!$B$19,"none") -> 50731.994 | C20: m3/yr | D20: (fixed costs - hook revenue - crusher net) / contribution per m3
A21: Capital recovery charge (10 yr annuity of initial capex at r) | B21: =Valuation!$B$15*(discount_rate_real/100)/(1-(1+discount_rate_real/100)^-10) -> 819662.19 | C21: EUR/yr | D21: memo
A22: Volume where EBITDA covers the capital charge (year-3 basis, pre-tax) | B22: =IF(Valuation!$B$19>0,(INDEX(Opex!$C$59:$M$59,1,opt_start_delay+4)-INDEX(Revenue!$C$27:$M$27,1,opt_start_delay+4)-INDEX(Opex!$C$65:$M$65,1,opt_start_delay+4)+Valuation!$B$21)/Valuation!$B$19,"none") -> 80509.563 | C22: m3/yr | D22: rough NPV break-even; exact Python value below
A24: Computed by model_core.py (base case, values - not live)
A25: NPV break-even steady-state volume (same ramp %) | B25: 111842.28 | C25: m3/yr
A26: NPV break-even plant-average price (2026 basis) | B26: 149.24081 | C26: EUR/m3
A27: NPV break-even public green premium (private 0%) | B27: 46.050735 | C27: % of price
A28: NPV break-even plant-equipment capex | B28: -0.42580152 | C28: MEUR (negative = impossible)
A29: NPV with 60k m3/yr steady state (market SOM) | B29: -5920016.2 | C29: EUR
A30: NPV at 6% discount rate | B30: -4189318.9 | C30: EUR
A31: NPV at 10% discount rate | B31: -4726018.2 | C31: EUR
A32: NPV without grant | B32: -4864033.2 | C32: EUR

Sheet Scenarios
A1: Scenarios - pessimistic / base / optimistic (values from model_core.py)
A2: Each input takes the column shown in Inputs!F (pessimistic) and Inputs!G (optimistic). Cost-type inputs: pessimistic = high column; revenue-type inputs: pessimistic = low column; 'fixed' inputs (discount rate, tax, lifetimes, recipes) stay at base. ALL inputs move together, so these are stress bounds, not likely cases. To see a scenario live, set Inputs!C3 to 1, 2 or 3.
A4: KPI | B4: Pessimistic | C4: Base | D4: Optimistic | E4: unit
A5: NPV @ 8% | B5: -38250548 | C5: -4481665.4 | D5: 29963057 | E5: EUR
A6: IRR | B6: n/a / not reached | C6: -0.070638263 | D6: 1.1937549 | E6: %
A7: Payback | B7: n/a / not reached | C7: n/a / not reached | D7: 1.1227018 | E7: yr
A8: Discounted payback | B8: n/a / not reached | C8: n/a / not reached | D8: 1.1901088 | E8: yr
A9: EBITDA year 3 (2029) | B9: -4109613.7 | C9: 530374.26 | D9: 6952848.4 | E9: EUR
A10: Funding need | B10: 53454569 | C10: 6835872.8 | D10: 2842680 | E10: EUR
A11: Initial capex | B11: 8000000 | C11: 5500000 | D11: 4000000 | E11: EUR
A12: NPV / capex | B12: -4.7813185 | C12: -0.81484825 | D12: 7.4907642 | E12: %
A13: Break-even volume (EBITDA=0, yr-3 basis) | B13: n/a / not reached | C13: 50731.994 | D13: 10070.447 | E13: m3/yr
A15: EBITDA by year | B15: 2026 | C15: 2027 | D15: 2028 | E15: 2029 | F15: 2030 | G15: 2031 | H15: 2032 | I15: 2033 | J15: 2034 | K15: 2035 | L15: 2036
A16: pessimistic | B16: -660000 | C16: -3029181.9 | D16: -3550774.1 | E16: -4109613.7 | F16: -4200402.1 | G16: -4514697.6 | H16: -4595896.7 | I16: -4680049 | J16: -4773795.3 | K16: -4809273.6 | L16: -4844759.9
A17: base | B17: -380000 | C17: -418885.84 | D17: 136864.45 | E17: 530374.26 | F17: 506811.9 | G17: 437358.64 | H17: 420465.72 | I17: 401457.04 | J17: 380332.5 | K17: 376377.81 | L17: 372403.35
A18: optimistic | B18: -240000 | C18: 4117667.8 | D18: 6103974 | E18: 6952848.4 | F18: 7026529.4 | G18: 7100584.2 | H18: 7175009.3 | I18: 7249805.3 | J18: 7324973.2 | K18: 7400524.5 | L18: 7476454.1
A20: Free cash flow by year | B20: 2026 | C20: 2027 | D20: 2028 | E20: 2029 | F20: 2030 | G20: 2031 | H20: 2032 | I20: 2033 | J20: 2034 | K20: 2035 | L20: 2036
A21: pessimistic | B21: -8660000 | C21: -3551703.9 | D21: -3963564.5 | E21: -4523269.9 | F21: -4350469.2 | G21: -4701092.2 | H21: -4744455.3 | I21: -4829111.2 | J21: -4924439.3 | K21: -4950476.5 | L21: -4255986.9
A22: base | B22: -5480000 | C22: -1084616.1 | D22: -271256.68 | E22: 218415.6 | F22: 450217.42 | G22: 365412.8 | H22: 366116.17 | I22: 346405.95 | J22: 324579.87 | K22: 309146.45 | L22: 1552946.7
A23: optimistic | B23: -2842680 | C23: 2319394.3 | D23: 4264694.7 | E23: 5072524.6 | F23: 5247830.6 | G23: 5303131.4 | H23: 5358494.8 | I23: 5414080.1 | J23: 5469914.8 | K23: 5526404.5 | L23: 7022909.8
A25: Volume by year | B25: 2026 | C25: 2027 | D25: 2028 | E25: 2029 | F25: 2030 | G25: 2031 | H25: 2032 | I25: 2033 | J25: 2034 | K25: 2035 | L25: 2036
A26: pessimistic | B26: 0 | C26: 17500 | D26: 30000 | E26: 42500 | F26: 42500 | G26: 42500 | H26: 42500 | I26: 42500 | J26: 42500 | K26: 42500 | L26: 42500
A27: base | B27: 0 | C27: 35000 | D27: 55300 | E27: 70000 | F27: 70000 | G27: 70000 | H27: 70000 | I27: 70000 | J27: 70000 | K27: 70000 | L27: 70000
A28: optimistic | B28: 0 | C28: 58500 | D28: 81000 | E28: 90000 | F28: 90000 | G28: 90000 | H28: 90000 | I28: 90000 | J28: 90000 | K28: 90000 | L28: 90000
A30: Plausible range (memo): base NPV +/- root-sum-square of the one-at-a-time NPV deviations of independent drivers
A31: NPV low (RSS) | B31: -15957355
A32: NPV high (RSS) | B32: 3479658.7
A33: Drivers in RSS: Average selling price (EUR 115-155/m3), Capex (plant, civil, permits), Cement price 2026 (EUR 95-130/t), Circular share of volume (40-80%), Concrete delivery distance (10-35 km), Delivery cost rates (fixed + per km), ETS/CBAM carbon cost path only, Grant DEI+/VEKI (EUR 0-1.5M), Gravel price (EUR 25-40/t), Green premium (public & private), Maintenance (1.5-4% of capex), Plant utilisation (50k-90k m3/yr), Production staff (FTE x cost), RCA haul distance (15-50 km), Ramp-up speed (yr1-3), Recycled aggregate price, ex-works (EUR 10-25/t), SG&A (staff + non-staff), Salvage value (10-40% of capex), Sand price (EUR 14-25/t), Site lease (area x rate), Working capital days

Sheet Sensitivity
A1: Sensitivity - one input group at a time to its low / high column, effect on NPV @ 8% (values from model_core.py)
A2: Base NPV = -4,481,665 EUR. Sorted by swing (tornado order).
A4: Rank | B4: Driver | C4: NPV at LOW input | D4: NPV at HIGH input | E4: Swing | F4: Pessimistic column | G4: NPV at pessimistic | H4: Main driver (crit. 4) | I4: Parameters moved
A5: 1 | B5: Average selling price (EUR 115-155/m3) | C5: -12772739 | D5: 1766053.7 | E5: 14538792 | F5: low | G5: -12772739 | I5: price_plant_avg_all_classes
A6: 2 | B6: Transport distance (delivery 10-35 km + RCA haul 15-50 km) | C6: -2410207.1 | D6: -8357077.5 | E6: 5946870.4 | F6: high | G6: -8357077.5 | H6: yes | I6: delivery_avg_distance_oneway, rca_transport_distance
A7: 3 | B7: Plant utilisation (50k-90k m3/yr) | C7: -7375999.3 | D7: -2293855.6 | E7: 5082143.7 | F7: low | G7: -7375999.3 | H7: yes | I7: output_steady_state
A8: 4 | B8: Gravel price (EUR 25-40/t) | C8: -2485489.4 | D8: -7391073.4 | E8: 4905584 | F8: high | G8: -7391073.4 | I8: price_gravel_delivered
A9: 5 | B9: Concrete delivery distance (10-35 km) | C9: -2814524.3 | D9: -7649248.8 | E9: 4834724.5 | F9: high | G9: -7649248.8 | I9: delivery_avg_distance_oneway
A10: 6 | B10: Cement price + ETS/CBAM path | C10: -2738425.5 | D10: -7461840.8 | E10: 4723415.3 | F10: high | G10: -7461840.8 | H10: yes | I10: price_cem3b_2026_delivered, carbon_cost_cem3b_2026, carbon_cost_cem3b_2027 ...
A11: 7 | B11: Cement price 2026 (EUR 95-130/t) | C11: -2879030.6 | D11: -7187864.2 | E11: 4308833.6 | F11: high | G11: -7187864.2 | I11: price_cem3b_2026_delivered
A12: 8 | B12: Capex (plant, civil, permits) | C12: -2947011.4 | D12: -7237858.5 | E12: 4290847.1 | F12: high | G12: -7237858.5 | H12: yes | I12: capex_plant_equipment, capex_site_prep_civil, capex_permits_engineering
A13: 9 | B13: SG&A (staff + non-staff) | C13: -3333465.7 | D13: -6639429.9 | E13: 3305964.2 | F13: high | G13: -6639429.9 | I13: staff_sga_fte, cost_per_fte_sga, sga_fixed_non_staff
A14: 10 | B14: Delivery cost rates (fixed + per km) | C14: -3134179.1 | D14: -6162814.9 | E14: 3028635.8 | F14: high | G14: -6162814.9 | I14: delivery_fixed_per_m3, delivery_variable_per_km_oneway
A15: 11 | B15: Sand price (EUR 14-25/t) | C15: -3414588.4 | D15: -6065748.5 | E15: 2651160.1 | F15: high | G15: -6065748.5 | I15: price_sand_delivered
A16: 12 | B16: Ramp-up speed (yr1-3) | C16: -6234273.2 | D16: -4108398.8 | E16: 2125874.4 | F16: low | G16: -6234273.2 | I16: ramp_year1_pct_of_steady, ramp_year2_pct_of_steady, ramp_year3plus_pct_of_steady
A17: 13 | B17: Production staff (FTE x cost) | C17: -3812491.9 | D17: -5921700.9 | E17: 2109209 | F17: high | G17: -5921700.9 | I17: staff_production_fte, cost_per_fte_production
A18: 14 | B18: Site lease (area x rate) | C18: -3978032.7 | D18: -5973801.6 | E18: 1995768.9 | F18: high | G18: -5973801.6 | I18: site_area, site_lease_rate
A19: 15 | B19: Recycled aggregate price, ex-works (EUR 10-25/t) | C19: -3900214.7 | D19: -5879690.6 | E19: 1979475.9 | F19: high | G19: -5879690.6 | H19: yes | I19: price_rca_coarse_exworks
A20: 16 | B20: Green premium (public & private) | C20: -5289068 | D20: -3442743.6 | E20: 1846324.3 | F20: low | G20: -5289068 | H20: yes | I20: green_premium_public, green_premium_private
A21: 17 | B21: Grant DEI+/VEKI (EUR 0-1.5M) | C21: -4864033.2 | D21: -3601181.4 | E21: 1262851.8 | F21: low | G21: -4864033.2 | I21: grant_dei_veki_first_plant
A22: 18 | B22: RCA haul distance (15-50 km) | C22: -4039138 | D22: -5171861.9 | E22: 1132723.9 | F22: high | G22: -5171861.9 | I22: rca_transport_distance
A23: 19 | B23: Maintenance (1.5-4% of capex) | C23: -4198300.8 | D23: -4967289.3 | E23: 768988.56 | F23: high | G23: -4967289.3 | I23: maintenance_pct_of_capex
A24: 20 | B24: Salvage value (10-40% of capex) | C24: -4829060.5 | D24: -4134270.3 | E24: 694790.23 | F24: low | G24: -4829060.5 | I24: salvage_value_yr10_pct_of_plant_civil_capex
A25: 21 | B25: Circular share of volume (40-80%) | C25: -4797744.3 | D25: -4201698.8 | E25: 596045.57 | F25: low | G25: -4797744.3 | I25: circular_share_of_volume
A26: 22 | B26: Discount rate (6-10%) | C26: -4189318.9 | D26: -4726018.2 | E26: 536699.33 | F26: high | G26: -4726018.2 | I26: discount_rate_real
A27: 23 | B27: Working capital days | C27: -4219118.2 | D27: -4680719.3 | E27: 461601.1 | F27: high | G27: -4680719.3 | I27: working_capital_receivable_days, working_capital_payable_days, working_capital_inventory_days
A28: 24 | B28: ETS/CBAM carbon cost path only | C28: -4326176.6 | D28: -4738009.8 | E28: 411833.17 | F28: high | G28: -4738009.8 | I28: carbon_cost_cem3b_2026, carbon_cost_cem3b_2027, carbon_cost_cem3b_2028 ...

Sheet Viability
A1: Viability gate - plan.md section 2.1 (criteria fixed before results)
A2: ="Criteria 1-3 are LIVE for the active scenario: "&Inputs!D3&". Criterion 4 is the base-case robustness test from model_core.py." -> Criteria 1-3 are LIVE for the active scenario: Base. Criterion 4 is the base-case robustness test from model_core.py.
A4: # | B4: Criterion | C4: Value | D4: Threshold | E4: Result
A5: 1 | B5: NPV > 0 at 8% real (10 yr, salvage-only terminal value) | C5: =Valuation!$B$5 -> -4481665.4 | D5: > 0 | E5: =IF(C5>0,"PASS","FAIL") -> FAIL
A6: 2 | B6: Payback period < 7 years | C6: =Valuation!$B$9 -> not reached | D6: < 7 | E6: =IF(ISNUMBER(C6),IF(C6<7,"PASS","FAIL"),"FAIL") -> FAIL
A7: 3 | B7: EBITDA positive by year 3 (2029) | C7: =Valuation!$B$11 -> 530374.26 | D7: > 0 | E7: =IF(C7>0,"PASS","FAIL") -> PASS
A8: 4 | B8: NPV > 0 with each of 6 main drivers at its pessimistic value (one at a time): at least 2 of 6 | C8: 0 | D8: >= 2 of 6 | E8: =IF(C8>=2,"PASS","FAIL") -> FAIL
B10: Borderline test: NPV between -10% and 0% of initial capex | C10: =Valuation!$B$16 -> -0.81484825 | E10: =IF(AND(C10>=-0.1,C10<=0),"YES","NO") -> NO
B12: VERDICT | C12: =IF(AND(E5="PASS",E6="PASS",E7="PASS",E8="PASS"),"VIABLE",IF(OR(AND(E5="PASS",E6="PASS",E7="PASS"),E10="YES"),"BORDERLINE","NOT VIABLE")) -> NOT VIABLE
B14: Criterion 4 detail (base case, model_core.py) | C14: NPV at pessimistic | D14: Pessimistic column | E14: NPV > 0?
B15: Green premium (public & private) | C15: -5289068 | D15: low | E15: FAIL
B16: Recycled aggregate price, ex-works (EUR 10-25/t) | C16: -5879690.6 | D16: high | E16: FAIL
B17: Transport distance (delivery 10-35 km + RCA haul 15-50 km) | C17: -8357077.5 | D17: high | E17: FAIL
B18: Cement price + ETS/CBAM path | C18: -7461840.8 | D18: high | E18: FAIL
B19: Plant utilisation (50k-90k m3/yr) | C19: -7375999.3 | D19: low | E19: FAIL
B20: Capex (plant, civil, permits) | C20: -7237858.5 | D20: high | E20: FAIL

Sheet Opt_Overview
A1: Viability options - live option selector (Agent 7)
A2: Set Inputs!I3 to an option number (1..N, row 5) and the WHOLE model recalculates live with that option's values (blank cell = parameter keeps its scenario/base value). 0 = base case. Option O6 (asset-light) is a separate model: sheet Opt_AssetLight. Results table below: values from model/options.py (grey) - see research/viability_options.md.
A3: Active option number (Inputs!I3) | B3: =option_sel -> 0 | C3: =IF(option_sel=0,"none (base case)",INDEX($C$6:$M$6,1,option_sel)) -> none (base case) | E3: Live NPV of active option | G3: =Valuation!$B$5 -> -4481665.4
A5: parameter | B5: base value | C5: 1 | D5: 2 | E5: 3 | F5: 4 | G5: 5 | H5: 6 | I5: 7 | J5: 8 | K5: 9 | L5: 10 | M5: 11
A6: option | C6: O0 Corrected base: first sales 2028 | D6: O1 A+B own mobile crushing line | E6: O2 A+B with demolition partner (contract crushing) | F6: O3 Acquire and convert an existing plant | G6: O4 Offtake / framework contracts (MKI tenders) | H6: O5 Lower-CO2 binder product (from 2029) | I6: O7 Maximum realistic subsidies | J6: O8 Bigger plant: 100k m3/yr | K6: O9 Urban site closer to demand (truck-fed) | L6: P1 Package 1: acquire + partner crushing + frameworks | M6: P2 Package 2: P1 + scale to 90k m3/yr
A7: opt_start_delay | B7: 0 | C7: 1 | D7: 1 | E7: 1 | G7: 1 | H7: 1 | I7: 1 | J7: 1 | K7: 1
A8: opt_crusher_on | B8: 0 | D8: 1 | E8: 1 | L8: 1 | M8: 1
A9: opt_crusher_start_year | B9: 0 | D9: 2029 | E9: 2029 | L9: 2029 | M9: 2029
A10: opt_rubble_intake_tpy | B10: 0 | D10: 40500 | E10: 40500 | L10: 40500 | M10: 40500
A11: opt_crusher_capex | B11: 0 | D11: 2000000 | E11: 400000 | L11: 400000 | M11: 400000
A12: opt_crusher_salvage_pct | B12: 0 | D12: 10 | E12: 10 | L12: 10 | M12: 10
A13: opt_crusher_mia_share_pct | B13: 0 | D13: 100 | E13: 0 | L13: 0 | M13: 0
A14: opt_crusher_contract_rate | B14: 0 | E14: 7.5 | L14: 7.5 | M14: 7.5
A15: hybrid_crusher_diesel | B15: 0.3 | E15: 0 | L15: 0 | M15: 0
A16: hybrid_crusher_wear | B16: 0.4 | E16: 0 | L16: 0 | M16: 0
A17: hybrid_crusher_staff_fte | B17: 3 | E17: 1 | L17: 1 | M17: 1
A18: capex_plant_equipment | B18: 4 | F18: 3.3 | L18: 3.3 | M18: 3.3
A19: capex_site_prep_civil | B19: 1 | F19: 0.2 | L19: 0.2 | M19: 0.2
A20: capex_permits_engineering | B20: 0.5 | F20: 0.2 | L20: 0.2 | M20: 0.2
A21: capex_preopening_costs | B21: 300000 | F21: 100000 | L21: 100000 | M21: 100000
A22: ramp_year1_pct_of_steady | B22: 50 | F22: 55 | G22: 75 | L22: 75 | M22: 75
A23: ramp_year2_pct_of_steady | B23: 79 | F23: 85 | G23: 95 | L23: 95 | M23: 95
A24: maintenance_pct_of_capex | B24: 2.5 | F24: 3.5 | L24: 3.5 | M24: 3.5
A25: salvage_value_yr10_pct_of_plant_civil_capex | B25: 25 | F25: 15 | L25: 15 | M25: 15
A26: opt_price_delta_per_m3 | B26: 0 | G26: -1 | L26: -1 | M26: -1
A27: opt_circ_price_delta_per_m3 | B27: 0 | H27: 1.5
A28: opt_circ_cost_delta_per_m3 | B28: 0 | H28: 1.5
A29: opt_circ_delta_start_year | B29: 0 | H29: 2029
A30: opt_extra_capex_y0 | B30: 0 | H30: 150000
A31: opt_extra_opex_per_yr | B31: 0 | H31: 40000
A32: grant_dei_veki_first_plant | B32: 0.4 | I32: 1
A33: mia_eligible_share_of_capex | B33: 20 | I33: 50
A34: output_steady_state | B34: 70000 | J34: 100000 | M34: 90000
A35: staff_production_fte | B35: 7 | J35: 9 | M35: 8
A36: delivery_avg_distance_oneway | B36: 20 | J36: 23 | K36: 15 | M36: 22
A37: site_lease_rate | B37: 10 | K37: 15
A38: price_gravel_delivered | B38: 32 | K38: 37
A41: Results per option (values from model/options.py; criterion 4 = option-relative stress test)
A42: option | B42: NPV @ 8% | C42: IRR | D42: payback (yr) | E42: EBITDA 3rd op. year | F42: funding need | G42: initial capex | H42: criteria passed | I42: crit. 4 (of 6) | J42: verdict | K42: feasibility 1-5
A43: BASE Base case as gated (sales 2027) | B43: -4481665.4 | C43: -0.070638263 | D43: not reached | E43: 530374.26 | F43: 6835872.8 | G43: 5500000 | H43: 1/4 | I43: 0 | J43: NOT VIABLE
A44: O0 Corrected base: first sales 2028 | B44: -4383366.2 | C44: -0.089960929 | D44: not reached | E44: 506811.9 | F44: 6855141.8 | G44: 5500000 | H44: 1/4 | I44: 0 | J44: NOT VIABLE | K44: 5
A45: O1 A+B own mobile crushing line | B45: -3872697.2 | C45: -0.033990852 | D45: not reached | E45: 1028218.2 | F45: 8581964.2 | G45: 7500000 | H45: 1/4 | I45: 0 | J45: NOT VIABLE | K45: 3
A46: O2 A+B with demolition partner (contract crushing) | B46: -3087304.6 | C46: -0.025678765 | D46: not reached | E46: 950321.77 | F46: 7004140.5 | G46: 5900000 | H46: 1/4 | I46: 0 | J46: NOT VIABLE | K46: 3
A47: O3 Acquire and convert an existing plant | B47: -2705789.6 | C47: -0.056678846 | D47: not reached | E47: 532874.26 | F47: 4661681.4 | G47: 3700000 | H47: 1/4 | I47: 0 | J47: NOT VIABLE | K47: 3
A48: O4 Offtake / framework contracts (MKI tenders) | B48: -4142336.4 | C48: -0.091577111 | D48: not reached | E48: 436660.42 | F48: 6439041.5 | G48: 5500000 | H48: 1/4 | I48: 0 | J48: NOT VIABLE | K48: 3
A49: O5 Lower-CO2 binder product (from 2029) | B49: -4763214 | C49: -0.10350642 | D49: not reached | E49: 466496.9 | F49: 7093572 | G49: 5650000 | H49: 1/4 | I49: 0 | J49: NOT VIABLE | K49: 2
A50: O6 Asset-light: licence + RCA service (archetype D) | B50: -2512811.2 | C50: n/a | D50: not reached | E50: -282200 | F50: 3346049.3 | G50: 200000 | H50: 0/4 | I50: 0 | J50: NOT VIABLE | K50: 2
A51: O7 Maximum realistic subsidies | B51: -3827810.7 | C51: -0.078648099 | D51: not reached | E51: 506811.9 | F51: 6255141.8 | G51: 5500000 | H51: 1/4 | I51: 0 | J51: NOT VIABLE | K51: 2
A52: O8 Bigger plant: 100k m3/yr | B52: -2850494 | C52: -0.019747159 | D52: not reached | E52: 1031330.7 | F52: 6683326.8 | G52: 5500000 | H52: 1/4 | I52: 0 | J52: NOT VIABLE | K52: 2
A53: O9 Urban site closer to demand (truck-fed) | B53: -5472675.5 | C53: -0.1458657 | D53: not reached | E53: 302871.9 | F53: 7168062.8 | G53: 5500000 | H53: 1/4 | I53: 0 | J53: NOT VIABLE | K53: 3
A54: P1 Package 1: acquire + partner crushing + frameworks | B54: -1358150 | C54: 0.021135375 | D54: 9.8021415 | E54: 906587.92 | F54: 4719595 | G54: 4100000 | H54: 1/4 | I54: 0 | J54: NOT VIABLE | K54: 3
A55: P2 Package 2: P1 + scale to 90k m3/yr | B55: 414.27654 | C55: 0.080016521 | D55: 7.2803217 | E55: 1276012.6 | F55: 4579629.1 | G55: 4100000 | H55: 2/4 | I55: 0 | J55: NOT VIABLE | K55: 2
A57: Policy dependence (values from model/options.py)
A58: case | B58: levy on gravel+sand for NPV=0 (EUR/t) | C58: public green premium for NPV=0 (%) | D58: MKI value on circular m3 for NPV=0 (EUR/m3) | E58: NPV high ETS path | F58: NPV gate fee 15 | G58: price for NPV=0 (EUR/m3) | H58: volume for NPV=0 (m3/yr)
A59: O0 | B59: none in range | C59: 51.950356 | D59: 27.315285 | E59: -4649664.7 | F59: -4383366.2 | G59: 151.27201 | H59: 118706.78
A60: P1 | B60: none in range | C60: 15.621456 | D60: 7.8367325 | E60: -1568819.1 | F60: 62155.214 | G60: 139.13951 | H60: 82605.599
A61: P2 | B61: 0.036638785 | C61: 2.997003 | D61: none in range | E61: -269745.23 | F61: 1420719.5 | G61: 134.99902 | H61: 89995.971

Sheet Opt_AssetLight
A1: Option O6 - asset-light licence + RCA service (archetype D), EUR real 2026
A2: Separate small model (no plant). Inputs in column P (blue). Same tax and discounting rules as the plant model.
A3: Year | B3: unit | C3: =2026+C4 -> 2026 | D3: =2026+D4 -> 2027 | E3: =2026+E4 -> 2028 | F3: =2026+F4 -> 2029 | G3: =2026+G4 -> 2030 | H3: =2026+H4 -> 2031 | I3: =2026+I4 -> 2032 | J3: =2026+J4 -> 2033 | ... M3: =2026+M4 -> 2036
A4: t (year index) | C4: 0 | D4: 1 | E4: 2 | F4: 3 | G4: 4 | H4: 5 | I4: 6 | J4: 7 | K4: 8 | L4: 9 | M4: 10
O5: input | Q5: value | R5: unit | S5: low | T5: high | U5: ID
A6: Licensee plants | B6: plants | C6: =IF(C$4=0,0,MIN(al_licensees_max,C$4)) -> 0 | D6: =IF(D$4=0,0,MIN(al_licensees_max,D$4)) -> 1 | E6: =IF(E$4=0,0,MIN(al_licensees_max,E$4)) -> 2 | F6: =IF(F$4=0,0,MIN(al_licensees_max,F$4)) -> 3 | G6: =IF(G$4=0,0,MIN(al_licensees_max,G$4)) -> 4 | H6: =IF(H$4=0,0,MIN(al_licensees_max,H$4)) -> 4 | I6: =IF(I$4=0,0,MIN(al_licensees_max,I$4)) -> 4 | J6: =IF(J$4=0,0,MIN(al_licensees_max,J$4)) -> 4 | ... M6: =IF(M$4=0,0,MIN(al_licensees_max,M$4)) -> 4 | O6: Licensee plants at maturity (+1 per year from 2027) | Q6: 4 | R6: plants | S6: 2 | T6: 8 | U6: A-OPT-19
A7: Circular volume at licensees | B7: m3 | C7: =C6*al_circ_volume_per_licensee -> 0 | D7: =D6*al_circ_volume_per_licensee -> 15000 | E7: =E6*al_circ_volume_per_licensee -> 30000 | F7: =F6*al_circ_volume_per_licensee -> 45000 | G7: =G6*al_circ_volume_per_licensee -> 60000 | H7: =H6*al_circ_volume_per_licensee -> 60000 | I7: =I6*al_circ_volume_per_licensee -> 60000 | J7: =J6*al_circ_volume_per_licensee -> 60000 | ... M7: =M6*al_circ_volume_per_licensee -> 60000 | O7: Circular volume per licensee plant | Q7: 15000 | R7: m3/yr | S7: 8000 | T7: 25000 | U7: A-OPT-19
A8: Licence / service fees | B8: EUR | C8: =C7*al_fee_per_m3 -> 0 | D8: =D7*al_fee_per_m3 -> 30000 | E8: =E7*al_fee_per_m3 -> 60000 | F8: =F7*al_fee_per_m3 -> 90000 | G8: =G7*al_fee_per_m3 -> 120000 | H8: =H7*al_fee_per_m3 -> 120000 | I8: =I7*al_fee_per_m3 -> 120000 | J8: =J7*al_fee_per_m3 -> 120000 | ... M8: =M7*al_fee_per_m3 -> 120000 | O8: Licence / service fee | Q8: 2 | R8: EUR/m3 | S8: 1 | T8: 3.5 | U8: A-OPT-20
A9: RCA brokerage margin | B9: EUR | C9: =C7*al_rca_t_per_m3*al_rca_margin_per_t -> 0 | D9: =D7*al_rca_t_per_m3*al_rca_margin_per_t -> 12600 | E9: =E7*al_rca_t_per_m3*al_rca_margin_per_t -> 25200 | F9: =F7*al_rca_t_per_m3*al_rca_margin_per_t -> 37800 | G9: =G7*al_rca_t_per_m3*al_rca_margin_per_t -> 50400 | H9: =H7*al_rca_t_per_m3*al_rca_margin_per_t -> 50400 | I9: =I7*al_rca_t_per_m3*al_rca_margin_per_t -> 50400 | J9: =J7*al_rca_t_per_m3*al_rca_margin_per_t -> 50400 | ... M9: =M7*al_rca_t_per_m3*al_rca_margin_per_t -> 50400 | O9: RCA supplied per m3 | Q9: 0.56 | R9: t/m3 | S9: 0.33 | T9: 0.56 | U9: inputs mix_circ_rca_coarse
A10: LCA/EPD/MKI services | B10: EUR | C10: =IF(C$4>=2,al_services_rev,0) -> 0 | D10: =IF(D$4>=2,al_services_rev,0) -> 0 | E10: =IF(E$4>=2,al_services_rev,0) -> 100000 | F10: =IF(F$4>=2,al_services_rev,0) -> 100000 | G10: =IF(G$4>=2,al_services_rev,0) -> 100000 | H10: =IF(H$4>=2,al_services_rev,0) -> 100000 | I10: =IF(I$4>=2,al_services_rev,0) -> 100000 | J10: =IF(J$4>=2,al_services_rev,0) -> 100000 | ... M10: =IF(M$4>=2,al_services_rev,0) -> 100000 | O10: Brokerage margin on RCA | Q10: 1.5 | R10: EUR/t | S10: 0.5 | T10: 3 | U10: A-OPT-21
A11: Revenue | B11: EUR | C11: =C8+C9+C10 -> 0 | D11: =D8+D9+D10 -> 42600 | E11: =E8+E9+E10 -> 185200 | F11: =F8+F9+F10 -> 227800 | G11: =G8+G9+G10 -> 270400 | H11: =H8+H9+H10 -> 270400 | I11: =I8+I9+I10 -> 270400 | J11: =J8+J9+J10 -> 270400 | ... M11: =M8+M9+M10 -> 270400 | O11: LCA/EPD/MKI project services (from 2028) | Q11: 100000 | R11: EUR/yr | S11: 0 | T11: 200000 | U11: A-OPT-22
A12: Staff | B12: EUR | C12: =IF(C$4>=1,al_fte*al_cost_per_fte,0) -> 0 | D12: =IF(D$4>=1,al_fte*al_cost_per_fte,0) -> 360000 | E12: =IF(E$4>=1,al_fte*al_cost_per_fte,0) -> 360000 | F12: =IF(F$4>=1,al_fte*al_cost_per_fte,0) -> 360000 | G12: =IF(G$4>=1,al_fte*al_cost_per_fte,0) -> 360000 | H12: =IF(H$4>=1,al_fte*al_cost_per_fte,0) -> 360000 | I12: =IF(I$4>=1,al_fte*al_cost_per_fte,0) -> 360000 | J12: =IF(J$4>=1,al_fte*al_cost_per_fte,0) -> 360000 | ... M12: =IF(M$4>=1,al_fte*al_cost_per_fte,0) -> 360000 | O12: Team (technologist, LCA, sales, logistics) | Q12: 4 | R12: FTE | S12: 3 | T12: 5 | U12: A-OPT-23
A13: Other overhead | B13: EUR | C13: =IF(C$4>=1,al_overhead,0) -> 0 | D13: =IF(D$4>=1,al_overhead,0) -> 150000 | E13: =IF(E$4>=1,al_overhead,0) -> 150000 | F13: =IF(F$4>=1,al_overhead,0) -> 150000 | G13: =IF(G$4>=1,al_overhead,0) -> 150000 | H13: =IF(H$4>=1,al_overhead,0) -> 150000 | I13: =IF(I$4>=1,al_overhead,0) -> 150000 | J13: =IF(J$4>=1,al_overhead,0) -> 150000 | ... M13: =IF(M$4>=1,al_overhead,0) -> 150000 | O13: Cost per FTE | Q13: 90000 | R13: EUR/yr | S13: 80000 | T13: 110000 | U13: inputs cost_per_fte_sga
A14: Start-up costs (expensed) | B14: EUR | C14: =IF(C$4=0,al_startup_t0,0) -> 350000 | D14: =IF(D$4=0,al_startup_t0,0) -> 0 | E14: =IF(E$4=0,al_startup_t0,0) -> 0 | F14: =IF(F$4=0,al_startup_t0,0) -> 0 | G14: =IF(G$4=0,al_startup_t0,0) -> 0 | H14: =IF(H$4=0,al_startup_t0,0) -> 0 | I14: =IF(I$4=0,al_startup_t0,0) -> 0 | J14: =IF(J$4=0,al_startup_t0,0) -> 0 | ... M14: =IF(M$4=0,al_startup_t0,0) -> 0 | O14: Other overhead (office, IT, insurance, LCA software) | Q14: 150000 | R14: EUR/yr | S14: 100000 | T14: 200000 | U14: A-OPT-23
A15: EBITDA | B15: EUR | C15: =C11-C12-C13-C14 -> -350000 | D15: =D11-D12-D13-D14 -> -467400 | E15: =E11-E12-E13-E14 -> -324800 | F15: =F11-F12-F13-F14 -> -282200 | G15: =G11-G12-G13-G14 -> -239600 | H15: =H11-H12-H13-H14 -> -239600 | I15: =I11-I12-I13-I14 -> -239600 | J15: =J11-J12-J13-J14 -> -239600 | ... M15: =M11-M12-M13-M14 -> -239600 | O15: Mix development, trial mixes, EPDs, contracts (2026, expensed) | Q15: 350000 | R15: EUR | S15: 250000 | T15: 500000 | U15: A-OPT-23
A16: Depreciation | B16: EUR | C16: =IF(AND(C$4>=1,C$4<=al_capex_life),al_capex_t0/al_capex_life,0) -> 0 | D16: =IF(AND(D$4>=1,D$4<=al_capex_life),al_capex_t0/al_capex_life,0) -> 40000 | E16: =IF(AND(E$4>=1,E$4<=al_capex_life),al_capex_t0/al_capex_life,0) -> 40000 | F16: =IF(AND(F$4>=1,F$4<=al_capex_life),al_capex_t0/al_capex_life,0) -> 40000 | G16: =IF(AND(G$4>=1,G$4<=al_capex_life),al_capex_t0/al_capex_life,0) -> 40000 | H16: =IF(AND(H$4>=1,H$4<=al_capex_life),al_capex_t0/al_capex_life,0) -> 40000 | I16: =IF(AND(I$4>=1,I$4<=al_capex_life),al_capex_t0/al_capex_life,0) -> 0 | J16: =IF(AND(J$4>=1,J$4<=al_capex_life),al_capex_t0/al_capex_life,0) -> 0 | ... M16: =IF(AND(M$4>=1,M$4<=al_capex_life),al_capex_t0/al_capex_life,0) -> 0 | O16: Lab equipment, software (2026) | Q16: 200000 | R16: EUR | S16: 100000 | T16: 300000 | U16: A-OPT-23
A17: EBIT | B17: EUR | C17: =C15-C16 -> -350000 | D17: =D15-D16 -> -507400 | E17: =E15-E16 -> -364800 | F17: =F15-F16 -> -322200 | G17: =G15-G16 -> -279600 | H17: =H15-H16 -> -279600 | I17: =I15-I16 -> -239600 | J17: =J15-J16 -> -239600 | ... M17: =M15-M16 -> -239600 | O17: Depreciation life | Q17: 5 | R17: yr | S17: 5 | T17: 5 | U17: ASSUMPTION
A18: Taxable profit after loss offset | B18: EUR | C18: =MAX(0,C17) -> 0 | D18: =MAX(0,D17-C19) -> 0 | E18: =MAX(0,E17-D19) -> 0 | F18: =MAX(0,F17-E19) -> 0 | G18: =MAX(0,G17-F19) -> 0 | H18: =MAX(0,H17-G19) -> 0 | I18: =MAX(0,I17-H19) -> 0 | J18: =MAX(0,J17-I19) -> 0 | K18: =MAX(0,K17-J19) -> 0 | ... M18: =MAX(0,M17-L19) -> 0 | O18: Receivable days | Q18: 60 | R18: d | S18: 45 | T18: 75 | U18: inputs working_capital_receivable_days
A19: Tax-loss pool (end of year) | B19: EUR | C19: =MAX(0,-C17) -> 350000 | D19: =MAX(0,C19-D17) -> 857400 | E19: =MAX(0,D19-E17) -> 1222200 | F19: =MAX(0,E19-F17) -> 1544400 | G19: =MAX(0,F19-G17) -> 1824000 | H19: =MAX(0,G19-H17) -> 2103600 | I19: =MAX(0,H19-I17) -> 2343200 | J19: =MAX(0,I19-J17) -> 2582800 | K19: =MAX(0,J19-K17) -> 2822400 | ... M19: =MAX(0,L19-M17) -> 3301600
A20: Corporate income tax | B20: EUR | C20: =MIN(C18,tax_vpb_low_bracket_limit)*tax_rate_vpb_low_bracket/100+MAX(0,C18-tax_vpb_low_bracket_limit)*tax_rate_vpb_high_bracket/100 -> 0 | D20: =MIN(D18,tax_vpb_low_bracket_limit)*tax_rate_vpb_low_bracket/100+MAX(0,D18-tax_vpb_low_bracket_limit)*tax_rate_vpb_high_bracket/100 -> 0 | E20: =MIN(E18,tax_vpb_low_bracket_limit)*tax_rate_vpb_low_bracket/100+MAX(0,E18-tax_vpb_low_bracket_limit)*tax_rate_vpb_high_bracket/100 -> 0 | F20: =MIN(F18,tax_vpb_low_bracket_limit)*tax_rate_vpb_low_bracket/100+MAX(0,F18-tax_vpb_low_bracket_limit)*tax_rate_vpb_high_bracket/100 -> 0 | G20: =MIN(G18,tax_vpb_low_bracket_limit)*tax_rate_vpb_low_bracket/100+MAX(0,G18-tax_vpb_low_bracket_limit)*tax_rate_vpb_high_bracket/100 -> 0 | H20: =MIN(H18,tax_vpb_low_bracket_limit)*tax_rate_vpb_low_bracket/100+MAX(0,H18-tax_vpb_low_bracket_limit)*tax_rate_vpb_high_bracket/100 -> 0 | I20: =MIN(I18,tax_vpb_low_bracket_limit)*tax_rate_vpb_low_bracket/100+MAX(0,I18-tax_vpb_low_bracket_limit)*tax_rate_vpb_high_bracket/100 -> 0 | J20: =MIN(J18,tax_vpb_low_bracket_limit)*tax_rate_vpb_low_bracket/100+MAX(0,J18-tax_vpb_low_bracket_limit)*tax_rate_vpb_high_bracket/100 -> 0 | ... M20: =MIN(M18,tax_vpb_low_bracket_limit)*tax_rate_vpb_low_bracket/100+MAX(0,M18-tax_vpb_low_bracket_limit)*tax_rate_vpb_high_bracket/100 -> 0
A21: Receivables | B21: EUR | C21: =C11*al_receivable_days/365 -> 0 | D21: =D11*al_receivable_days/365 -> 7002.7397 | E21: =E11*al_receivable_days/365 -> 30443.836 | F21: =F11*al_receivable_days/365 -> 37446.575 | G21: =G11*al_receivable_days/365 -> 44449.315 | H21: =H11*al_receivable_days/365 -> 44449.315 | I21: =I11*al_receivable_days/365 -> 44449.315 | J21: =J11*al_receivable_days/365 -> 44449.315 | ... M21: =M11*al_receivable_days/365 -> 44449.315
A22: Change in working capital (cash out = negative) | B22: EUR | C22: =-C21 -> 0 | D22: =-(D21-C21) -> -7002.7397 | E22: =-(E21-D21) -> -23441.096 | F22: =-(F21-E21) -> -7002.7397 | G22: =-(G21-F21) -> -7002.7397 | H22: =-(H21-G21) -> 0 | I22: =-(I21-H21) -> 0 | J22: =-(J21-I21) -> 0 | K22: =-(K21-J21) -> 0 | ... M22: =-(M21-L21) -> 0
A23: Capex | B23: EUR | C23: =IF(C$4=0,-al_capex_t0,0) -> -200000 | D23: =IF(D$4=0,-al_capex_t0,0) -> 0 | E23: =IF(E$4=0,-al_capex_t0,0) -> 0 | F23: =IF(F$4=0,-al_capex_t0,0) -> 0 | G23: =IF(G$4=0,-al_capex_t0,0) -> 0 | H23: =IF(H$4=0,-al_capex_t0,0) -> 0 | I23: =IF(I$4=0,-al_capex_t0,0) -> 0 | J23: =IF(J$4=0,-al_capex_t0,0) -> 0 | ... M23: =IF(M$4=0,-al_capex_t0,0) -> 0
A24: FREE CASH FLOW | B24: EUR | C24: =C15-C20+C22+C23 -> -550000 | D24: =D15-D20+D22+D23 -> -474402.74 | E24: =E15-E20+E22+E23 -> -348241.1 | F24: =F15-F20+F22+F23 -> -289202.74 | G24: =G15-G20+G22+G23 -> -246602.74 | H24: =H15-H20+H22+H23 -> -239600 | I24: =I15-I20+I22+I23 -> -239600 | J24: =J15-J20+J22+J23 -> -239600 | ... M24: =M15-M20+M22+M23 -> -239600
A25: Cumulative FCF | B25: EUR | C25: =SUM($C$24:C24) -> -550000 | D25: =SUM($C$24:D24) -> -1024402.7 | E25: =SUM($C$24:E24) -> -1372643.8 | F25: =SUM($C$24:F24) -> -1661846.6 | G25: =SUM($C$24:G24) -> -1908449.3 | H25: =SUM($C$24:H24) -> -2148049.3 | I25: =SUM($C$24:I24) -> -2387649.3 | J25: =SUM($C$24:J24) -> -2627249.3 | ... M25: =SUM($C$24:M24) -> -3346049.3
A26: Discount factor | B26: x | C26: =1/(1+discount_rate_real/100)^C$4 -> 1 | D26: =1/(1+discount_rate_real/100)^D$4 -> 0.92592593 | E26: =1/(1+discount_rate_real/100)^E$4 -> 0.85733882 | F26: =1/(1+discount_rate_real/100)^F$4 -> 0.79383224 | G26: =1/(1+discount_rate_real/100)^G$4 -> 0.73502985 | H26: =1/(1+discount_rate_real/100)^H$4 -> 0.6805832 | I26: =1/(1+discount_rate_real/100)^I$4 -> 0.63016963 | J26: =1/(1+discount_rate_real/100)^J$4 -> 0.5834904 | ... M26: =1/(1+discount_rate_real/100)^M$4 -> 0.46319349
A27: Payback crossing (year) | B27: yr | D27: =IF(AND(C25<0,D25>=0),D$4-1+(-C25)/(D25-C25),"") | E27: =IF(AND(D25<0,E25>=0),E$4-1+(-D25)/(E25-D25),"") | F27: =IF(AND(E25<0,F25>=0),F$4-1+(-E25)/(F25-E25),"") | G27: =IF(AND(F25<0,G25>=0),G$4-1+(-F25)/(G25-F25),"") | H27: =IF(AND(G25<0,H25>=0),H$4-1+(-G25)/(H25-G25),"") | I27: =IF(AND(H25<0,I25>=0),I$4-1+(-H25)/(I25-H25),"") | J27: =IF(AND(I25<0,J25>=0),J$4-1+(-I25)/(J25-I25),"") | K27: =IF(AND(J25<0,K25>=0),K$4-1+(-J25)/(K25-J25),"") | ... M27: =IF(AND(L25<0,M25>=0),M$4-1+(-L25)/(M25-L25),"")
A29: NPV @ discount rate | C29: =SUMPRODUCT(Opt_AssetLight!$C$24:$M$24,Opt_AssetLight!$C$26:$M$26) -> -2512811.2
A30: IRR | C30: =IFERROR(IRR(Opt_AssetLight!$C$24:$M$24,0.1),IFERROR(IRR(Opt_AssetLight!$C$24:$M$24,-0.1),"n/a")) -> n/a
A31: Payback (years from 2026) | C31: =IF(COUNT(Opt_AssetLight!$D$27:$M$27)=0,"not reached",MIN(Opt_AssetLight!$D$27:$M$27)) -> not reached
A32: EBITDA 2029 | C32: =Opt_AssetLight!$F$15 -> -282200
A33: Funding need | C33: =MAX(0,-MIN(Opt_AssetLight!$C$25:$M$25)) -> 3346049.3
